Workbook

Sheet Summary
A1: R1 Education Account Test Cases v2.2: Summary (Tender requirement R1, MOE Finance System, baseline FS R1 V1.0 and F03 of the first FS)
A2: Scope: functional and integration cases only. Performance and security are excluded. All counts are formulas over TestCases, Scenarios, Checkpoint, Assumptions and Questions. No test case has been executed.
A4: Test cases by Status
A5: Status | B5: Count | C5: Percent | D5: Meaning
A6: Approve | B6: =COUNTIF(TestCases!$V$2:$V$158,A6) -> 93 | C6: =B6/B10 -> 0.59235669 | D6: The expected result is stated by the FS ([CR], [TD] or an untagged criterion), the tender or a client answer, or the open assumption was resolved. Assumption Ref is N/A.
A7: Draft | B7: =COUNTIF(TestCases!$V$2:$V$158,A7) -> 40 | C7: =B7/B10 -> 0.25477707 | D7: The expected result rests on an open assumption (FS tag [WA] or an inference). Assumption Ref names it and its source. Each open assumption is a question in Questions.
A8: Block | B8: =COUNTIF(TestCases!$V$2:$V$158,A8) -> 15 | C8: =B8/B10 -> 0.095541401 | D8: Information exists but no assumption can settle it: the FS defers the feature ([Deferred]) or two sources conflict. Dependency Ref lists the blocking questions.
A9: Reject | B9: =COUNTIF(TestCases!$V$2:$V$158,A9) -> 9 | C9: =B9/B10 -> 0.057324841 | D9: No testable expectation exists in the sources. Steps are not written.
A10: Total | B10: =SUM(B6:B9) -> 157 | C10: =SUM(C6:C9) -> 1
A12: Status by Priority
A13: Priority | B13: Approve | C13: Draft | D13: Block | E13: Reject | F13: Total
A14: Critical | B14: =COUNTIFS(TestCases!$H$2:$H$158,$A14,TestCases!$V$2:$V$158,"Approve") -> 18 | C14: =COUNTIFS(TestCases!$H$2:$H$158,$A14,TestCases!$V$2:$V$158,"Draft") -> 12 | D14: =COUNTIFS(TestCases!$H$2:$H$158,$A14,TestCases!$V$2:$V$158,"Block") -> 1 | E14: =COUNTIFS(TestCases!$H$2:$H$158,$A14,TestCases!$V$2:$V$158,"Reject") -> 2 | F14: =SUM(B14:E14) -> 33
A15: High | B15: =COUNTIFS(TestCases!$H$2:$H$158,$A15,TestCases!$V$2:$V$158,"Approve") -> 50 | C15: =COUNTIFS(TestCases!$H$2:$H$158,$A15,TestCases!$V$2:$V$158,"Draft") -> 18 | D15: =COUNTIFS(TestCases!$H$2:$H$158,$A15,TestCases!$V$2:$V$158,"Block") -> 11 | E15: =COUNTIFS(TestCases!$H$2:$H$158,$A15,TestCases!$V$2:$V$158,"Reject") -> 1 | F15: =SUM(B15:E15) -> 80
A16: Medium | B16: =COUNTIFS(TestCases!$H$2:$H$158,$A16,TestCases!$V$2:$V$158,"Approve") -> 22 | C16: =COUNTIFS(TestCases!$H$2:$H$158,$A16,TestCases!$V$2:$V$158,"Draft") -> 10 | D16: =COUNTIFS(TestCases!$H$2:$H$158,$A16,TestCases!$V$2:$V$158,"Block") -> 3 | E16: =COUNTIFS(TestCases!$H$2:$H$158,$A16,TestCases!$V$2:$V$158,"Reject") -> 5 | F16: =SUM(B16:E16) -> 40
A17: Low | B17: =COUNTIFS(TestCases!$H$2:$H$158,$A17,TestCases!$V$2:$V$158,"Approve") -> 3 | C17: =COUNTIFS(TestCases!$H$2:$H$158,$A17,TestCases!$V$2:$V$158,"Draft") -> 0 | D17: =COUNTIFS(TestCases!$H$2:$H$158,$A17,TestCases!$V$2:$V$158,"Block") -> 0 | E17: =COUNTIFS(TestCases!$H$2:$H$158,$A17,TestCases!$V$2:$V$158,"Reject") -> 1 | F17: =SUM(B17:E17) -> 4
A18: Total | B18: =SUM(B14:B17) -> 93 | C18: =SUM(C14:C17) -> 40 | D18: =SUM(D14:D17) -> 15 | E18: =SUM(E14:E17) -> 9 | F18: =SUM(F14:F17) -> 157
A20: Status by Severity (1 is the most severe)
A21: Severity | B21: Approve | C21: Draft | D21: Block | E21: Reject | F21: Total
A22: 1 | B22: =COUNTIFS(TestCases!$I$2:$I$158,$A22,TestCases!$V$2:$V$158,"Approve") -> 18 | C22: =COUNTIFS(TestCases!$I$2:$I$158,$A22,TestCases!$V$2:$V$158,"Draft") -> 12 | D22: =COUNTIFS(TestCases!$I$2:$I$158,$A22,TestCases!$V$2:$V$158,"Block") -> 2 | E22: =COUNTIFS(TestCases!$I$2:$I$158,$A22,TestCases!$V$2:$V$158,"Reject") -> 2 | F22: =SUM(B22:E22) -> 34
A23: 2 | B23: =COUNTIFS(TestCases!$I$2:$I$158,$A23,TestCases!$V$2:$V$158,"Approve") -> 50 | C23: =COUNTIFS(TestCases!$I$2:$I$158,$A23,TestCases!$V$2:$V$158,"Draft") -> 19 | D23: =COUNTIFS(TestCases!$I$2:$I$158,$A23,TestCases!$V$2:$V$158,"Block") -> 10 | E23: =COUNTIFS(TestCases!$I$2:$I$158,$A23,TestCases!$V$2:$V$158,"Reject") -> 1 | F23: =SUM(B23:E23) -> 80
A24: 3 | B24: =COUNTIFS(TestCases!$I$2:$I$158,$A24,TestCases!$V$2:$V$158,"Approve") -> 23 | C24: =COUNTIFS(TestCases!$I$2:$I$158,$A24,TestCases!$V$2:$V$158,"Draft") -> 9 | D24: =COUNTIFS(TestCases!$I$2:$I$158,$A24,TestCases!$V$2:$V$158,"Block") -> 3 | E24: =COUNTIFS(TestCases!$I$2:$I$158,$A24,TestCases!$V$2:$V$158,"Reject") -> 6 | F24: =SUM(B24:E24) -> 41
A25: 4 | B25: =COUNTIFS(TestCases!$I$2:$I$158,$A25,TestCases!$V$2:$V$158,"Approve") -> 2 | C25: =COUNTIFS(TestCases!$I$2:$I$158,$A25,TestCases!$V$2:$V$158,"Draft") -> 0 | D25: =COUNTIFS(TestCases!$I$2:$I$158,$A25,TestCases!$V$2:$V$158,"Block") -> 0 | E25: =COUNTIFS(TestCases!$I$2:$I$158,$A25,TestCases!$V$2:$V$158,"Reject") -> 0 | F25: =SUM(B25:E25) -> 2
A26: Total | B26: =SUM(B22:B25) -> 93 | C26: =SUM(C22:C25) -> 40 | D26: =SUM(D22:D25) -> 15 | E26: =SUM(E22:E25) -> 9 | F26: =SUM(F22:F25) -> 157
A28: Priority by Severity (test cases)
A29: Priority | B29: Severity 1 | C29: Severity 2 | D29: Severity 3 | E29: Severity 4 | F29: Total
A30: Critical | B30: =COUNTIFS(TestCases!$H$2:$H$158,$A30,TestCases!$I$2:$I$158,1) -> 33 | C30: =COUNTIFS(TestCases!$H$2:$H$158,$A30,TestCases!$I$2:$I$158,2) -> 0 | D30: =COUNTIFS(TestCases!$H$2:$H$158,$A30,TestCases!$I$2:$I$158,3) -> 0 | E30: =COUNTIFS(TestCases!$H$2:$H$158,$A30,TestCases!$I$2:$I$158,4) -> 0 | F30: =SUM(B30:E30) -> 33
A31: High | B31: =COUNTIFS(TestCases!$H$2:$H$158,$A31,TestCases!$I$2:$I$158,1) -> 1 | C31: =COUNTIFS(TestCases!$H$2:$H$158,$A31,TestCases!$I$2:$I$158,2) -> 79 | D31: =COUNTIFS(TestCases!$H$2:$H$158,$A31,TestCases!$I$2:$I$158,3) -> 0 | E31: =COUNTIFS(TestCases!$H$2:$H$158,$A31,TestCases!$I$2:$I$158,4) -> 0 | F31: =SUM(B31:E31) -> 80
A32: Medium | B32: =COUNTIFS(TestCases!$H$2:$H$158,$A32,TestCases!$I$2:$I$158,1) -> 0 | C32: =COUNTIFS(TestCases!$H$2:$H$158,$A32,TestCases!$I$2:$I$158,2) -> 1 | D32: =COUNTIFS(TestCases!$H$2:$H$158,$A32,TestCases!$I$2:$I$158,3) -> 39 | E32: =COUNTIFS(TestCases!$H$2:$H$158,$A32,TestCases!$I$2:$I$158,4) -> 0 | F32: =SUM(B32:E32) -> 40
A33: Low | B33: =COUNTIFS(TestCases!$H$2:$H$158,$A33,TestCases!$I$2:$I$158,1) -> 0 | C33: =COUNTIFS(TestCases!$H$2:$H$158,$A33,TestCases!$I$2:$I$158,2) -> 0 | D33: =COUNTIFS(TestCases!$H$2:$H$158,$A33,TestCases!$I$2:$I$158,3) -> 2 | E33: =COUNTIFS(TestCases!$H$2:$H$158,$A33,TestCases!$I$2:$I$158,4) -> 2 | F33: =SUM(B33:E33) -> 4
A34: Total | B34: =SUM(B30:B33) -> 34 | C34: =SUM(C30:C33) -> 80 | D34: =SUM(D30:D33) -> 41 | E34: =SUM(E30:E33) -> 2 | F34: =SUM(F30:F33) -> 157
A36: Severity scale (Test plan 1.0.7)
A37: Severity | B37: Meaning
A38: 1 | B38: Blocks a core flow or corrupts a financial record
A39: 2 | B39: Other major failure
A40: 3 | B40: Lower impact, a workaround exists
A41: 4 | B41: Cosmetic
A43: Status by Sprint (1 is the Sprint 1 MVP in the FS header, TBD waits for a decision, a next sprint feature or the CPF Transfer)
A44: Sprint | B44: Approve | C44: Draft | D44: Block | E44: Reject | F44: Total
A45: 1 | B45: =COUNTIFS(TestCases!$D$2:$D$158,$A45,TestCases!$V$2:$V$158,"Approve") -> 93 | C45: =COUNTIFS(TestCases!$D$2:$D$158,$A45,TestCases!$V$2:$V$158,"Draft") -> 28 | D45: =COUNTIFS(TestCases!$D$2:$D$158,$A45,TestCases!$V$2:$V$158,"Block") -> 2 | E45: =COUNTIFS(TestCases!$D$2:$D$158,$A45,TestCases!$V$2:$V$158,"Reject") -> 0 | F45: =SUM(B45:E45) -> 123
A46: TBD | B46: =COUNTIFS(TestCases!$D$2:$D$158,$A46,TestCases!$V$2:$V$158,"Approve") -> 0 | C46: =COUNTIFS(TestCases!$D$2:$D$158,$A46,TestCases!$V$2:$V$158,"Draft") -> 12 | D46: =COUNTIFS(TestCases!$D$2:$D$158,$A46,TestCases!$V$2:$V$158,"Block") -> 13 | E46: =COUNTIFS(TestCases!$D$2:$D$158,$A46,TestCases!$V$2:$V$158,"Reject") -> 9 | F46: =SUM(B46:E46) -> 34
A47: Total | B47: =SUM(B45:B46) -> 93 | C47: =SUM(C45:C46) -> 40 | D47: =SUM(D45:D46) -> 15 | E47: =SUM(E45:E46) -> 9 | F47: =SUM(F45:F46) -> 157
A49: Status by Test Type
A50: Test Type | B50: Approve | C50: Draft | D50: Block | E50: Reject | F50: Total
A51: Functional | B51: =COUNTIFS(TestCases!$U$2:$U$158,$A51,TestCases!$V$2:$V$158,"Approve") -> 64 | C51: =COUNTIFS(TestCases!$U$2:$U$158,$A51,TestCases!$V$2:$V$158,"Draft") -> 23 | D51: =COUNTIFS(TestCases!$U$2:$U$158,$A51,TestCases!$V$2:$V$158,"Block") -> 6 | E51: =COUNTIFS(TestCases!$U$2:$U$158,$A51,TestCases!$V$2:$V$158,"Reject") -> 4 | F51: =SUM(B51:E51) -> 97
A52: Integration | B52: =COUNTIFS(TestCases!$U$2:$U$158,$A52,TestCases!$V$2:$V$158,"Approve") -> 29 | C52: =COUNTIFS(TestCases!$U$2:$U$158,$A52,TestCases!$V$2:$V$158,"Draft") -> 17 | D52: =COUNTIFS(TestCases!$U$2:$U$158,$A52,TestCases!$V$2:$V$158,"Block") -> 9 | E52: =COUNTIFS(TestCases!$U$2:$U$158,$A52,TestCases!$V$2:$V$158,"Reject") -> 5 | F52: =SUM(B52:E52) -> 60
A53: Total | B53: =SUM(B51:B52) -> 93 | C53: =SUM(C51:C52) -> 40 | D53: =SUM(D51:D52) -> 15 | E53: =SUM(E51:E52) -> 9 | F53: =SUM(F51:F52) -> 157
A55: Status by Lens (counted over the scenarios)
A56: Lens | B56: Approve | C56: Draft | D56: Block | E56: Reject | F56: Total
A57: Boundary | B57: =SUMIF(Scenarios!$F$2:$F$33,$A57,Scenarios!$M$2:$M$33) -> 13 | C57: =SUMIF(Scenarios!$F$2:$F$33,$A57,Scenarios!$N$2:$N$33) -> 1 | D57: =SUMIF(Scenarios!$F$2:$F$33,$A57,Scenarios!$O$2:$O$33) -> 2 | E57: =SUMIF(Scenarios!$F$2:$F$33,$A57,Scenarios!$P$2:$P$33) -> 0 | F57: =SUM(B57:E57) -> 16
A58: Business Risk | B58: =SUMIF(Scenarios!$F$2:$F$33,$A58,Scenarios!$M$2:$M$33) -> 8 | C58: =SUMIF(Scenarios!$F$2:$F$33,$A58,Scenarios!$N$2:$N$33) -> 2 | D58: =SUMIF(Scenarios!$F$2:$F$33,$A58,Scenarios!$O$2:$O$33) -> 0 | E58: =SUMIF(Scenarios!$F$2:$F$33,$A58,Scenarios!$P$2:$P$33) -> 1 | F58: =SUM(B58:E58) -> 11
A59: Data | B59: =SUMIF(Scenarios!$F$2:$F$33,$A59,Scenarios!$M$2:$M$33) -> 7 | C59: =SUMIF(Scenarios!$F$2:$F$33,$A59,Scenarios!$N$2:$N$33) -> 0 | D59: =SUMIF(Scenarios!$F$2:$F$33,$A59,Scenarios!$O$2:$O$33) -> 0 | E59: =SUMIF(Scenarios!$F$2:$F$33,$A59,Scenarios!$P$2:$P$33) -> 0 | F59: =SUM(B59:E59) -> 7
A60: Data Integrity | B60: =SUMIF(Scenarios!$F$2:$F$33,$A60,Scenarios!$M$2:$M$33) -> 25 | C60: =SUMIF(Scenarios!$F$2:$F$33,$A60,Scenarios!$N$2:$N$33) -> 17 | D60: =SUMIF(Scenarios!$F$2:$F$33,$A60,Scenarios!$O$2:$O$33) -> 0 | E60: =SUMIF(Scenarios!$F$2:$F$33,$A60,Scenarios!$P$2:$P$33) -> 6 | F60: =SUM(B60:E60) -> 48
A61: Failure&Recovery | B61: =SUMIF(Scenarios!$F$2:$F$33,$A61,Scenarios!$M$2:$M$33) -> 5 | C61: =SUMIF(Scenarios!$F$2:$F$33,$A61,Scenarios!$N$2:$N$33) -> 3 | D61: =SUMIF(Scenarios!$F$2:$F$33,$A61,Scenarios!$O$2:$O$33) -> 5 | E61: =SUMIF(Scenarios!$F$2:$F$33,$A61,Scenarios!$P$2:$P$33) -> 2 | F61: =SUM(B61:E61) -> 15
A62: Happy Path | B62: =SUMIF(Scenarios!$F$2:$F$33,$A62,Scenarios!$M$2:$M$33) -> 0 | C62: =SUMIF(Scenarios!$F$2:$F$33,$A62,Scenarios!$N$2:$N$33) -> 0 | D62: =SUMIF(Scenarios!$F$2:$F$33,$A62,Scenarios!$O$2:$O$33) -> 0 | E62: =SUMIF(Scenarios!$F$2:$F$33,$A62,Scenarios!$P$2:$P$33) -> 0 | F62: =SUM(B62:E62) -> 0
A63: Negative | B63: =SUMIF(Scenarios!$F$2:$F$33,$A63,Scenarios!$M$2:$M$33) -> 11 | C63: =SUMIF(Scenarios!$F$2:$F$33,$A63,Scenarios!$N$2:$N$33) -> 2 | D63: =SUMIF(Scenarios!$F$2:$F$33,$A63,Scenarios!$O$2:$O$33) -> 1 | E63: =SUMIF(Scenarios!$F$2:$F$33,$A63,Scenarios!$P$2:$P$33) -> 0 | F63: =SUM(B63:E63) -> 14
A64: Sequence | B64: =SUMIF(Scenarios!$F$2:$F$33,$A64,Scenarios!$M$2:$M$33) -> 3 | C64: =SUMIF(Scenarios!$F$2:$F$33,$A64,Scenarios!$N$2:$N$33) -> 2 | D64: =SUMIF(Scenarios!$F$2:$F$33,$A64,Scenarios!$O$2:$O$33) -> 2 | E64: =SUMIF(Scenarios!$F$2:$F$33,$A64,Scenarios!$P$2:$P$33) -> 0 | F64: =SUM(B64:E64) -> 7
A65: State | B65: =SUMIF(Scenarios!$F$2:$F$33,$A65,Scenarios!$M$2:$M$33) -> 9 | C65: =SUMIF(Scenarios!$F$2:$F$33,$A65,Scenarios!$N$2:$N$33) -> 12 | D65: =SUMIF(Scenarios!$F$2:$F$33,$A65,Scenarios!$O$2:$O$33) -> 3 | E65: =SUMIF(Scenarios!$F$2:$F$33,$A65,Scenarios!$P$2:$P$33) -> 0 | F65: =SUM(B65:E65) -> 24
A66: Workflow | B66: =SUMIF(Scenarios!$F$2:$F$33,$A66,Scenarios!$M$2:$M$33) -> 12 | C66: =SUMIF(Scenarios!$F$2:$F$33,$A66,Scenarios!$N$2:$N$33) -> 1 | D66: =SUMIF(Scenarios!$F$2:$F$33,$A66,Scenarios!$O$2:$O$33) -> 2 | E66: =SUMIF(Scenarios!$F$2:$F$33,$A66,Scenarios!$P$2:$P$33) -> 0 | F66: =SUM(B66:E66) -> 15
A67: Total | B67: =SUM(B57:B66) -> 93 | C67: =SUM(C57:C66) -> 40 | D67: =SUM(D57:D66) -> 15 | E67: =SUM(E57:E66) -> 9 | F67: =SUM(F57:F66) -> 157
A69: Status by Type
A70: Type | B70: Approve | C70: Draft | D70: Block | E70: Reject | F70: Total
A71: positive | B71: =COUNTIFS(TestCases!$J$2:$J$158,$A71,TestCases!$V$2:$V$158,"Approve") -> 33 | C71: =COUNTIFS(TestCases!$J$2:$J$158,$A71,TestCases!$V$2:$V$158,"Draft") -> 14 | D71: =COUNTIFS(TestCases!$J$2:$J$158,$A71,TestCases!$V$2:$V$158,"Block") -> 4 | E71: =COUNTIFS(TestCases!$J$2:$J$158,$A71,TestCases!$V$2:$V$158,"Reject") -> 7 | F71: =SUM(B71:E71) -> 58
A72: negative | B72: =COUNTIFS(TestCases!$J$2:$J$158,$A72,TestCases!$V$2:$V$158,"Approve") -> 37 | C72: =COUNTIFS(TestCases!$J$2:$J$158,$A72,TestCases!$V$2:$V$158,"Draft") -> 13 | D72: =COUNTIFS(TestCases!$J$2:$J$158,$A72,TestCases!$V$2:$V$158,"Block") -> 3 | E72: =COUNTIFS(TestCases!$J$2:$J$158,$A72,TestCases!$V$2:$V$158,"Reject") -> 1 | F72: =SUM(B72:E72) -> 54
A73: boundary | B73: =COUNTIFS(TestCases!$J$2:$J$158,$A73,TestCases!$V$2:$V$158,"Approve") -> 20 | C73: =COUNTIFS(TestCases!$J$2:$J$158,$A73,TestCases!$V$2:$V$158,"Draft") -> 6 | D73: =COUNTIFS(TestCases!$J$2:$J$158,$A73,TestCases!$V$2:$V$158,"Block") -> 1 | E73: =COUNTIFS(TestCases!$J$2:$J$158,$A73,TestCases!$V$2:$V$158,"Reject") -> 0 | F73: =SUM(B73:E73) -> 27
A74: exception | B74: =COUNTIFS(TestCases!$J$2:$J$158,$A74,TestCases!$V$2:$V$158,"Approve") -> 3 | C74: =COUNTIFS(TestCases!$J$2:$J$158,$A74,TestCases!$V$2:$V$158,"Draft") -> 7 | D74: =COUNTIFS(TestCases!$J$2:$J$158,$A74,TestCases!$V$2:$V$158,"Block") -> 7 | E74: =COUNTIFS(TestCases!$J$2:$J$158,$A74,TestCases!$V$2:$V$158,"Reject") -> 1 | F74: =SUM(B74:E74) -> 18
A75: Total | B75: =SUM(B71:B74) -> 93 | C75: =SUM(C71:C74) -> 40 | D75: =SUM(D71:D74) -> 15 | E75: =SUM(E71:E74) -> 9 | F75: =SUM(F71:F74) -> 157
A77: Status by Technique (counted over the scenarios)
A78: Technique | B78: Approve | C78: Draft | D78: Block | E78: Reject | F78: Total
A79: BVA | B79: =SUMIF(Scenarios!$G$2:$G$33,$A79,Scenarios!$M$2:$M$33) -> 19 | C79: =SUMIF(Scenarios!$G$2:$G$33,$A79,Scenarios!$N$2:$N$33) -> 4 | D79: =SUMIF(Scenarios!$G$2:$G$33,$A79,Scenarios!$O$2:$O$33) -> 3 | E79: =SUMIF(Scenarios!$G$2:$G$33,$A79,Scenarios!$P$2:$P$33) -> 0 | F79: =SUM(B79:E79) -> 26
A80: DecisionTable | B80: =SUMIF(Scenarios!$G$2:$G$33,$A80,Scenarios!$M$2:$M$33) -> 5 | C80: =SUMIF(Scenarios!$G$2:$G$33,$A80,Scenarios!$N$2:$N$33) -> 7 | D80: =SUMIF(Scenarios!$G$2:$G$33,$A80,Scenarios!$O$2:$O$33) -> 0 | E80: =SUMIF(Scenarios!$G$2:$G$33,$A80,Scenarios!$P$2:$P$33) -> 0 | F80: =SUM(B80:E80) -> 12
A81: EP | B81: =SUMIF(Scenarios!$G$2:$G$33,$A81,Scenarios!$M$2:$M$33) -> 57 | C81: =SUMIF(Scenarios!$G$2:$G$33,$A81,Scenarios!$N$2:$N$33) -> 22 | D81: =SUMIF(Scenarios!$G$2:$G$33,$A81,Scenarios!$O$2:$O$33) -> 3 | E81: =SUMIF(Scenarios!$G$2:$G$33,$A81,Scenarios!$P$2:$P$33) -> 6 | F81: =SUM(B81:E81) -> 88
A82: N/A | B82: =SUMIF(Scenarios!$G$2:$G$33,$A82,Scenarios!$M$2:$M$33) -> 0 | C82: =SUMIF(Scenarios!$G$2:$G$33,$A82,Scenarios!$N$2:$N$33) -> 0 | D82: =SUMIF(Scenarios!$G$2:$G$33,$A82,Scenarios!$O$2:$O$33) -> 0 | E82: =SUMIF(Scenarios!$G$2:$G$33,$A82,Scenarios!$P$2:$P$33) -> 0 | F82: =SUM(B82:E82) -> 0
A83: StateTransition | B83: =SUMIF(Scenarios!$G$2:$G$33,$A83,Scenarios!$M$2:$M$33) -> 12 | C83: =SUMIF(Scenarios!$G$2:$G$33,$A83,Scenarios!$N$2:$N$33) -> 7 | D83: =SUMIF(Scenarios!$G$2:$G$33,$A83,Scenarios!$O$2:$O$33) -> 9 | E83: =SUMIF(Scenarios!$G$2:$G$33,$A83,Scenarios!$P$2:$P$33) -> 3 | F83: =SUM(B83:E83) -> 31
A84: Total | B84: =SUM(B79:B83) -> 93 | C84: =SUM(C79:C83) -> 40 | D84: =SUM(D79:D83) -> 15 | E84: =SUM(E79:E83) -> 9 | F84: =SUM(F79:F83) -> 157
A86: Checkpoints by Flag and Sprint
A87: Flag | B87: Sprint 1 | C87: Sprint TBD | D87: Total
A88: Clear | B88: =COUNTIFS(Checkpoint!$H$2:$H$26,$A88,Checkpoint!$G$2:$G$26,"1") -> 6 | C88: =COUNTIFS(Checkpoint!$H$2:$H$26,$A88,Checkpoint!$G$2:$G$26,"TBD") -> 0 | D88: =SUM(B88:C88) -> 6
A89: Assumed | B89: =COUNTIFS(Checkpoint!$H$2:$H$26,$A89,Checkpoint!$G$2:$G$26,"1") -> 10 | C89: =COUNTIFS(Checkpoint!$H$2:$H$26,$A89,Checkpoint!$G$2:$G$26,"TBD") -> 0 | D89: =SUM(B89:C89) -> 10
A90: Open | B90: =COUNTIFS(Checkpoint!$H$2:$H$26,$A90,Checkpoint!$G$2:$G$26,"1") -> 5 | C90: =COUNTIFS(Checkpoint!$H$2:$H$26,$A90,Checkpoint!$G$2:$G$26,"TBD") -> 4 | D90: =SUM(B90:C90) -> 9
A91: Total | B91: =SUM(B88:B90) -> 21 | C91: =SUM(C88:C90) -> 4 | D91: =SUM(D88:D90) -> 25
A93: Assumptions by State
A94: State | B94: Count
A95: Open | B95: =COUNTIF(Assumptions!$J$2:$J$51,A95) -> 31
A96: Resolved | B96: =COUNTIF(Assumptions!$J$2:$J$51,A96) -> 9
A97: Superseded | B97: =COUNTIF(Assumptions!$J$2:$J$51,A97) -> 7
A98: Deferred | B98: =COUNTIF(Assumptions!$J$2:$J$51,A98) -> 0
A99: Not adopted | B99: =COUNTIF(Assumptions!$J$2:$J$51,A99) -> 2
A100: Agreed | B100: =COUNTIF(Assumptions!$J$2:$J$51,A100) -> 1
A101: Total | B101: =SUM(B95:B100) -> 50
A103: Questions
A104: Measure | B104: Count
A105: Questions | B105: =COUNTA(Questions!$B$2:$B$50) -> 49
A106: Questions with an assumption | B106: =COUNTIF(Questions!$A$2:$A$50,"ASM-R1-*") -> 31
A107: Questions without an assumption (Assumption Ref N/A) | B107: =COUNTIF(Questions!$A$2:$A$50,"N/A") -> 18
A108: Questions with an answer | B108: =COUNTA(Questions!$C$2:$C$50) -> 0
A109: Questions without an answer | B109: =B105-B108 -> 49
A111: Coverage
A112: Measure | B112: Count
A113: Checkpoints | B113: =COUNTA(Checkpoint!$A$2:$A$26) -> 25
A114: Checkpoints with at least one test case that can be generated | B114: =COUNTIF(Checkpoint!$I$2:$I$26,"Yes") -> 22
...

Sheet TestCases
A1: TC ID | B1: Requirement (Tender clause) | C1: Module | D1: Sprint | E1: Scenario ID | F1: Title | G1: Objective | H1: Priority | I1: Severity | J1: Type | K1: Precondition | L1: Postcondition | M1: Test Data | N1: Steps | O1: Expected Result | P1: Actual Result | Q1: Traceability Requirement | R1: Checkpoint Ref | S1: Assumption Ref | T1: Dependency Ref | U1: Test Type | V1: Status | W1: Reason
A2: TC-R1-01-01 | B2: R1 | C2: Education Account | D2: 1 | E2: SCN-R1-01 | F2: Account is created on the 7th birthday | G2: A Singapore Citizen who turns 7 on the business date gets an Active account, and a citizen who turns 7 the next day does not. Case: Account is created on the 7th birthday | H2: Critical | I2: 1 | J2: boundary | K2: 1. The SIT environment is ready and both synchronizations can be run for a chosen business date (ASM-R1-01) 2. The Mock Government Citizen API holds the records of the Test Data. Every record has a Full Name and a Gender and has no address unless the Test Data says otherwise (ASM-R1-32) 3. The Initial Synchronization has already run 4. Student A is a Singapore Citizen in the Mock Government Citizen API and has no Education Account | L2: Data created or changed by the steps stays in the SIT test data | M2: Student A: NRIC T9901011D, Singapore Citizen, DOB 15 Oct 2019. Business date 15 Oct 2026 (turns 7 that day) | N2: 1. Set the business date to 15 Oct 2026 2. Run the Daily Incremental Synchronization 3. Look up the Education Account of student A by NRIC T9901011D | O2: 1. The System creates one Education Account for student A 2. The Account Status is Active | P2: Not Executed | Q2: Tender R1 (Education Account); FS R1 V1.0 F01-AC02, 1.1.5 step 9, 1.1.6 age examples | R2: CP-R1-02 | S2: N/A | T2: ASM-R1-01, ASM-R1-02, ASM-R1-03, ASM-R1-14, ASM-R1-32 | U2: Functional | V2: Approve | W2: F01-AC02 says the Daily Sync creates the account for a citizen who just turned 7. The age example in 1.1.6 (DOB 15/06/2019, processing date 15/06/2026) gives the same offset.
A3: TC-R1-01-02 | B3: R1 | C3: Education Account | D3: 1 | E3: SCN-R1-01 | F3: No account the day before the 7th birthday | G3: A Singapore Citizen who turns 7 on the business date gets an Active account, and a citizen who turns 7 the next day does not. Case: No account the day before the 7th birthday | H3: High | I3: 2 | J3: boundary | K3: 1. The SIT environment is ready and both synchronizations can be run for a chosen business date (ASM-R1-01) 2. The Mock Government Citizen API holds the records of the Test Data. Every record has a Full Name and a Gender and has no address unless the Test Data says otherwise (ASM-R1-32) 3. The Initial Synchronization has already run 4. Student B is a Singapore Citizen in the Mock Government Citizen API and has no Education Account | L3: Data created or changed by the steps stays in the SIT test data | M3: Student B: NRIC T9901021A, Singapore Citizen, DOB 16 Oct 2019. Business date 15 Oct 2026 (6 years and 364 days old) | N3: 1. Set the business date to 15 Oct 2026 2. Run the Daily Incremental Synchronization 3. Look up the Education Account of student B by NRIC T9901021A | O3: 1. The System creates no Education Account for student B | P3: Not Executed | Q3: Tender R1 (Education Account); FS R1 V1.0 F01-AC04, 1.1.6 age examples | R3: CP-R1-02 | S3: N/A | T3: ASM-R1-01, ASM-R1-02, ASM-R1-03, ASM-R1-14, ASM-R1-32 | U3: Functional | V3: Approve | W3: The age example in 1.1.6 (DOB 15/06/2019, processing date 14/06/2026) says the citizen is not yet 7 and gets no account. F01-AC04 says the same for a citizen under 7.
A4: TC-R1-02-01 | B4: R1 | C4: Education Account | D4: 1 | E4: SCN-R1-02 | F4: No account for a citizen below 7 | G4: A citizen below 7 or from 16 on, with no account, gets none. Case: No account for a citizen below 7 | H4: Medium | I4: 3 | J4: negative | K4: 1. The SIT environment is ready and both synchronizations can be run for a chosen business date (ASM-R1-01) 2. The Mock Government Citizen API holds the records of the Test Data. Every record has a Full Name and a Gender and has no address unless the Test Data says otherwise (ASM-R1-32) 3. The Initial Synchronization has not run yet and can be run again for this case 4. Student A is a Singapore Citizen in the Mock Government Citizen API and has no Education Account | L4: Data created or changed by the steps stays in the SIT test data | M4: Student A: NRIC T9902011Z, Singapore Citizen, DOB 15 Oct 2022. Business date 15 Oct 2026 (4 years old) | N4: 1. Set the business date to 15 Oct 2026 2. Run the Initial Synchronization 3. Look up the Education Account of student A by NRIC T9902011Z | O4: 1. The System creates no Education Account for student A | P4: Not Executed | Q4: Tender R1 (Education Account); FS R1 V1.0 F01-AC04, F01-AF02, 1.1.4 step 2 | R4: CP-R1-02 | S4: N/A | T4: ASM-R1-01, ASM-R1-02, ASM-R1-03, ASM-R1-14, ASM-R1-32 | U4: Functional | V4: Approve | W4: F01-AC04 and F01-AF02 say a citizen under 7 gets no account.
A5: TC-R1-02-02 | B5: R1 | C5: Education Account | D5: 1 | E5: SCN-R1-02 | F5: No account for a citizen aged 18 | G5: A citizen below 7 or from 16 on, with no account, gets none. Case: No account for a citizen aged 18 | H5: Medium | I5: 3 | J5: negative | K5: 1. The SIT environment is ready and both synchronizations can be run for a chosen business date (ASM-R1-01) 2. The Mock Government Citizen API holds the records of the Test Data. Every record has a Full Name and a Gender and has no address unless the Test Data says otherwise (ASM-R1-32) 3. The Initial Synchronization has not run yet and can be run again for this case 4. Student A is a Singapore Citizen in the Mock Government Citizen API and has no Education Account | L5: Data created or changed by the steps stays in the SIT test data | M5: Student A: NRIC T9902021G, Singapore Citizen, DOB 15 Oct 2008. Business date 15 Oct 2026 (18 years old) | N5: 1. Set the business date to 15 Oct 2026 2. Run the Initial Synchronization 3. Look up the Education Account of student A by NRIC T9902021G | O5: 1. The System creates no Education Account for student A | P5: Not Executed | Q5: Tender R1 (Education Account); FS R1 V1.0 F01-AC05, F01-AF02, F01-BR05 | R5: CP-R1-02 | S5: N/A | T5: ASM-R1-01, ASM-R1-02, ASM-R1-03, ASM-R1-14, ASM-R1-32 | U5: Functional | V5: Approve | W5: F01-AC05 and F01-BR05 say a citizen from 16 on who has no account gets none.
A6: TC-R1-02-03 | B6: R1 | C6: Education Account | D6: 1 | E6: SCN-R1-02 | F6: No account for a citizen who turns 16 today | G6: A citizen below 7 or from 16 on, with no account, gets none. Case: No account for a citizen who turns 16 today | H6: High | I6: 2 | J6: boundary | K6: 1. The SIT environment is ready and both synchronizations can be run for a chosen business date (ASM-R1-01) 2. The Mock Government Citizen API holds the records of the Test Data. Every record has a Full Name and a Gender and has no address unless the Test Data says otherwise (ASM-R1-32) 3. The Initial Synchronization has not run yet and can be run again for this case 4. Student A is a Singapore Citizen in the Mock Government Citizen API and has no Education Account | L6: Data created or changed by the steps stays in the SIT test data | M6: Student A: NRIC T9902031D, Singapore Citizen, DOB 15 Oct 2010. Business date 15 Oct 2026 (turns 16 that day) | N6: 1. Set the business date to 15 Oct 2026 2. Run the Initial Synchronization 3. Look up the Education Account of student A by NRIC T9902031D | O6: 1. The System creates no Education Account for student A | P6: Not Executed | Q6: Tender R1 (Education Account); FS R1 V1.0 F01-BR05, F01-AC05, 1.1.6 age examples, F02-BR01 [CR] | R6: CP-R1-02 | S6: N/A | T6: ASM-R1-01, ASM-R1-02, ASM-R1-03, ASM-R1-04, ASM-R1-14, ASM-R1-32, Question on 16th birthday rule | U6: Functional | V6: Approve | W6: 1.1.6 gives DOB 15/06/2019 and processing date 15/06/2035 (16th birthday) as no new account. F02-BR01 [CR] closes at 16, so the same day is the upper boundary.
A7: TC-R1-03-01 | B7: R1 | C7: Education Account | D7: 1 | E7: SCN-R1-03 | F7: Singapore Citizen gets an account | G7: Citizenship decides whether an account is created. Case: Singapore Citizen gets an account | H7: Critical | I7: 1 | J7: positive | K7: 1. The SIT environment is ready and both synchronizations can be run for a chosen business date (ASM-R1-01) 2. The Mock Government Citizen API holds the records of the Test Data. Every record has a Full Name and a Gender and has no address unless the Test Data says otherwise (ASM-R1-32) 3. The Initial Synchronization has already run 4. Student A is in the Mock Government Citizen API and has no Education Account | L7: Data created or changed by the steps stays in the SIT test data | M7: Student A: NRIC T9903011E, Singapore Citizen, DOB 15 Oct 2019. Business date 15 Oct 2026 | N7: 1. Set the business date to 15 Oct 2026 2. Run the Daily Incremental Synchronization 3. Look up the Education Account of student A by NRIC T9903011E | O7: 1. The System creates one Education Account for student A 2. The Account Status is Active | P7: Not Executed | Q7: Tender R1 (Education Account); FS R1 V1.0 F01-BR01 [CR], F01-AC02 | R7: CP-R1-01 | S7: N/A | T7: ASM-R1-01, ASM-R1-02, ASM-R1-14, ASM-R1-32 | U7: Functional | V7: Approve | W7: F01-BR01 [CR] gives the account to Singapore Citizens.
A8: TC-R1-03-02 | B8: R1 | C8: Education Account | D8: 1 | E8: SCN-R1-03 | F8: Dual citizen gets an account | G8: Citizenship decides whether an account is created. Case: Dual citizen gets an account | H8: High | I8: 2 | J8: positive | K8: 1. The SIT environment is ready and both synchronizations can be run for a chosen business date (ASM-R1-01) 2. The Mock Government Citizen API holds the records of the Test Data. Every record has a Full Name and a Gender and has no address unless the Test Data says otherwise (ASM-R1-32) 3. The Initial Synchronization has already run 4. Student A is in the Mock Government Citizen API and has no Education Account | L8: Data created or changed by the steps stays in the SIT test data | M8: Student A: NRIC T9903021B, citizen of Singapore and another country (shown as Singapore Citizen, ASM-R1-31), DOB 15 Oct 2019. Business date 15 Oct 2026 | N8: 1. Set the business date to 15 Oct 2026 2. Run the Daily Incremental Synchronization 3. Look up the Education Account of student A by NRIC T9903021B | O8: 1. The System creates one Education Account for student A 2. The Account Status is Active | P8: Not Executed | Q8: Tender R1 (Education Account); Register NEW-03, 1.1.3 Required Data Validation | R8: CP-R1-01 | S8: ASM-R1-31: FS 1.1.3, register NEW-03 | T8: ASM-R1-01, ASM-R1-02, ASM-R1-31, ASM-R1-32 | U8: Functional | V8: Draft | W8: Register NEW-03 says a dual citizen counts as Singaporean. FS 1.1.3 requires a recognised Citizenship value but gives no list, so the way a dual citizen is shown is an assumption.
A9: TC-R1-03-03 | B9: R1 | C9: Education Account | D9: 1 | E9: SCN-R1-03 | F9: Permanent Resident gets no account | G9: Citizenship decides whether an account is created. Case: Permanent Resident gets no account | H9: High | I9: 2 | J9: negative | K9: 1. The SIT environment is ready and both synchronizations can be run for a chosen business date (ASM-R1-01) 2. The Mock Government Citizen API holds the records of the Test Data. Every record has a Full Name and a Gender and has no address unless the Test Data says otherwise (ASM-R1-32) 3. The Initial Synchronization has already run 4. Student A is in the Mock Government Citizen API and has no Education Account | L9: Data created or changed by the steps stays in the SIT test data | M9: Student A: NRIC T9903031Z, Permanent Resident, DOB 15 Oct 2019. Business date 15 Oct 2026 | N9: 1. Set the business date to 15 Oct 2026 2. Run the Daily Incremental Synchronization 3. Look up the Education Account of student A by NRIC T9903031Z | O9: 1. The System creates no Education Account for student A | P9: Not Executed | Q9: Tender R1 (Education Account); FS R1 V1.0 F01-AC03, F01-AF01 | R9: CP-R1-01 | S9: N/A | T9: ASM-R1-01, ASM-R1-02, ASM-R1-14, ASM-R1-32 | U9: Functional | V9: Approve | W9: F01-AC03 says a Permanent Resident gets no account.
A10: TC-R1-03-04 | B10: R1 | C10: Education Account | D10: 1 | E10: SCN-R1-03 | F10: Foreign student gets no account | G10: Citizenship decides whether an account is created. Case: Foreign student gets no account | H10: High | I10: 2 | J10: negative | K10: 1. The SIT environment is ready and both synchronizations can be run for a chosen business date (ASM-R1-01) 2. The Mock Government Citizen API holds the records of the Test Data. Every record has a Full Name and a Gender and has no address unless the Test Data says otherwise (ASM-R1-32) 3. The Initial Synchronization has already run 4. Student A is in the Mock Government Citizen API and has no Education Account | L10: Data created or changed by the steps stays in the SIT test data | M10: Student A: NRIC T9903041G, Foreign, DOB 15 Oct 2019. Business date 15 Oct 2026 | N10: 1. Set the business date to 15 Oct 2026 2. Run the Daily Incremental Synchronization 3. Look up the Education Account of student A by NRIC T9903041G | O10: 1. The System creates no Education Account for student A | P10: Not Executed | Q10: Tender R1 (Education Account); FS R1 V1.0 F01-AC03, F01-AF01, 2.1 rules | R10: CP-R1-01 | S10: N/A | T10: ASM-R1-01, ASM-R1-02, ASM-R1-14, ASM-R1-32 | U10: Functional | V10: Approve | W10: F01-AC03 says a non Singapore Citizen gets no account. 2.1 names the Foreign Student as a profile without an account.
A11: TC-R1-03-05 | B11: R1 | C11: Education Account | D11: 1 | E11: SCN-R1-03 | F11: Citizen living overseas gets an account | G11: Citizenship decides whether an account is created. Case: Citizen living overseas gets an account | H11: High | I11: 2 | J11: positive | K11: 1. The SIT environment is ready and both synchronizations can be run for a chosen business date (ASM-R1-01) 2. The Mock Government Citizen API holds the records of the Test Data. Every record has a Full Name and a Gender and has no address unless the Test Data says otherwise (ASM-R1-32) 3. The Initial Synchronization has already run 4. Student A is in the Mock Government Citizen API and has no Education Account | L11: Data created or changed by the steps stays in the SIT test data | M11: Student A: NRIC T9903051D, Singapore Citizen, DOB 15 Oct 2019, residential Country Australia. Business date 15 Oct 2026 | N11: 1. Set the business date to 15 Oct 2026 2. Run the Daily Incremental Synchronization 3. Look up the Education Account of student A by NRIC T9903051D | O11: 1. The System creates one Education Account for student A 2. The Account Status is Active | P11: Not Executed | Q11: Tender R1 (Education Account); Register NEW-04, F01-BR01 [CR], 2.1 Country (optional) | R11: CP-R1-01 | S11: N/A | T11: ASM-R1-01, ASM-R1-02, ASM-R1-14, ASM-R1-32 | U11: Functional | V11: Approve | W11: Register NEW-04 says a citizen studying overseas still gets an account. Inference: the only overseas field in the FS is the optional Country in 2.1, and optional data does not block creation (1.1.3).
A12: TC-R1-04-01 | B12: R1 | C12: Education Account | D12: 1 | E12: SCN-R1-04 | F12: New account starts Active with a zero balance in SGD | G12: A new account is Active with a zero SGD balance, a unique number and a link to the right Student Profile. Case: New account starts Active with a zero balance in SGD | H12: Critical | I12: 1 | J12: positive | K12: 1. The SIT environment is ready and both synchronizations can be run for a chosen business date (ASM-R1-01) 2. The Mock Government Citizen API holds the records of the Test Data. Every record has a Full Name and a Gender and has no address unless the Test Data says otherwise (ASM-R1-32) 3. The Initial Synchronization has already run 4. Student A is a Singapore Citizen in the Mock Government Citizen API and has no Education Account | L12: Data created or changed by the steps stays in the SIT test data | M12: Student A: NRIC T9904011J, Singapore Citizen, DOB 15 Oct 2019. Business date 15 Oct 2026 | N12: 1. Set the business date to 15 Oct 2026 2. Run the Daily Incremental Synchronization 3. Look up the Education Account of student A by NRIC T9904011J 4. Read the Account Status, Account Balance and Currency | O12: 1. The Account Status is Active 2. The Account Balance is SGD 0.00 3. The Currency is SGD | P12: Not Executed | Q12: Tender R1 (Education Account); FS R1 V1.0 F01-AC01, 1.1.4 step 8, 1.1.5 step 10, 1.1.8 table, 2.2, register TBD-15 | R12: CP-R1-03 | S12: N/A | T12: ASM-R1-01, ASM-R1-02, ASM-R1-20, ASM-R1-32 | U12: Functional | V12: Approve | W12: 1.1.4 step 8 and 1.1.5 step 10 give Active, SGD 0.00 and SGD. The table in 1.1.8 lists the status and the balance. Register TBD-15 records that the initial balance is always zero.
A13: TC-R1-04-02 | B13: R1 | C13: Education Account | D13: 1 | E13: SCN-R1-04 | F13: Account number is unique and the account links to the right Student Profile | G13: A new account is Active with a zero SGD balance, a unique number and a link to the right Student Profile. Case: Account number is unique and the account links to the right Student Profile | H13: High | I13: 2 | J13: positive | K13: 1. The SIT environment is ready and both synchronizations can be run for a chosen business date (ASM-R1-01) 2. The Mock Government Citizen API holds the records of the Test Data. Every record has a Full Name and a Gender and has no address unless the Test Data says otherwise (ASM-R1-32) 3. The Initial Synchronization has already run 4. Students A and B are Singapore Citizens in the Mock Government Citizen API, turn 7 on the business date and have no Education Account | L13: Data created or changed by the steps stays in the SIT test data | M13: Student A: NRIC T9904021H, Singapore Citizen, DOB 15 Oct 2019. Student B: NRIC T9904022F, Singapore Citizen, DOB 15 Oct 2019. Business date 15 Oct 2026 | N13: 1. Set the business date to 15 Oct 2026 2. Run the Daily Incremental Synchronization 3. Look up the Education Account of student A by NRIC T9904021H and of student B by NRIC T9904022F 4. Read the Education Account Number and the Account Holder Reference of each account | O13: 1. Each account has an Education Account Number and the two numbers differ 2. The Account Holder Reference of the account of student A points to the Student Profile of T9904021H 3. The Account Holder Reference of the account of student B points to the Student Profile of T9904022F | P13: Not Executed | Q13: Tender R1 (Education Account); FS R1 V1.0 1.1.5 step 9, 1.1.8 table, 2.2 | R13: CP-R1-03 | S13: N/A | T13: ASM-R1-01, ASM-R1-02, ASM-R1-14, ASM-R1-32 | U13: Functional | V13: Approve | W13: 1.1.8 says the Education Account Number is unique and the Account Holder Reference (Student id) links the account to the right Student Profile. 1.1.5 step 9 says the System links the account to the profile.
... A158: TC-R1-32-04 | B158: R1 | C158: Education Account | D158: 1 | E158: SCN-R1-32 | F158: A Government update of the Father or Mother NRIC needs no rescan by R1 | G158: Student data is stored at account creation. The Daily Job and the closure check do not refresh it, and R1 does not rescan a student after a Government update. Case: A Government update of the Father or Mother NRIC needs no rescan by R1 | H158: Medium | I158: 3 | J158: negative | K158: 1. The SIT environment is ready and both synchronizations can be run for a chosen business date (ASM-R1-01) 2. The Mock Government Citizen API holds the records of the Test Data. Every record has a Full Name and a Gender and has no address unless the Test Data says otherwise (ASM-R1-32) 3. The Initial Synchronization has already run 4. Student A, aged 10, has an Active Education Account and a Student Profile with Father NRIC and Mother NRIC empty (seeded as test data) | L158: Data created or changed by the steps stays in the SIT test data | M158: Student A: NRIC T9932041E, DOB 15 Oct 2016, Father NRIC and Mother NRIC empty at creation. Father NRIC T9932042C added in the Mock Government Citizen API on 15 Oct 2026. Business date 15 Oct 2026 | N158: 1. Add the Father NRIC T9932042C to the record of student A in the Mock Government Citizen API 2. Set the business date to 15 Oct 2026 3. Run the Daily Incremental Synchronization 4. Look up the Student Profile of student A by NRIC T9932041E and read the Father NRIC | O158: 1. The Father NRIC in the Student Profile is still empty 2. The System does not rescan student A | P158: Not Executed | Q158: Tender R1 (Education Account); FS R1 V1.0 1.1.1 Cross-Function Dependency R8, F01-AC16, 1.1.5 Notes [TD] | R158: CP-R1-25 | S158: N/A | T158: ASM-R1-01, ASM-R1-02, ASM-R1-14, ASM-R1-32 | U158: Integration | V158: Approve | W158: 1.1.1 (Cross-Function Dependency R8) says a Government update of the Father or Mother NRIC after creation does not make R1 scan the student again. R8 checks the relationship when the parent signs in.

Sheet Scenarios
A1: Scenario ID | B1: Checkpoint | C1: Requirement (Tender clause) | D1: Module | E1: Sprint | F1: Lens | G1: Technique | H1: Title | I1: Condition | J1: Evidence | K1: Open ASM and questions | L1: Test cases | M1: Approve | N1: Draft | O1: Block | P1: Reject | Q1: Status
A2: SCN-R1-01 | B2: CP-R1-02 | C2: R1 | D2: Education Account | E2: 1 | F2: Boundary | G2: BVA | H2: Account is created on the 7th birthday | I2: A Singapore Citizen who turns 7 on the business date gets an Active account, and a citizen who turns 7 the next day does not | J2: FS F01-AC02, 1.1.5 step 2, 1.1.6 examples | K2: N/A | L2: =COUNTIFS(TestCases!$E$2:$E$158,$A2) -> 2 | M2: =COUNTIFS(TestCases!$E$2:$E$158,$A2,TestCases!$V$2:$V$158,"Approve") -> 2 | N2: =COUNTIFS(TestCases!$E$2:$E$158,$A2,TestCases!$V$2:$V$158,"Draft") -> 0 | O2: =COUNTIFS(TestCases!$E$2:$E$158,$A2,TestCases!$V$2:$V$158,"Block") -> 0 | P2: =COUNTIFS(TestCases!$E$2:$E$158,$A2,TestCases!$V$2:$V$158,"Reject") -> 0 | Q2: =IF(P2=L2,"Reject",IF(O2>0,"Block",IF(N2>0,"Draft","Approve"))) -> Approve
A3: SCN-R1-02 | B3: CP-R1-02 | C3: R1 | D3: Education Account | E3: 1 | F3: Data | G3: EP | H3: No account outside the age range | I3: A citizen below 7 or from 16 on, with no account, gets none | J3: FS F01-AC04, F01-AC05, F01-BR05 | K3: Question on 16th birthday rule | L3: =COUNTIFS(TestCases!$E$2:$E$158,$A3) -> 3 | M3: =COUNTIFS(TestCases!$E$2:$E$158,$A3,TestCases!$V$2:$V$158,"Approve") -> 3 | N3: =COUNTIFS(TestCases!$E$2:$E$158,$A3,TestCases!$V$2:$V$158,"Draft") -> 0 | O3: =COUNTIFS(TestCases!$E$2:$E$158,$A3,TestCases!$V$2:$V$158,"Block") -> 0 | P3: =COUNTIFS(TestCases!$E$2:$E$158,$A3,TestCases!$V$2:$V$158,"Reject") -> 0 | Q3: =IF(P3=L3,"Reject",IF(O3>0,"Block",IF(N3>0,"Draft","Approve"))) -> Approve
A4: SCN-R1-03 | B4: CP-R1-01 | C4: R1 | D4: Education Account | E4: 1 | F4: Business Risk | G4: DecisionTable | H4: Eligibility by citizenship | I4: Citizenship decides whether an account is created | J4: FS F01-BR01 [CR], F01-AC03, register NEW-03, NEW-04 | K4: ASM-R1-31 | L4: =COUNTIFS(TestCases!$E$2:$E$158,$A4) -> 5 | M4: =COUNTIFS(TestCases!$E$2:$E$158,$A4,TestCases!$V$2:$V$158,"Approve") -> 4 | N4: =COUNTIFS(TestCases!$E$2:$E$158,$A4,TestCases!$V$2:$V$158,"Draft") -> 1 | O4: =COUNTIFS(TestCases!$E$2:$E$158,$A4,TestCases!$V$2:$V$158,"Block") -> 0 | P4: =COUNTIFS(TestCases!$E$2:$E$158,$A4,TestCases!$V$2:$V$158,"Reject") -> 0 | Q4: =IF(P4=L4,"Reject",IF(O4>0,"Block",IF(N4>0,"Draft","Approve"))) -> Draft
A5: SCN-R1-04 | B5: CP-R1-03 | C5: R1 | D5: Education Account | E5: 1 | F5: Data Integrity | G5: EP | H5: New account starts clean | I5: A new account is Active with a zero SGD balance, a unique number and a link to the right Student Profile | J5: FS 1.1.4 steps 6 to 9, 1.1.5 steps 8 to 11, 1.1.8, 2.2, 2.3 Scope Note, register TBD-15 | K5: ASM-R1-34, ASM-R1-36 | L5: =COUNTIFS(TestCases!$E$2:$E$158,$A5) -> 7 | M5: =COUNTIFS(TestCases!$E$2:$E$158,$A5,TestCases!$V$2:$V$158,"Approve") -> 5 | N5: =COUNTIFS(TestCases!$E$2:$E$158,$A5,TestCases!$V$2:$V$158,"Draft") -> 2 | O5: =COUNTIFS(TestCases!$E$2:$E$158,$A5,TestCases!$V$2:$V$158,"Block") -> 0 | P5: =COUNTIFS(TestCases!$E$2:$E$158,$A5,TestCases!$V$2:$V$158,"Reject") -> 0 | Q5: =IF(P5=L5,"Reject",IF(O5>0,"Block",IF(N5>0,"Draft","Approve"))) -> Draft
A6: SCN-R1-05 | B6: CP-R1-05 | C6: R1 | D6: Education Account | E6: 1 | F6: Data Integrity | G6: EP | H6: One account per citizen | I6: The same NRIC never gets two accounts, whatever the job, rerun or account state | J6: FS 1.1.7, F01-AC06, F01-AC07, F01-AC12, F01-EF03 | K6: ASM-R1-33 | L6: =COUNTIFS(TestCases!$E$2:$E$158,$A6) -> 8 | M6: =COUNTIFS(TestCases!$E$2:$E$158,$A6,TestCases!$V$2:$V$158,"Approve") -> 7 | N6: =COUNTIFS(TestCases!$E$2:$E$158,$A6,TestCases!$V$2:$V$158,"Draft") -> 1 | O6: =COUNTIFS(TestCases!$E$2:$E$158,$A6,TestCases!$V$2:$V$158,"Block") -> 0 | P6: =COUNTIFS(TestCases!$E$2:$E$158,$A6,TestCases!$V$2:$V$158,"Reject") -> 0 | Q6: =IF(P6=L6,"Reject",IF(O6>0,"Block",IF(N6>0,"Draft","Approve"))) -> Draft
A7: SCN-R1-06 | B7: CP-R1-12 | C7: R1 | D7: Education Account | E7: 1 | F7: Boundary | G7: BVA | H7: Late records | I7: A record added to the dataset after the 7th birthday is not picked up by the Daily Job. Manual Account Creation and Bulk Re-synchronization handle it in the next sprint | J7: FS 1.1.1 B [TD, Deferred], 1.1.5 Notes [TD], section 4 [TD], register NEW-02 | K7: Question on Manual Account Creation and Bulk Re-synchronization, Question on late records | L7: =COUNTIFS(TestCases!$E$2:$E$158,$A7) -> 6 | M7: =COUNTIFS(TestCases!$E$2:$E$158,$A7,TestCases!$V$2:$V$158,"Approve") -> 4 | N7: =COUNTIFS(TestCases!$E$2:$E$158,$A7,TestCases!$V$2:$V$158,"Draft") -> 0 | O7: =COUNTIFS(TestCases!$E$2:$E$158,$A7,TestCases!$V$2:$V$158,"Block") -> 2 | P7: =COUNTIFS(TestCases!$E$2:$E$158,$A7,TestCases!$V$2:$V$158,"Reject") -> 0 | Q7: =IF(P7=L7,"Reject",IF(O7>0,"Block",IF(N7>0,"Draft","Approve"))) -> Block
A8: SCN-R1-07 | B8: CP-R1-10 | C8: R1 | D8: Education Account | E8: 1 | F8: Negative | G8: EP | H8: Invalid or missing citizen data | I8: A record without required data creates no account. A record without optional data still creates one. Where the exception is recorded is an open question | J8: FS 1.1.3, F01-EF02, F01-AC08, F01-AC09, 1.1.4 step 5 and Implementation Notes [TD] | K8: ASM-R1-30, Question on exception record | L8: =COUNTIFS(TestCases!$E$2:$E$158,$A8) -> 14 | M8: =COUNTIFS(TestCases!$E$2:$E$158,$A8,TestCases!$V$2:$V$158,"Approve") -> 11 | N8: =COUNTIFS(TestCases!$E$2:$E$158,$A8,TestCases!$V$2:$V$158,"Draft") -> 2 | O8: =COUNTIFS(TestCases!$E$2:$E$158,$A8,TestCases!$V$2:$V$158,"Block") -> 1 | P8: =COUNTIFS(TestCases!$E$2:$E$158,$A8,TestCases!$V$2:$V$158,"Reject") -> 0 | Q8: =IF(P8=L8,"Reject",IF(O8>0,"Block",IF(N8>0,"Draft","Approve"))) -> Block
A9: SCN-R1-08 | B9: CP-R1-12 | C9: R1 | D9: Education Account | E9: 1 | F9: Boundary | G9: BVA | H9: Leap day births | I9: A citizen born on 29 February follows the leap day rule | J9: FS 1.1.6 Leap Year Handling [WA], F01-AC14 [WA], F02-AC15 [WA], register TBD-01 | K9: ASM-R1-22, Question on leap rule in F02 | L9: =COUNTIFS(TestCases!$E$2:$E$158,$A9) -> 5 | M9: =COUNTIFS(TestCases!$E$2:$E$158,$A9,TestCases!$V$2:$V$158,"Approve") -> 4 | N9: =COUNTIFS(TestCases!$E$2:$E$158,$A9,TestCases!$V$2:$V$158,"Draft") -> 1 | O9: =COUNTIFS(TestCases!$E$2:$E$158,$A9,TestCases!$V$2:$V$158,"Block") -> 0 | P9: =COUNTIFS(TestCases!$E$2:$E$158,$A9,TestCases!$V$2:$V$158,"Reject") -> 0 | Q9: =IF(P9=L9,"Reject",IF(O9>0,"Block",IF(N9>0,"Draft","Approve"))) -> Draft
A10: SCN-R1-09 | B10: CP-R1-11 | C10: R1 | D10: Education Account | E10: 1 | F10: Workflow | G10: EP | H10: Citizen data intake | I10: Both synchronizations read the Mock Government Citizen API with the credential and select the right citizens, and a bad record does not stop the others | J10: FS 1.1.1, 1.1.2, 1.1.4, 1.1.5, 1.1.9 (next sprint) | K10: Question on job recovery, Question on weekly frequency | L10: =COUNTIFS(TestCases!$E$2:$E$158,$A10) -> 7 | M10: =COUNTIFS(TestCases!$E$2:$E$158,$A10,TestCases!$V$2:$V$158,"Approve") -> 5 | N10: =COUNTIFS(TestCases!$E$2:$E$158,$A10,TestCases!$V$2:$V$158,"Draft") -> 0 | O10: =COUNTIFS(TestCases!$E$2:$E$158,$A10,TestCases!$V$2:$V$158,"Block") -> 2 | P10: =COUNTIFS(TestCases!$E$2:$E$158,$A10,TestCases!$V$2:$V$158,"Reject") -> 0 | Q10: =IF(P10=L10,"Reject",IF(O10>0,"Block",IF(N10>0,"Draft","Approve"))) -> Block
A11: SCN-R1-10 | B11: CP-R1-12 | C11: R1 | D11: Education Account | E11: 1 | F11: Sequence | G11: StateTransition | H11: Daily run at 00:00 | I11: No account exists before the midnight run and it exists after it. The job runs once a day | J11: FS 1.1.2 Execution Time [WA], Execution Frequency [TD] | K11: ASM-R1-24 | L11: =COUNTIFS(TestCases!$E$2:$E$158,$A11) -> 3 | M11: =COUNTIFS(TestCases!$E$2:$E$158,$A11,TestCases!$V$2:$V$158,"Approve") -> 1 | N11: =COUNTIFS(TestCases!$E$2:$E$158,$A11,TestCases!$V$2:$V$158,"Draft") -> 2 | O11: =COUNTIFS(TestCases!$E$2:$E$158,$A11,TestCases!$V$2:$V$158,"Block") -> 0 | P11: =COUNTIFS(TestCases!$E$2:$E$158,$A11,TestCases!$V$2:$V$158,"Reject") -> 0 | Q11: =IF(P11=L11,"Reject",IF(O11>0,"Block",IF(N11>0,"Draft","Approve"))) -> Draft
A12: SCN-R1-11 | B12: CP-R1-06 | C12: R1 | D12: Education Account | E12: 1 | F12: State | G12: EP | H12: Account does not depend on school status | I12: School transfer, no school record, held back year, drop out and Student Profile Status do not decide the account | J12: FS F01-BR03, F01-BR04, F01-AC10, F02-BR07, register TBD-02 | K12: ASM-R1-17, ASM-R1-35 | L12: =COUNTIFS(TestCases!$E$2:$E$158,$A12) -> 5 | M12: =COUNTIFS(TestCases!$E$2:$E$158,$A12,TestCases!$V$2:$V$158,"Approve") -> 3 | N12: =COUNTIFS(TestCases!$E$2:$E$158,$A12,TestCases!$V$2:$V$158,"Draft") -> 2 | O12: =COUNTIFS(TestCases!$E$2:$E$158,$A12,TestCases!$V$2:$V$158,"Block") -> 0 | P12: =COUNTIFS(TestCases!$E$2:$E$158,$A12,TestCases!$V$2:$V$158,"Reject") -> 0 | Q12: =IF(P12=L12,"Reject",IF(O12>0,"Block",IF(N12>0,"Draft","Approve"))) -> Draft
A13: SCN-R1-12 | B13: CP-R1-17 | C13: R1 | D13: Education Account | E13: 1 | F13: Business Risk | G13: EP | H13: Account is not a login account | I13: Creating an account creates no sign in for the student | J13: Client clarification CD-01 | K13: N/A | L13: =COUNTIFS(TestCases!$E$2:$E$158,$A13) -> 1 | M13: =COUNTIFS(TestCases!$E$2:$E$158,$A13,TestCases!$V$2:$V$158,"Approve") -> 1 | N13: =COUNTIFS(TestCases!$E$2:$E$158,$A13,TestCases!$V$2:$V$158,"Draft") -> 0 | O13: =COUNTIFS(TestCases!$E$2:$E$158,$A13,TestCases!$V$2:$V$158,"Block") -> 0 | P13: =COUNTIFS(TestCases!$E$2:$E$158,$A13,TestCases!$V$2:$V$158,"Reject") -> 0 | Q13: =IF(P13=L13,"Reject",IF(O13>0,"Block",IF(N13>0,"Draft","Approve"))) -> Approve
... A33: SCN-R1-32 | B33: CP-R1-25 | C33: R1 | D33: Education Account | E33: 1 | F33: Data Integrity | G33: EP | H33: Student data stays as stored | I33: Student data is stored at account creation. The Daily Job and the closure check do not refresh it, and R1 does not rescan a student after a Government update | J33: FS F01-AC16, F02-AC13, F02-BR13 [TD], F02-EF05, 1.1.1 (Cross-Function Dependency R8), 1.2.6 [TD] | K33: N/A | L33: =COUNTIFS(TestCases!$E$2:$E$158,$A33) -> 4 | M33: =COUNTIFS(TestCases!$E$2:$E$158,$A33,TestCases!$V$2:$V$158,"Approve") -> 4 | N33: =COUNTIFS(TestCases!$E$2:$E$158,$A33,TestCases!$V$2:$V$158,"Draft") -> 0 | O33: =COUNTIFS(TestCases!$E$2:$E$158,$A33,TestCases!$V$2:$V$158,"Block") -> 0 | P33: =COUNTIFS(TestCases!$E$2:$E$158,$A33,TestCases!$V$2:$V$158,"Reject") -> 0 | Q33: =IF(P33=L33,"Reject",IF(O33>0,"Block",IF(N33>0,"Draft","Approve"))) -> Approve

Sheet Checkpoint
A1: CP ID | B1: Source | C1: Requirement (Tender clause) | D1: Point to test | E1: FS R1 V1.0 items | F1: Module | G1: Sprint | H1: Flag | I1: Test case can be generated | J1: Open ASM and questions | K1: Expected test case status | L1: Short reason | M1: TC IDs | N1: Defect IDs | O1: Approve | P1: Draft | Q1: Block | R1: Reject
A2: CP-R1-01 | B2: Tender R1, FS F01-BR01 [CR], register NEW-03, NEW-04 | C2: R1.1 Education Accounts are for Singapore Citizens only. Dual citizens count as Singaporean. A citizen studying overseas still gets an account. | D2: Only Singapore Citizens, including dual citizens, get an account. Permanent Residents and foreign students do not. | E2: F01-BR01, F01-AC03, F01-AF01, 2.1 rules | F2: Education Account | G2: 1 | H2: =IF(OR(Q2>0,AND(R2>0,O2+P2+Q2=0)),"Open",IF(P2>0,"Assumed","Clear")) -> Assumed | I2: =IF(COUNTIFS(TestCases!$R$2:$R$158,$A2,TestCases!$V$2:$V$158,"<>Reject")>0,"Yes","No") -> Yes | J2: ASM-R1-31 | K2: =IF(O2+P2+Q2=0,"Reject",IF(Q2>0,"Block",IF(P2>0,"Draft","Approve"))) -> Draft | L2: The FS and the register state who is eligible. How a dual citizen is shown is assumed. | M2: TC-R1-03-01, TC-R1-03-02, TC-R1-03-03, TC-R1-03-04, TC-R1-03-05 | N2: N/A | O2: =COUNTIFS(TestCases!$R$2:$R$158,$A2,TestCases!$V$2:$V$158,"Approve") -> 4 | P2: =COUNTIFS(TestCases!$R$2:$R$158,$A2,TestCases!$V$2:$V$158,"Draft") -> 1 | Q2: =COUNTIFS(TestCases!$R$2:$R$158,$A2,TestCases!$V$2:$V$158,"Block") -> 0 | R2: =COUNTIFS(TestCases!$R$2:$R$158,$A2,TestCases!$V$2:$V$158,"Reject") -> 0
A3: CP-R1-02 | B3: Tender R1, FS 1.1.1 [CR], F01-BR02, F01-BR05 | C3: R1.2 The account is created and activated automatically when the child turns 7. | D3: The account appears on the 7th birthday, not before, and not for citizens outside the age range. | E3: F01-AC02, F01-AC04, F01-AC05, F01-BR02, F01-BR05, 1.1.6 examples | F3: Education Account | G3: 1 | H3: =IF(OR(Q3>0,AND(R3>0,O3+P3+Q3=0)),"Open",IF(P3>0,"Assumed","Clear")) -> Clear | I3: =IF(COUNTIFS(TestCases!$R$2:$R$158,$A3,TestCases!$V$2:$V$158,"<>Reject")>0,"Yes","No") -> Yes | J3: Question on 16th birthday rule | K3: =IF(O3+P3+Q3=0,"Reject",IF(Q3>0,"Block",IF(P3>0,"Draft","Approve"))) -> Approve | L3: The FS gives the age rule and dated examples. | M3: TC-R1-01-01, TC-R1-01-02, TC-R1-02-01, TC-R1-02-02, TC-R1-02-03 | N3: N/A | O3: =COUNTIFS(TestCases!$R$2:$R$158,$A3,TestCases!$V$2:$V$158,"Approve") -> 5 | P3: =COUNTIFS(TestCases!$R$2:$R$158,$A3,TestCases!$V$2:$V$158,"Draft") -> 0 | Q3: =COUNTIFS(TestCases!$R$2:$R$158,$A3,TestCases!$V$2:$V$158,"Block") -> 0 | R3: =COUNTIFS(TestCases!$R$2:$R$158,$A3,TestCases!$V$2:$V$158,"Reject") -> 0
A4: CP-R1-03 | B4: Register TBD-15, FS 1.1.8, F01-AC01 | C4: R1.3 A new account starts Active with a zero balance. | D4: Opening state, balance, currency, account number, holder link and creation date of a new account. | E4: 1.1.4 steps 6 to 9, 1.1.5 steps 8 to 11, 1.1.8, 2.2, 2.3 Scope Note | F4: Education Account | G4: 1 | H4: =IF(OR(Q4>0,AND(R4>0,O4+P4+Q4=0)),"Open",IF(P4>0,"Assumed","Clear")) -> Assumed | I4: =IF(COUNTIFS(TestCases!$R$2:$R$158,$A4,TestCases!$V$2:$V$158,"<>Reject")>0,"Yes","No") -> Yes | J4: ASM-R1-34, ASM-R1-36 | K4: =IF(O4+P4+Q4=0,"Reject",IF(Q4>0,"Block",IF(P4>0,"Draft","Approve"))) -> Draft | L4: The flow steps and the 1.1.8 table state the opening values. The opening transaction and the profile of a Permanent Resident are assumptions. | M4: TC-R1-04-01, TC-R1-04-02, TC-R1-04-03, TC-R1-04-04, TC-R1-04-05, TC-R1-04-06, TC-R1-04-07 | N4: N/A | O4: =COUNTIFS(TestCases!$R$2:$R$158,$A4,TestCases!$V$2:$V$158,"Approve") -> 5 | P4: =COUNTIFS(TestCases!$R$2:$R$158,$A4,TestCases!$V$2:$V$158,"Draft") -> 2 | Q4: =COUNTIFS(TestCases!$R$2:$R$158,$A4,TestCases!$V$2:$V$158,"Block") -> 0 | R4: =COUNTIFS(TestCases!$R$2:$R$158,$A4,TestCases!$V$2:$V$158,"Reject") -> 0
A5: CP-R1-04 | B5: Tender R1, FS F02-BR01 [CR] | C5: R1.4 The account is closed automatically when the child reaches 16. | D5: On a backend access the account is Active before the 16th birthday and Closed from it. | E5: F02-BR01, F02-BR02, F02-AC01 to F02-AC03, 1.2.3, 1.2.5 | F5: Education Account | G5: 1 | H5: =IF(OR(Q5>0,AND(R5>0,O5+P5+Q5=0)),"Open",IF(P5>0,"Assumed","Clear")) -> Clear | I5: =IF(COUNTIFS(TestCases!$R$2:$R$158,$A5,TestCases!$V$2:$V$158,"<>Reject")>0,"Yes","No") -> Yes | J5: Question on 16th birthday rule | K5: =IF(O5+P5+Q5=0,"Reject",IF(Q5>0,"Block",IF(P5>0,"Draft","Approve"))) -> Approve | L5: The 16th birthday is [CR]. Closure happens at a backend access [TD]. | M5: TC-R1-13-01, TC-R1-13-02, TC-R1-13-03 | N5: N/A | O5: =COUNTIFS(TestCases!$R$2:$R$158,$A5,TestCases!$V$2:$V$158,"Approve") -> 3 | P5: =COUNTIFS(TestCases!$R$2:$R$158,$A5,TestCases!$V$2:$V$158,"Draft") -> 0 | Q5: =COUNTIFS(TestCases!$R$2:$R$158,$A5,TestCases!$V$2:$V$158,"Block") -> 0 | R5: =COUNTIFS(TestCases!$R$2:$R$158,$A5,TestCases!$V$2:$V$158,"Reject") -> 0
A6: CP-R1-05 | B6: Tender R1, FS 1.1.7 [CR] [TD] | C6: R1.5 Each citizen has one Education Account. A rerun creates no duplicate. | D6: No second account for the same NRIC, whatever the job, rerun or account state. | E6: 1.1.7 table, F01-AC06, F01-AC07, F01-AC12, F01-AF03, F01-EF03 | F6: Education Account | G6: 1 | H6: =IF(OR(Q6>0,AND(R6>0,O6+P6+Q6=0)),"Open",IF(P6>0,"Assumed","Clear")) -> Assumed | I6: =IF(COUNTIFS(TestCases!$R$2:$R$158,$A6,TestCases!$V$2:$V$158,"<>Reject")>0,"Yes","No") -> Yes | J6: ASM-R1-33 | K6: =IF(O6+P6+Q6=0,"Reject",IF(Q6>0,"Block",IF(P6>0,"Draft","Approve"))) -> Draft | L6: One account per citizen is [CR]. Conflicting records are an assumption. | M6: TC-R1-05-01, TC-R1-05-02, TC-R1-05-03, TC-R1-05-04, TC-R1-05-05, TC-R1-05-06, TC-R1-05-07, TC-R1-05-08 | N6: N/A | O6: =COUNTIFS(TestCases!$R$2:$R$158,$A6,TestCases!$V$2:$V$158,"Approve") -> 7 | P6: =COUNTIFS(TestCases!$R$2:$R$158,$A6,TestCases!$V$2:$V$158,"Draft") -> 1 | Q6: =COUNTIFS(TestCases!$R$2:$R$158,$A6,TestCases!$V$2:$V$158,"Block") -> 0 | R6: =COUNTIFS(TestCases!$R$2:$R$158,$A6,TestCases!$V$2:$V$158,"Reject") -> 0
A7: CP-R1-06 | B7: Client clarification CD-06, FS F01-BR03, F01-BR04, F02-BR07 | C7: R1.6 The account does not depend on schooling status, school enrolment or school transfer. | D7: School transfer, class change, held back year, no school record and Student Profile Status do not decide the account. | E7: F01-BR03, F01-BR04, F01-AC10, F02-BR07, 1.1.3 note | F7: Education Account | G7: 1 | H7: =IF(OR(Q7>0,AND(R7>0,O7+P7+Q7=0)),"Open",IF(P7>0,"Assumed","Clear")) -> Assumed | I7: =IF(COUNTIFS(TestCases!$R$2:$R$158,$A7,TestCases!$V$2:$V$158,"<>Reject")>0,"Yes","No") -> Yes | J7: ASM-R1-17, ASM-R1-35 | K7: =IF(O7+P7+Q7=0,"Reject",IF(Q7>0,"Block",IF(P7>0,"Draft","Approve"))) -> Draft | L7: The independence from schooling is stated in the FS (F01-BR03, F01-BR04, F02-BR07). The drop out and the profile status cases are assumptions. | M7: TC-R1-11-01, TC-R1-11-02, TC-R1-11-03, TC-R1-11-04, TC-R1-11-05 | N7: N/A | O7: =COUNTIFS(TestCases!$R$2:$R$158,$A7,TestCases!$V$2:$V$158,"Approve") -> 3 | P7: =COUNTIFS(TestCases!$R$2:$R$158,$A7,TestCases!$V$2:$V$158,"Draft") -> 2 | Q7: =COUNTIFS(TestCases!$R$2:$R$158,$A7,TestCases!$V$2:$V$158,"Block") -> 0 | R7: =COUNTIFS(TestCases!$R$2:$R$158,$A7,TestCases!$V$2:$V$158,"Reject") -> 0
A8: CP-R1-07 | B8: CD-02, register TBD-05, FS 1.2.7 [CR] and [Deferred], first FS F03 | C8: R1.7 At closure the remaining balance is transferred to CPF. A mock API is acceptable. | D8: The remaining balance goes to CPF through the Mock CPF Service, a CPF Transfer Record keeps the result, and a failure, a retry or an interruption never loses or duplicates money. | E8: 1.2.7, F02-AC10, section 4 item 3, first FS F03-BR01 to BR07, F03-AC01 to AC04, 2.4 | F8: Education Account | G8: 1 | H8: =IF(OR(Q8>0,AND(R8>0,O8+P8+Q8=0)),"Open",IF(P8>0,"Assumed","Clear")) -> Assumed | I8: =IF(COUNTIFS(TestCases!$R$2:$R$158,$A8,TestCases!$V$2:$V$158,"<>Reject")>0,"Yes","No") -> Yes | J8: ASM-R1-41, ASM-R1-42, ASM-R1-43, ASM-R1-44, ASM-R1-45, ASM-R1-46, Question on CPF delivery | K8: =IF(O8+P8+Q8=0,"Reject",IF(Q8>0,"Block",IF(P8>0,"Draft","Approve"))) -> Draft | L8: FS R1 V1.0 defers the transfer. The QA lead keeps F03 of the first FS as the rule, so the cases are Draft and wait for the delivery sprint. | M8: TC-R1-14-01, TC-R1-14-02, TC-R1-14-03, TC-R1-14-04, TC-R1-14-05, TC-R1-14-06, TC-R1-14-07, TC-R1-14-08, TC-R1-14-09, TC-R1-14-10, TC-R1-14-11, TC-R1-14-12 | N8: N/A | O8: =COUNTIFS(TestCases!$R$2:$R$158,$A8,TestCases!$V$2:$V$158,"Approve") -> 1 | P8: =COUNTIFS(TestCases!$R$2:$R$158,$A8,TestCases!$V$2:$V$158,"Draft") -> 11 | Q8: =COUNTIFS(TestCases!$R$2:$R$158,$A8,TestCases!$V$2:$V$158,"Block") -> 0 | R8: =COUNTIFS(TestCases!$R$2:$R$158,$A8,TestCases!$V$2:$V$158,"Reject") -> 0
A9: CP-R1-08 | B9: CD-02, FS 1.2.2 [TD], F02-BR09 [TD] | C9: R1.8 There should be no pending transactions at closure. | D9: Closure behaviour when a transaction is pending. | E9: 1.2.2, 1.2.7, F02-BR09 | F9: Education Account | G9: TBD | H9: =IF(OR(Q9>0,AND(R9>0,O9+P9+Q9=0)),"Open",IF(P9>0,"Assumed","Clear")) -> Open | I9: =IF(COUNTIFS(TestCases!$R$2:$R$158,$A9,TestCases!$V$2:$V$158,"<>Reject")>0,"Yes","No") -> No | J9: Question on pending transactions | K9: =IF(O9+P9+Q9=0,"Reject",IF(Q9>0,"Block",IF(P9>0,"Draft","Approve"))) -> Reject | L9: The team assumes none exist and builds no reconciliation. | M9: TC-R1-15-01, TC-R1-15-02 | N9: N/A | O9: =COUNTIFS(TestCases!$R$2:$R$158,$A9,TestCases!$V$2:$V$158,"Approve") -> 0 | P9: =COUNTIFS(TestCases!$R$2:$R$158,$A9,TestCases!$V$2:$V$158,"Draft") -> 0 | Q9: =COUNTIFS(TestCases!$R$2:$R$158,$A9,TestCases!$V$2:$V$158,"Block") -> 0 | R9: =COUNTIFS(TestCases!$R$2:$R$158,$A9,TestCases!$V$2:$V$158,"Reject") -> 2
A10: CP-R1-09 | B10: Register NEW-01 | C10: R1.9 Unpaid fees do not block closure. | D10: Closure when the student has an unpaid fee. | E10: Not in FS V1.0, register NEW-01 | F10: Education Account | G10: 1 | H10: =IF(OR(Q10>0,AND(R10>0,O10+P10+Q10=0)),"Open",IF(P10>0,"Assumed","Clear")) -> Assumed | I10: =IF(COUNTIFS(TestCases!$R$2:$R$158,$A10,TestCases!$V$2:$V$158,"<>Reject")>0,"Yes","No") -> Yes | J10: ASM-R1-42, Question on CPF delivery, Question on unpaid fees | K10: =IF(O10+P10+Q10=0,"Reject",IF(Q10>0,"Block",IF(P10>0,"Draft","Approve"))) -> Draft | L10: The client confirmed that closure is not blocked. The CPF amount waits for the transfer. | M10: TC-R1-16-01, TC-R1-16-02 | N10: N/A | O10: =COUNTIFS(TestCases!$R$2:$R$158,$A10,TestCases!$V$2:$V$158,"Approve") -> 1 | P10: =COUNTIFS(TestCases!$R$2:$R$158,$A10,TestCases!$V$2:$V$158,"Draft") -> 1 | Q10: =COUNTIFS(TestCases!$R$2:$R$158,$A10,TestCases!$V$2:$V$158,"Block") -> 0 | R10: =COUNTIFS(TestCases!$R$2:$R$158,$A10,TestCases!$V$2:$V$158,"Reject") -> 0
A11: CP-R1-10 | B11: CD-03, FS 1.1.3, 2.1 | C11: R1.10 Account setup uses NRIC, name, date of birth, citizenship and gender. Missing or invalid required data creates no account and an exception is recorded. | D11: Required and optional data, and the handling of invalid data. | E11: 1.1.3 Required Data Validation, F01-EF02, F01-AC08, F01-AC09, 1.1.4 step 5, 2.1 Business Rules | F11: Education Account | G11: 1 | H11: =IF(OR(Q11>0,AND(R11>0,O11+P11+Q11=0)),"Open",IF(P11>0,"Assumed","Clear")) -> Open | I11: =IF(COUNTIFS(TestCases!$R$2:$R$158,$A11,TestCases!$V$2:$V$158,"<>Reject")>0,"Yes","No") -> Yes | J11: ASM-R1-30, Question on exception record | K11: =IF(O11+P11+Q11=0,"Reject",IF(Q11>0,"Block",IF(P11>0,"Draft","Approve"))) -> Block | L11: Most rules are stated. The place where the exception is recorded conflicts inside the FS (see the question on the exception record). Gender and the value lists need confirmation. | M11: TC-R1-07-01, TC-R1-07-02, TC-R1-07-03, TC-R1-07-04, TC-R1-07-05, TC-R1-07-06, TC-R1-07-07, TC-R1-07-08, TC-R1-07-09, TC-R1-07-10, TC-R1-07-11, TC-R1-07-12, TC-R1-07-13, TC-R1-07-14 | N11: N/A | O11: =COUNTIFS(TestCases!$R$2:$R$158,$A11,TestCases!$V$2:$V$158,"Approve") -> 11 | P11: =COUNTIFS(TestCases!$R$2:$R$158,$A11,TestCases!$V$2:$V$158,"Draft") -> 2 | Q11: =COUNTIFS(TestCases!$R$2:$R$158,$A11,TestCases!$V$2:$V$158,"Block") -> 1 | R11: =COUNTIFS(TestCases!$R$2:$R$158,$A11,TestCases!$V$2:$V$158,"Reject") -> 0
A12: CP-R1-11 | B12: Register NEW-02, FS 1.1.2, 1.1.4, 1.1.5 | C12: R1.11 Citizenship data comes from the government source. The FS uses a Mock Government Citizen API with an API credential. | D12: Both synchronizations read the Mock Government Citizen API with the credential and select the right citizens. | E12: 1.1.1, 1.1.2, 1.1.4, 1.1.5, F01-AC01, F01-AC02 | F12: Education Account | G12: 1 | H12: =IF(OR(Q12>0,AND(R12>0,O12+P12+Q12=0)),"Open",IF(P12>0,"Assumed","Clear")) -> Open | I12: =IF(COUNTIFS(TestCases!$R$2:$R$158,$A12,TestCases!$V$2:$V$158,"<>Reject")>0,"Yes","No") -> Yes | J12: Question on job recovery, Question on weekly frequency | K12: =IF(O12+P12+Q12=0,"Reject",IF(Q12>0,"Block",IF(P12>0,"Draft","Approve"))) -> Block | L12: The mechanism is a team decision [TD]. Weekly frequency conflicts with the register. The recovery rules of 1.1.9 are next sprint. | M12: TC-R1-09-01, TC-R1-09-02, TC-R1-09-03, TC-R1-09-04, TC-R1-09-05, TC-R1-09-06, TC-R1-09-07 | N12: N/A | O12: =COUNTIFS(TestCases!$R$2:$R$158,$A12,TestCases!$V$2:$V$158,"Approve") -> 5 | P12: =COUNTIFS(TestCases!$R$2:$R$158,$A12,TestCases!$V$2:$V$158,"Draft") -> 0 | Q12: =COUNTIFS(TestCases!$R$2:$R$158,$A12,TestCases!$V$2:$V$158,"Block") -> 2 | R12: =COUNTIFS(TestCases!$R$2:$R$158,$A12,TestCases!$V$2:$V$158,"Reject") -> 0
A13: CP-R1-12 | B13: FS 1.1.1 B, 1.1.2, 1.1.5, 1.1.6 [WA], section 4, register TBD-01 | C13: R1.12 Eligibility is evaluated daily. A 29 February birth follows a leap day rule. | D13: Daily schedule, weekends, holidays, missed days, late records and the leap day rule. | E13: 1.1.1 B, 1.1.2, 1.1.5, 1.1.9 (next sprint), section 4, F01-AC13, F01-AC14, 1.1.6 Leap Year Handling | F13: Education Account | G13: 1 | H13: =IF(OR(Q13>0,AND(R13>0,O13+P13+Q13=0)),"Open",IF(P13>0,"Assumed","Clear")) -> Open | I13: =IF(COUNTIFS(TestCases!$R$2:$R$158,$A13,TestCases!$V$2:$V$158,"<>Reject")>0,"Yes","No") -> Yes | J13: ASM-R1-22, ASM-R1-24, Question on Manual Account Creation and Bulk Re-synchronization, Question on job recovery, Question on late records, Question on leap rule in F02 | K13: =IF(O13+P13+Q13=0,"Reject",IF(Q13>0,"Block",IF(P13>0,"Draft","Approve"))) -> Block | L13: Weekends and holidays have no tag now. The run time and the leap rule are [WA]. Late records and missed days are next sprint (Deferred) and those cases are Block. | M13: TC-R1-06-01, TC-R1-06-02, TC-R1-06-03, TC-R1-06-04, TC-R1-06-05, TC-R1-06-06, TC-R1-08-01, TC-R1-08-02, TC-R1-08-03, TC-R1-08-04, TC-R1-08-05, TC-R1-10-01, TC-R1-10-02, TC-R1-10-03, TC-R1-25-01, TC-R1-25-02, TC-R1-25-03, TC-R1-25-04 | N13: N/A | O13: =COUNTIFS(TestCases!$R$2:$R$158,$A13,TestCases!$V$2:$V$158,"Approve") -> 11 | P13: =COUNTIFS(TestCases!$R$2:$R$158,$A13,TestCases!$V$2:$V$158,"Draft") -> 3 | Q13: =COUNTIFS(TestCases!$R$2:$R$158,$A13,TestCases!$V$2:$V$158,"Block") -> 4 | R13: =COUNTIFS(TestCases!$R$2:$R$158,$A13,TestCases!$V$2:$V$158,"Reject") -> 0
... A26: CP-R1-25 | B26: FS R1 V1.0 F01-AC16, F02-AC13, F02-BR13 [TD], 1.1.1, 1.2.6 | C26: R1.25 Student data is stored at account creation. The Daily Job and the closure check do not refresh it (FS R1 V1.0 only, not in the tender). | D26: A Government update of the address, gender, name, race or parent NRIC after creation is not copied into the Student Profile by the Daily Job or by the closure check. | E26: F01-AC16, F02-AC13, F02-BR13, F02-EF05, 1.1.1 Cross-Function Dependency R8, 1.2.3 Notes, 1.2.6 | F26: Education Account | G26: 1 | H26: =IF(OR(Q26>0,AND(R26>0,O26+P26+Q26=0)),"Open",IF(P26>0,"Assumed","Clear")) -> Clear | I26: =IF(COUNTIFS(TestCases!$R$2:$R$158,$A26,TestCases!$V$2:$V$158,"<>Reject")>0,"Yes","No") -> Yes | J26: ASM-R1-01 only | K26: =IF(O26+P26+Q26=0,"Reject",IF(Q26>0,"Block",IF(P26>0,"Draft","Approve"))) -> Approve | L26: The FS states the boundary with untagged criteria and team decisions. | M26: TC-R1-32-01, TC-R1-32-02, TC-R1-32-03, TC-R1-32-04 | N26: N/A | O26: =COUNTIFS(TestCases!$R$2:$R$158,$A26,TestCases!$V$2:$V$158,"Approve") -> 4 | P26: =COUNTIFS(TestCases!$R$2:$R$158,$A26,TestCases!$V$2:$V$158,"Draft") -> 0 | Q26: =COUNTIFS(TestCases!$R$2:$R$158,$A26,TestCases!$V$2:$V$158,"Block") -> 0 | R26: =COUNTIFS(TestCases!$R$2:$R$158,$A26,TestCases!$V$2:$V$158,"Reject") -> 0

Sheet Assumptions
A1: ASM ID | B1: Type | C1: Requirement | D1: Original gap | E1: Assumption | F1: Source (as in Assumption Ref) | G1: Source detail | H1: Reason | I1: If the answer differs | J1: State | K1: Resolution | L1: Cases that make this assumption (Assumption Ref) | M1: Other cases that depend on it (Dependency Ref) | N1: Question to confirm
A2: ASM-R1-01 | B2: Dependency | C2: All R1 cases | D2: FS R1 V1.0 does not describe the test environment, the Mock Government Citizen API controls or how a backend action is triggered. | E2: The SIT environment is ready. QA can (1) run the Initial Synchronization and the Daily Job for a chosen business date and time, and run the Initial Synchronization again; (2) load records into the Mock Government Citizen API and set it to succeed, reject the credential, time out or fail, and change the data of a record; (3) send the backend requests that read or process an account (parent view, balance and history view, MOE HQ retrieval, Top-Up, Payment, Batch Top-Up), as API calls where a screen or function is not built; (4) seed an account with a status, balance, fee record and transactions; (5) read the job log (Job Failure and errors) and the request log of the Mock Government Citizen API; (6) read the stored status of an account and the stored Student Profile without making a backend access; (7) inject a failure while an account is created or closed or a transaction is posted. | F2: FS 1.1.2 | G2: FS 1.1.2 Sprint 1 Integration: Mock Government Citizen API [TD]. Register TBD-14 (mock integrations acceptable). Sprint Backlog TSK-R1-03. | H2: A test cannot start without an environment and the controls it needs. | I2: A case that needs a missing control moves to unit or API level, or becomes Block. | J2: Open | K2: None yet | L2: None | M2: 154 test cases, see the TestCases sheet | N2: Dev: To run the R1 test cases in SIT, QA needs to do seven things. Run the Initial Synchronization and the Daily Job for a date and time we choose, and run the Initial Synchronization again. Load citizen records into the Mock Government Citizen API and make it succeed, reject the credential, time out or fail. Send the backend requests that read or process an account (parent view, MOE HQ retrieval, Top-Up, Payment, Batch Top-Up) as API calls where there is no screen. Create an account with a chosen status, balance, fee and transactions. Read the job log and the request log of the Mock Government Citizen API. Read the stored status of an account and the stored Student Profile without opening the account. Make a failure happen while an account is created or closed or a transaction is posted. Is each of these possible in SIT, and what is the alternative for the ones that are not?
A3: ASM-R1-02 | B3: Data | C3: All R1 cases | D3: The FS gives examples with dates but the sprint test window needs fixed dates. | E3: Creation cases use the business date 15 Oct 2026. Closure cases use 28 Oct 2026. Dates of birth are set for those dates and shift together if another date is used. The tester sets the business date and starts the job by hand. | F3: Test data design | G3: Test plan 1.0.7 section 4.3. FS 1.1.6 and 1.2.5 give the same offsets (age 7 on the birthday, age 16 on the birthday). | H3: A boundary case needs a fixed date to be repeatable. | I3: Shift every date of birth by the same number of days. The expected results do not change. | J3: Resolved | K3: QA test data choice, no question | L3: None | M3: 141 test cases, see the TestCases sheet | N3: None
A4: ASM-R1-03 | B4: Data | C4: R1 age rules | D4: The tender says age 7 and age 16 but not how age is counted. | E4: Age is counted from the exact date of birth. A citizen is eligible from the 7th birthday up to the day before the 16th birthday. | F4: FS F01-BR02, 1.1.6 | G4: FS F01-BR02, F01-AC04, F01-AC05 and the age examples in 1.1.6 (DOB 15/06/2019: not eligible on 14/06/2026, eligible on 15/06/2026, no new account on 15/06/2035). | H4: The FS gives the rule and three dated examples. | I4: Not applicable, resolved. | J4: Resolved | K4: FS R1 V1.0, 1.1.6 age examples | L4: None | M4: TC-R1-01-01, TC-R1-01-02, TC-R1-02-01, TC-R1-02-02, TC-R1-02-03 | N4: None
A5: ASM-R1-04 | B5: Rule | C5: Tender R1 closure | D5: The tender says the account closes when the child reaches 16. The team lead said one day before the 16th birthday on 11 Oct. | E5: The account is due for closure on the 16th birthday itself. | F5: FS F02-BR01 [CR], 1.2.5 | G5: FS F02-BR01 [CR] and the example in 1.2.5 (DOB 10/10/2018: Active on 09/10/2034, closure on 10/10/2034). | H5: A client confirmed rule with a dated example. | I5: Not applicable, resolved. The team lead rule is not in the FS (see the question on the 16th birthday rule). | J5: Resolved | K5: FS F02-BR01 [CR] and 1.2.5 example | L5: None | M5: 44 test cases, see the TestCases sheet | N5: None
A6: ASM-R1-05 | B6: Dependency | C6: R1 not a login account | D6: The client says an Education Account is a financial account and not a login account. No way to check this is described. | E6: QA can list the sign in accounts of the SIT environment and see whether one is linked to the student. | F6: Client clarification CD-01 | G6: Client clarification CD-01. FS 1.1.2 Data Source Clarification says Singpass for parent login is a separate function. | H6: The rule is stated, only the way to observe it is missing. | I6: If sign in accounts cannot be listed, S12-01 is checked by trying to sign in with the student NRIC. | J6: Open | K6: None yet | L6: None | M6: TC-R1-12-01 | N6: Dev: The tender says the Education Account is a financial account and not a login account. How can QA check in SIT that no sign in account is created or linked to the student? For example, can QA read a list of the sign in accounts?
A7: ASM-R1-06 | B7: Rule | C7: R1 closure status | D7: Sources used the words closed, deactivated and inactive. | E7: Account Status has two values in the MVP: Active and Closed. | F7: FS 2.2 | G7: FS 2.2 Account Status 'gồm Active và Closed trong MVP'. | H7: The FS names the statuses. | I7: Not applicable, resolved. | J7: Resolved | K7: FS R1 V1.0, 2.2 | L7: None | M7: TC-R1-13-01, TC-R1-13-02, TC-R1-13-03 | N7: None
A8: ASM-R1-07 | B8: Rule | C8: R1 citizenship lost | D8: Citizenship lost before 16 was open in the register (TBD-04). The FS now closes the account and asks for business confirmation. | E8: When a backend access finds that the Account Holder is no longer a Singapore Citizen before 16, the System runs closure processing. With a balance of 0.00 the account becomes Closed and the Actual Closure Date is set. A Top-Up or Payment request on that account is not executed. The handling of a balance above 0.00 is not defined (open business decision). | F8: FS F02-BR05 [TD], F02-AC11 [TD], 1.2.6 | G8: FS F02-BR05 [TD, needs business or client confirmation], F02-AC11 [TD], F02-AF04, 1.2.5 example row 4 [TD], 1.2.6 [TD]. The 1.2.7 table and section 4 [Open Business Decision] say the handling of the remaining balance is not confirmed. | H8: The FS states the rule as a team decision and says the business has not confirmed it. | I8: If the account is not closed on loss of citizenship, S19-01 and S19-04 change and S19-03 is replaced. | J8: Open | K8: None yet | L8: TC-R1-19-01, TC-R1-19-04 | M8: TC-R1-19-03 | N8: BA: FS F02-BR05 and F02-AC11 close the account when the account holder is no longer a Singapore Citizen, and F02-BR05 says the business must confirm this. Is the closure confirmed? Where does a balance above 0.00 go (see the question on citizenship based closure balance)? Can the account be reopened if the citizenship is regained?
A9: ASM-R1-08 | B9: Rule | C9: R1 citizenship gained | D9: v1 assumed creation at the next feed run (register TBD-03). | E9: Superseded by FS section 4 [TD]: a citizen who gains citizenship after the Initial Synchronization is not added by the Daily Incremental Synchronization. | F9: FS section 4 [TD] | G9: FS section 4 Incremental Synchronization Scope [TD] and 1.1.5 Notes [TD]. | H9: The FS now states the behaviour. | I9: See the question on the conflict with register TBD-03. | J9: Superseded | K9: FS R1 V1.0, section 4 [TD] | L9: None | M9: None | N9: None
A10: ASM-R1-09 | B10: Rule | C10: R1 CPF transfer | D10: v1 assumed a mock CPF API. | E10: Superseded in v2.1 by the F03 carry over and the Mock CPF Service dependency. FS 1.2.7 still defers the transfer. | F10: FS 1.2.7 [Deferred] | G10: FS 1.2.7 and section 4 [Deferred] CPF Transfer. | H10: The FS defers the transfer. The QA lead keeps F03 of the first FS as the rule. | I10: See the questions on the F03 carry over and on the Mock CPF Service. | J10: Superseded | K10: Replaced by ASM-R1-42 and ASM-R1-47 on 14 Oct 2026 | L10: None | M10: None | N10: None
A11: ASM-R1-10 | B11: Rule | C11: R1 pending transactions | D11: v1 assumed that a pending transaction stops closure. | E11: The team assumes no pending transaction exists at closure and F02 builds no reconciliation. | F11: FS 1.2.2 [TD], F02-BR09 [TD] | G11: FS 1.2.2, 1.2.7 and F02-BR09. | H11: The FS now states the team assumption. | I11: See the question on pending transactions. | J11: Superseded | K11: FS R1 V1.0, F02-BR09 [TD] | L11: None | M11: None | N11: None
A12: ASM-R1-11 | B12: Rule | C12: R1 unpaid fees at closure | D12: v1 assumed that the whole balance goes to CPF when a fee is unpaid. | E12: Not adopted as an assumption of its own. Register NEW-01 says unpaid fees do not block closure. Case S16-02 follows F03-BR02 of the first FS, so the Transfer Amount is the whole Remaining Balance and no fee is deducted. | F12: Register NEW-01 | G12: Register NEW-01. FS R1 V1.0 is silent. First FS F03-BR02 has no fee term (searched the first FS for fee: no match). | H12: Whether the balance settles fees before the transfer stays a question. | I12: See the question on unpaid fees. | J12: Not adopted | K12: Kept as a question. Case S16-02 is Draft on ASM-R1-42 | L12: None | M12: None | N12: None
... A51: ASM-R1-50 | B51: Rule | C51: R1 Government API returns no valid record | D51: FS F02-EF02 and F02-BR14 say the account is not closed and a suitable error result is returned. They do not define the error result. | E51: When the Mock Government Citizen API returns no valid citizen record for the NRIC, the account stays Active and the backend action receives an error result. | F51: FS F02-EF02 [WA], F02-BR14 [WA] | G51: FS F02-EF02 [WA]: 'Không tự động đánh dấu Account Closed; trả kết quả lỗi phù hợp để backend action xử lý' and F02-BR14 [WA]. | H51: The FS tags both as working assumptions and does not name the error result. | I51: If the action goes on with the stored data, S30-07 changes. | J51: Open | K51: None yet | L51: TC-R1-30-07 | M51: None | N51: BA: FS F02-EF02 and F02-BR14 say that when the Government API returns no valid citizen record, the account is not closed and a suitable error result is returned. We assumed the account stays Active and the backend action receives an error result and stops. What error result is returned, and does a Top-Up or Payment stop?

Sheet Questions
A1: Assumption Ref | B1: Question | C1: Answer
A2: ASM-R1-01 | B2: Dev: To run the R1 test cases in SIT, QA needs to do seven things. Run the Initial Synchronization and the Daily Job for a date and time we choose, and run the Initial Synchronization again. Load citizen records into the Mock Government Citizen API and make it succeed, reject the credential, time out or fail. Send the backend requests that read or process an account (parent view, MOE HQ retrieval, Top-Up, Payment, Batch Top-Up) as API calls where there is no screen. Create an account with a chosen status, balance, fee and transactions. Read the job log and the request log of the Mock Government Citizen API. Read the stored status of an account and the stored Student Profile without opening the account. Make a failure happen while an account is created or closed or a transaction is posted. Is each of these possible in SIT, and what is the alternative for the ones that are not?
A3: ASM-R1-05 | B3: Dev: The tender says the Education Account is a financial account and not a login account. How can QA check in SIT that no sign in account is created or linked to the student? For example, can QA read a list of the sign in accounts?
A4: ASM-R1-07 | B4: BA: FS F02-BR05 and F02-AC11 close the account when the account holder is no longer a Singapore Citizen, and F02-BR05 says the business must confirm this. Is the closure confirmed? Where does a balance above 0.00 go (see the question on citizenship based closure balance)? Can the account be reopened if the citizenship is regained?
A5: ASM-R1-17 | B5: BA: A student leaves school before turning 16. We assumed the account stays Active, because F02-BR07 says school status does not affect closure. Is this correct, or should the account change in some way?
A6: ASM-R1-21 | B6: BA: FS 2.3 says a failed transaction does not change the balance and that a negative balance is not supported. We assumed a debit larger than the balance is refused and the balance stays the same. Is this correct, and what does the system return when it refuses the debit?
A7: ASM-R1-22 | B7: BA: FS 1.1.6 and F01-AC14 say a citizen born on 29 February turns 7 on 28 February in a non leap year. Register item TBD-01, which the client confirmed, says 1 March at 00:00. Which date is correct? We assumed 28 February, as the FS says.
A8: ASM-R1-23 | B8: Dev: After a day when the Daily Job did not run or failed, how does the next run find the days that were not processed, and which dates of birth does it send to the Mock Government Citizen API? We assumed the next run covers every unprocessed day and creates each account once. FS 1.1.9 is labelled next sprint.
A9: ASM-R1-24 | B9: BA: FS 1.1.2 says the Daily Job runs at 00:00 Singapore time, marked as a working assumption. We assumed a run at 00:00 on 15 October processes the citizens who turn 7 on 15 October. Is 00:00 confirmed, and which date does a run at that time use as the processing date?
A10: ASM-R1-26 | B10: PM: The FS header says account closure (F02) is part of Sprint 1, but PM backlog item PB-16 puts it in Sprint 3. In which sprint is closure built and tested? For now we label the closure cases Sprint 1.
A11: ASM-R1-28 | B11: BA: FS 1.1.9 (labelled next sprint) proposes that when the Government API times out, the job records the error and retries once after 15 minutes. If the retry also fails, the job is marked Failed and waits for the next scheduled run. Are these rules accepted? When a job stops halfway, how does it know which records it has already processed?
A12: ASM-R1-29 | B12: BA: FS 1.1.9 (labelled next sprint) says that if creating the account fails for one citizen record, the failure is recorded and no incomplete account is stored. We assumed the job also goes on with the next record (1.1.4 step 10). Is this correct?
A13: ASM-R1-30 | B13: BA: The FS marks Gender as required, as a working assumption. We assumed a record with an empty Gender, or a Gender outside the valid list, creates no account and is recorded as an exception. Is Gender required in the MVP, and which values are valid?
... A50: N/A | B50: BA, citizenship based closure balance: FS 1.2.7 and section 4 say the handling of the remaining balance for an account closed because of lost citizenship is not confirmed, and that the CPF Transfer rule of age based closure must not be used by default. What happens to a balance above 0.00 in this case? Test case TC-R1-19-03 has no steps until the business decides.

Sheet FS Trace
A1: FS item | B1: Tag in its FS | C1: Statement | D1: Test cases that cite it | E1: Count | F1: Covered | G1: Source FS
A2: F01-BR01 | B2: CR | C2: Only Singapore Citizens get an Education Account | D2: TC-R1-03-01, TC-R1-03-05, TC-R1-05-04 | E2: =IF(D2="None",0,(LEN(D2)-LEN(SUBSTITUTE(D2,"TC-R1","")))/5) -> 3 | F2: =IF(E2>0,"Yes","No") -> Yes | G2: FS R1 V1.0
A3: F01-BR02 | B3: None | C3: Eligible age from 7 to before 16 | D3: TC-R1-06-03 | E3: =IF(D3="None",0,(LEN(D3)-LEN(SUBSTITUTE(D3,"TC-R1","")))/5) -> 1 | F3: =IF(E3>0,"Yes","No") -> Yes | G3: FS R1 V1.0
A4: F01-BR03 | B4: None | C4: Age comes from DOB, not school level or schooling status | D4: TC-R1-11-03, TC-R1-11-04 | E4: =IF(D4="None",0,(LEN(D4)-LEN(SUBSTITUTE(D4,"TC-R1","")))/5) -> 2 | F4: =IF(E4>0,"Yes","No") -> Yes | G4: FS R1 V1.0
A5: F01-BR04 | B5: None | C5: Account creation does not depend on school enrolment | D5: TC-R1-11-01, TC-R1-11-02, TC-R1-11-05 | E5: =IF(D5="None",0,(LEN(D5)-LEN(SUBSTITUTE(D5,"TC-R1","")))/5) -> 3 | F5: =IF(E5>0,"Yes","No") -> Yes | G5: FS R1 V1.0
A6: F01-BR05 | B6: None | C6: A citizen aged 16 or more with no account gets none | D6: TC-R1-02-02, TC-R1-02-03, TC-R1-24-02 | E6: =IF(D6="None",0,(LEN(D6)-LEN(SUBSTITUTE(D6,"TC-R1","")))/5) -> 3 | F6: =IF(E6>0,"Yes","No") -> Yes | G6: FS R1 V1.0
A7: F01-AF01 | B7: None | C7: Not a Singapore Citizen: no account | D7: TC-R1-03-03, TC-R1-03-04 | E7: =IF(D7="None",0,(LEN(D7)-LEN(SUBSTITUTE(D7,"TC-R1","")))/5) -> 2 | F7: =IF(E7>0,"Yes","No") -> Yes | G7: FS R1 V1.0
A8: F01-AF02 | B8: None | C8: Under 7 or 16 and over: no account | D8: TC-R1-02-01, TC-R1-02-02 | E8: =IF(D8="None",0,(LEN(D8)-LEN(SUBSTITUTE(D8,"TC-R1","")))/5) -> 2 | F8: =IF(E8>0,"Yes","No") -> Yes | G8: FS R1 V1.0
A9: F01-AF03 | B9: None | C9: Already has an account, also Closed: skip creation | D9: TC-R1-05-06, TC-R1-19-02, TC-R1-24-03 | E9: =IF(D9="None",0,(LEN(D9)-LEN(SUBSTITUTE(D9,"TC-R1","")))/5) -> 3 | F9: =IF(E9>0,"Yes","No") -> Yes | G9: FS R1 V1.0
A10: F01-AF04 | B10: None | C10: No Father or Mother NRIC: account still created | D10: TC-R1-07-13 | E10: =IF(D10="None",0,(LEN(D10)-LEN(SUBSTITUTE(D10,"TC-R1","")))/5) -> 1 | F10: =IF(E10>0,"Yes","No") -> Yes | G10: FS R1 V1.0
A11: F01-EF01 | B11: None | C11: Government API authentication failure: Job Failure recorded | D11: TC-R1-26-01 | E11: =IF(D11="None",0,(LEN(D11)-LEN(SUBSTITUTE(D11,"TC-R1","")))/5) -> 1 | F11: =IF(E11>0,"Yes","No") -> Yes | G11: FS R1 V1.0
A12: F01-EF02 | B12: None | C12: Missing or invalid required data: no account, exception recorded | D12: TC-R1-07-01, TC-R1-07-02, TC-R1-07-03, TC-R1-07-14, TC-R1-09-03 | E12: =IF(D12="None",0,(LEN(D12)-LEN(SUBSTITUTE(D12,"TC-R1","")))/5) -> 5 | F12: =IF(E12>0,"Yes","No") -> Yes | G12: FS R1 V1.0
A13: F01-EF03 | B13: WA | C13: Duplicate citizen records with conflicting data: no duplicate, Data Conflict recorded | D13: TC-R1-05-05 | E13: =IF(D13="None",0,(LEN(D13)-LEN(SUBSTITUTE(D13,"TC-R1","")))/5) -> 1 | F13: =IF(E13>0,"Yes","No") -> Yes | G13: FS R1 V1.0
... A86: F02 BR10 (first FS) | B86: WA | C86: A retry or a repeated run never causes a duplicate closure or a duplicate CPF transfer | D86: TC-R1-14-09, TC-R1-14-10 | E86: =IF(D86="None",0,(LEN(D86)-LEN(SUBSTITUTE(D86,"TC-R1","")))/5) -> 2 | F86: =IF(E86>0,"Yes","No") -> Yes | G86: First FS (replaced)

Sheet Changes from v2.1
A1: Sheet | B1: ID | C1: Change | D1: Status v2.1 | E1: Status v2.2 | F1: What changed | G1: Why
A2: TestCases | B2: TC-R1-01-01 | C2: Changed | D2: Approve | E2: Approve | F2: Trace | G2: Step number updated: the Daily flow now creates the account in step 9.
A3: TestCases | B3: TC-R1-02-01 | C3: Changed | D3: Approve | E3: Approve | F3: Trace | G3: Step number updated: the Initial query now selects the age range in step 2.
A4: TestCases | B4: TC-R1-04-01 | C4: Changed | D4: Approve | E4: Approve | F4: Trace, Reason | G4: The Currency row of the 1.1.8 table was removed. Currency SGD is now cited from the flow steps.
A5: TestCases | B5: TC-R1-04-02 | C5: Changed | D5: Approve | E5: Approve | F5: Trace, Reason | G5: Step number updated.
A6: TestCases | B6: TC-R1-04-03 | C6: Changed | D6: Approve | E6: Approve | F6: Title, Steps, Expected, Trace, Reason | G6: The 1.1.8 table lost the Creation Date and Closure Date rows. The empty closure date check is dropped from this case and moved to S29-02.
A7: TestCases | B7: TC-R1-04-05 | C7: Changed | D7: Draft | E7: Draft | F7: Title, Expected, Trace, Assumption Ref, Reason | G7: v2.1 expected a profile for the Permanent Resident. The current FS stores profiles only for successfully processed records, so the expectation is reversed and stays Draft.
A8: TestCases | B8: TC-R1-04-06 | C8: Changed | D8: Draft | E8: Approve | F8: Trace, Assumption Ref, Dependency Ref, Status, Reason | G8: The FS now states who creates the Student Profile (steps 6 and 8). The assumption is closed for this case.
A9: TestCases | B9: TC-R1-04-07 | C9: Changed | D9: Approve | E9: Approve | F9: Expected, Trace, Reason | G9: Renumbered to F02-BR08. The Account Closure Date check is dropped because the FS no longer lists that field in 2.2.
A10: TestCases | B10: TC-R1-05-01 | C10: Changed | D10: Approve | E10: Approve | F10: Trace, Reason | G10: Citation moved from the 1.1.9 table to 1.1.5 step 7.
A11: TestCases | B11: TC-R1-05-05 | C11: Changed | D11: Draft | E11: Draft | F11: Steps, Expected, Reason | G11: The Processing Log no longer exists in the FS. The case reads the job log that Dev provides.
A12: TestCases | B12: TC-R1-05-08 | C12: Changed | D12: Approve | E12: Approve | F12: Trace, Reason | G12: Section 2.4 (Trigger Type) was removed. The citation now uses F01-AC06, F01-AC12 and the Initial Sync note.
... A16: TestCases | B16: TC-R1-06-04 | C16: Changed | D16: Approve | E16: Approve | F16: Steps, Expected, Trace, Reason | G16: The Processing Log check was dropped (the log is not in the FS). Citation updated.
A17: TestCases | B17: TC-R1-06-05 | C17: New | E17: Block | F17: Manual Account Creation creates the account of an eligible late record | G17: New. The FS now names the deferred path for late records.
A18: TestCases | B18: TC-R1-06-06 | C18: New | E18: Block | F18: Bulk Re-synchronization creates the missing accounts for citizens aged 7 to under 16 and no duplicate | G18: New. The FS now names the deferred path for late records.
A19: TestCases | B19: TC-R1-07-01 | C19: Changed | D19: Approve | E19: Approve | F19: Steps, Expected, Trace, Reason | G19: The Processing Log is not in the FS. The check of the log entry was removed and moved to S07-14 (Block). 1.1.4 step 5 is cited.
A20: TestCases | B20: TC-R1-07-02 | C20: Changed | D20: Approve | E20: Approve | F20: Steps, Expected, Trace, Reason | G20: The Processing Log is not in the FS. The check of the log entry was removed and moved to S07-14 (Block). 1.1.4 step 5 is cited.
A21: TestCases | B21: TC-R1-07-03 | C21: Changed | D21: Approve | E21: Approve | F21: Steps, Expected, Trace, Reason | G21: The Processing Log is not in the FS. The check of the log entry was removed and moved to S07-14 (Block). 1.1.4 step 5 is cited.
A22: TestCases | B22: TC-R1-07-04 | C22: Changed | D22: Approve | E22: Approve | F22: Steps, Expected, Trace, Reason | G22: The Processing Log is not in the FS. The check of the log entry was removed and moved to S07-14 (Block). 1.1.4 step 5 is cited.
A23: TestCases | B23: TC-R1-07-05 | C23: Changed | D23: Approve | E23: Approve | F23: Steps, Expected, Trace, Reason | G23: The Processing Log is not in the FS. The check of the log entry was removed and moved to S07-14 (Block). 1.1.4 step 5 is cited.
A24: TestCases | B24: TC-R1-07-07 | C24: Changed | D24: Approve | E24: Approve | F24: Steps, Expected, Trace, Reason | G24: The Processing Log is not in the FS. The check of the log entry was removed and moved to S07-14 (Block). 1.1.4 step 5 is cited.
A25: TestCases | B25: TC-R1-07-08 | C25: Changed | D25: Approve | E25: Approve | F25: Steps, Expected, Trace, Reason | G25: The Processing Log is not in the FS. The check of the log entry was removed and moved to S07-14 (Block). 1.1.4 step 5 is cited.
A26: TestCases | B26: TC-R1-07-09 | C26: Changed | D26: Draft | E26: Draft | F26: Steps, Expected, Trace, Reason | G26: The Processing Log is not in the FS. The check of the log entry was removed and moved to S07-14 (Block). 1.1.4 step 5 is cited.
A27: TestCases | B27: TC-R1-07-10 | C27: Changed | D27: Draft | E27: Draft | F27: Steps, Expected, Trace, Reason | G27: The Processing Log is not in the FS. The check of the log entry was removed and moved to S07-14 (Block). 1.1.4 step 5 is cited.
A28: TestCases | B28: TC-R1-07-11 | C28: Changed | D28: Approve | E28: Approve | F28: Steps, Expected, Trace, Reason | G28: The Processing Log is not in the FS. The check of the log entry was removed and moved to S07-14 (Block). 1.1.4 step 5 is cited.
A29: TestCases | B29: TC-R1-07-13 | C29: Changed | D29: Approve | E29: Approve | F29: Steps, Expected, Trace, Reason | G29: F01-AC15 is new in the FS. The case now checks the Student Profile and its link.
A30: TestCases | B30: TC-R1-07-14 | C30: New | E30: Block | F30: An exception is recorded for an invalid record | G30: New. The v2.1 cases checked a Processing Log entry. The FS now conflicts with itself on recording the exception, so that check is separated here.
A31: TestCases | B31: TC-R1-08-04 | C31: Changed | D31: Approve | E31: Approve | F31: Trace, Reason | G31: F02-AC15 is new in the FS and is cited here.
A32: TestCases | B32: TC-R1-09-01 | C32: Changed | D32: Approve | E32: Approve | F32: Trace, Reason | G32: Step numbers updated: the age and citizenship selection is now in the query (steps 2 and 3).
A33: TestCases | B33: TC-R1-09-02 | C33: Changed | D33: Approve | E33: Approve | F33: Expected, Trace, Reason | G33: The [TD] sentence about the DOB query was replaced in the FS. The query value is now an inference.
A34: TestCases | B34: TC-R1-09-03 | C34: Changed | D34: Approve | E34: Approve | F34: Steps, Expected, Trace, Reason | G34: The Processing Log check was dropped. Step numbers updated.
A35: TestCases | B35: TC-R1-09-04 | C35: Changed | D35: Draft | E35: Block | F35: Sprint, Steps, Expected, Trace, Assumption Ref, Dependency Ref, Status, Reason | G35: F01-AC11 was removed and 1.1.9 is labelled next sprint. Draft became Block, Sprint TBD.
A36: TestCases | B36: TC-R1-09-06 | C36: Changed | D36: Approve | E36: Approve | F36: Trace, Reason | G36: Step number updated.
A37: TestCases | B37: TC-R1-09-07 | C37: Changed | D37: Approve | E37: Approve | F37: Steps, Expected, Trace, Reason | G37: Section 2.4 (Job Name) was removed. The sequence is read from the request log.
A38: TestCases | B38: TC-R1-10-03 | C38: Changed | D38: Approve | E38: Approve | F38: Steps, Expected, Reason | G38: The Processing Log was replaced by the request log.
A39: TestCases | B39: TC-R1-11-01 | C39: Changed | D39: Approve | E39: Approve | F39: Trace, Reason | G39: Renumbered F02-BR04 to F02-BR07. The [CR] tag is no longer on this rule.
A40: TestCases | B40: TC-R1-11-03 | C40: Changed | D40: Draft | E40: Draft | F40: Trace, Assumption Ref, Reason | G40: Renumbered F02-BR04 to F02-BR07.
A41: TestCases | B41: TC-R1-11-05 | C41: Changed | D41: Draft | E41: Draft | F41: Trace, Assumption Ref, Reason | G41: The [WA] note in 1.1.3 was removed. The citation moves to 2.1 and F01-BR04.
A42: TestCases | B42: TC-R1-13-01 | C42: Changed | D42: Approve | E42: Approve | F42: Trace | G42: The sentence 'frontend receives the status after the check' in 1.2.4 was removed. The citation uses F02-AF03 and step 13.; F02-BR04 is cited.
... A63: TestCases | B63: TC-R1-19-04 | C63: Changed | D63: Draft | E63: Draft | F63: Title, Precondition, Test Data, Steps, Expected, Trace, Assumption Ref, Dependency Ref, Reason | G63: Rewritten: the block no longer waits for an eligibility review. The account is closed and the financial request is refused.
A64: TestCases | B64: TC-R1-19-05 | C64: New | E64: Draft | F64: A Closed account is not reopened when the citizenship is regained | G64: New. Covers the regained citizenship after a citizenship based closure.
A65: TestCases | B65: TC-R1-24-01 | C65: Changed | D65: Approve | E65: Approve | F65: Trace, Dependency Ref, Reason | G65: The [WA] tag on F01-BR02 was removed. Step numbers updated.
A66: TestCases | B66: TC-R1-24-02 | C66: Changed | D66: Approve | E66: Approve | F66: Trace | G66: Step numbers updated.
A67: TestCases | B67: TC-R1-24-03 | C67: Changed | D67: Approve | E67: Approve | F67: Trace, Reason | G67: The step 8 check of the old flow is gone. The citation moves to 1.1.1 A.
A68: TestCases | B68: TC-R1-24-04 | C68: Changed | D68: Approve | E68: Approve | F68: Steps, Expected, Trace, Reason | G68: The Processing Log record and its status were removed from the FS. The case checks that no Job Failure is written.
A69: TestCases | B69: TC-R1-25-01 | C69: Changed | D69: Draft | E69: Approve | F69: Precondition, Test Data, Steps, Trace, Assumption Ref, Dependency Ref, Status, Reason | G69: The [WA] tag was removed from 1.1.2 (weekends and holidays) and from F01-AC13. Draft became Approve.
A70: TestCases | B70: TC-R1-25-02 | C70: Changed | D70: Draft | E70: Approve | F70: Precondition, Test Data, Steps, Trace, Assumption Ref, Dependency Ref, Status | G70: The [WA] tag was removed from 1.1.2 (weekends and holidays) and from F01-AC13. Draft became Approve.
A71: TestCases | B71: TC-R1-25-03 | C71: Changed | D71: Draft | E71: Block | F71: Sprint, Trace, Assumption Ref, Dependency Ref, Status, Reason | G71: F01-AC11 was removed and 1.1.9 is labelled next sprint. Draft became Block, Sprint TBD.
A72: TestCases | B72: TC-R1-25-04 | C72: Changed | D72: Draft | E72: Block | F72: Sprint, Trace, Assumption Ref, Dependency Ref, Status, Reason | G72: F01-AC11 and F01-EF04 were removed and 1.1.9 is labelled next sprint. Draft became Block, Sprint TBD.
A73: TestCases | B73: TC-R1-26-01 | C73: Changed | D73: Approve | E73: Approve | F73: Steps, Expected, Trace, Reason | G73: Section 2.4 and the 1.1.9 table are no longer cited. The Processing Log became the job log. Failure reason text is not checked because the FS does not state it.
A74: TestCases | B74: TC-R1-26-02 | C74: Changed | D74: Draft | E74: Block | F74: Sprint, Steps, Expected, Assumption Ref, Dependency Ref, Status, Reason | G74: 1.1.9 is labelled next sprint. Draft became Block, Sprint TBD.
A75: TestCases | B75: TC-R1-26-03 | C75: Changed | D75: Draft | E75: Block | F75: Sprint, Steps, Expected, Assumption Ref, Dependency Ref, Status, Reason | G75: 1.1.9 is labelled next sprint. Draft became Block, Sprint TBD.
A76: TestCases | B76: TC-R1-26-04 | C76: Changed | D76: Draft | E76: Block | F76: Sprint, Assumption Ref, Dependency Ref, Status, Reason | G76: 1.1.9 is labelled next sprint. Draft became Block, Sprint TBD.
... A87: TestCases | B87: TC-R1-28-05 | C87: Changed | D87: Approve | E87: Approve | F87: Trace | G87: F02-BR06 is cited.
A88: TestCases | B88: TC-R1-28-08 | C88: New | E88: Draft | F88: Batch Top-Up does not top up an account of a holder aged 16 | G88: New. 1.2.2 now names the Batch Top-Up.
A89: TestCases | B89: TC-R1-29-01 | C89: Changed | D89: Approve | E89: Approve | F89: Steps, Expected, Trace, Reason | G89: The Closure Processing Result check was dropped. F02-BR09 [WA] became F02-BR12 [TD].
A90: TestCases | B90: TC-R1-29-02 | C90: Changed | D90: Draft | E90: Draft | F90: Steps, Expected, Trace, Assumption Ref, Reason | G90: The 2.2 row [WA] was removed. The date is now cited from step 12 and the empty value before closure is checked here.
A91: TestCases | B91: TC-R1-29-03 | C91: Changed | D91: Approve | E91: Reject | F91: Sprint, Precondition, Postcondition, Test Data, Steps, Expected, Trace, Dependency Ref, Status, Reason | G91: The Closure Processing Result was removed from the FS. Approve became Reject.
A92: TestCases | B92: TC-R1-29-04 | C92: Changed | D92: Approve | E92: Approve | F92: Trace, Reason | G92: Citation updated to the new wording of 1.2.4 and section 4.
A93: TestCases | B93: TC-R1-29-06 | C93: Changed | D93: Approve | E93: Approve | F93: Steps, Expected, Reason | G93: The Closure Processing Result check was dropped. The balance check was added from F02-EF03.
A94: TestCases | B94: TC-R1-30-01 | C94: Changed | D94: Approve | E94: Approve | F94: Trace | G94: F02-AC12 is new in the FS and is cited here.
A95: TestCases | B95: TC-R1-30-02 | C95: Changed | D95: Approve | E95: Approve | F95: Trace | G95: F02-AC12 is new in the FS and is cited here.
A96: TestCases | B96: TC-R1-30-03 | C96: Changed | D96: Approve | E96: Draft | F96: Trace, Assumption Ref, Dependency Ref, Status, Reason | G96: F02-AC09 now carries [WA] and the error record is only in F02-EF01 [WA]. Approve became Draft on ASM-R1-40.
A97: TestCases | B97: TC-R1-30-04 | C97: Changed | D97: Draft | E97: Draft | F97: Trace, Assumption Ref, Reason | G97: F02-AC09 now carries [WA] and is cited with F02-EF01.
A98: TestCases | B98: TC-R1-30-05 | C98: Changed | D98: Approve | E98: Approve | F98: Trace, Reason | G98: F02-BR04 [CR] became F02-BR07.
A99: TestCases | B99: TC-R1-30-06 | C99: Changed | D99: Approve | E99: Approve | F99: Trace, Reason | G99: The old F02-BR04 sentence on the creation date was dropped from the FS. The expected result now rests on F02-BR03 and F02-BR01.
A100: TestCases | B100: TC-R1-30-07 | C100: New | E100: Draft | F100: Government API returns no valid record: the account is not closed and an error result is returned | G100: New. F02-EF02 and F02-BR14 are new in the FS.
A101: TestCases | B101: TC-R1-31-01 | C101: Changed | D101: Draft | E101: Draft | F101: Trace, Assumption Ref | G101: FS item numbers updated: F02 business rules and alternative flows were renumbered, and tags changed in the FS.
A102: TestCases | B102: TC-R1-31-02 | C102: Changed | D102: Draft | E102: Draft | F102: Trace, Assumption Ref | G102: FS item numbers updated: F02 business rules and alternative flows were renumbered, and tags changed in the FS.
A103: TestCases | B103: TC-R1-31-03 | C103: Changed | D103: Draft | E103: Draft | F103: Trace, Assumption Ref, Reason | G103: FS item numbers updated: F02 business rules and alternative flows were renumbered, and tags changed in the FS.
A104: TestCases | B104: TC-R1-31-04 | C104: Changed | D104: Draft | E104: Draft | F104: Trace, Assumption Ref | G104: FS item numbers updated: F02 business rules and alternative flows were renumbered, and tags changed in the FS.
A105: TestCases | B105: TC-R1-31-05 | C105: Changed | D105: Draft | E105: Draft | F105: Steps, Trace, Assumption Ref, Reason | G105: The Closure Processing Result check was dropped. F02-BR09 [WA] became F02-BR12 [TD].
A106: TestCases | B106: TC-R1-32-01 | C106: New | E106: Approve | F106: Daily Job does not read a student who has an account and does not update the address | G106: New. F01-AC16 is new in the FS.
A107: TestCases | B107: TC-R1-32-02 | C107: New | E107: Approve | F107: Closure check does not update the address or the gender of the Student Profile | G107: New. F02-AC13 and F02-BR13 are new in the FS.
A108: TestCases | B108: TC-R1-32-03 | C108: New | E108: Approve | F108: Closure check does not update the full name or the race of the Student Profile | G108: New. F02-EF05 is new in the FS.
A109: TestCases | B109: TC-R1-32-04 | C109: New | E109: Approve | F109: A Government update of the Father or Mother NRIC needs no rescan by R1 | G109: New. The R8 dependency note is new in the FS.
A110: Scenarios | B110: SCN-R1-01 | C110: Changed | F110: Evidence | G110: Wording and FS items updated to the current FS.
A111: Scenarios | B111: SCN-R1-04 | C111: Changed | F111: Evidence | G111: Wording and FS items updated to the current FS.
A112: Scenarios | B112: SCN-R1-06 | C112: Changed | F112: Condition, Evidence | G112: Wording and FS items updated to the current FS.
A113: Scenarios | B113: SCN-R1-07 | C113: Changed | F113: Condition, Evidence | G113: Wording and FS items updated to the current FS.
A114: Scenarios | B114: SCN-R1-08 | C114: Changed | F114: Evidence | G114: Wording and FS items updated to the current FS.
A115: Scenarios | B115: SCN-R1-09 | C115: Changed | F115: Evidence | G115: Wording and FS items updated to the current FS.
A116: Scenarios | B116: SCN-R1-11 | C116: Changed | F116: Evidence | G116: Wording and FS items updated to the current FS.
A117: Scenarios | B117: SCN-R1-14 | C117: Changed | F117: Evidence | G117: Wording and FS items updated to the current FS.
A118: Scenarios | B118: SCN-R1-15 | C118: Changed | F118: Evidence | G118: Wording and FS items updated to the current FS.
A119: Scenarios | B119: SCN-R1-17 | C119: Changed | F119: Evidence | G119: Wording and FS items updated to the current FS.
A120: Scenarios | B120: SCN-R1-18 | C120: Changed | F120: Condition, Evidence | G120: Wording and FS items updated to the current FS.
A121: Scenarios | B121: SCN-R1-19 | C121: Changed | F121: Condition, Evidence | G121: Wording and FS items updated to the current FS.
... A144: Checkpoint | B144: CP-R1-25 | C144: New | F144: R1.25 Student data is stored at account creation. The Daily Job and the closure | G144: New FS only checkpoint for the student data boundary.
A145: Assumptions | B145: ASM-R1-01 | C145: Changed | D145: Open | E145: Open | F145: Assumption, Reason, Question to confirm | G145: The Processing Log and the Closure Processing Result no longer exist in the FS. QA reads the job log and the request log instead.
A146: Assumptions | B146: ASM-R1-07 | C146: Changed | D146: Open | E146: Open | F146: Original gap, Assumption, Source (as in Assumption Ref), Source detail, Reason, If the answer differs, Question to confirm | G146: F02 now closes the account on loss of citizenship (F02-BR05, F02-AC11). The Eligibility Review rule is gone.
A147: Assumptions | B147: ASM-R1-08 | C147: Changed | D147: Superseded | E147: Superseded | F147: Assumption, Source (as in Assumption Ref), Source detail, Resolution | G147: The sentence moved from 1.2.6 to section 4.
A148: Assumptions | B148: ASM-R1-09 | C148: Changed | D148: Superseded | E148: Superseded | F148: Source detail | G148: Section 4 now holds the Deferred CPF Transfer.
A149: Assumptions | B149: ASM-R1-10 | C149: Changed | D149: Superseded | E149: Superseded | F149: Source (as in Assumption Ref), Source detail, Resolution | G149: F02-BR06 became F02-BR09.
A150: Assumptions | B150: ASM-R1-12 | C150: Changed | D150: Resolved | E150: Resolved | F150: Assumption, Source (as in Assumption Ref), Source detail, Reason, Resolution | G150: Narrowed to the result for the account. The place of the exception is a separate question.
A151: Assumptions | B151: ASM-R1-13 | C151: Changed | D151: Superseded | E151: Superseded | F151: Assumption, Source (as in Assumption Ref), Source detail, Resolution | G151: The late record limit moved to 1.1.1 B and section 4.
A152: Assumptions | B152: ASM-R1-15 | C152: Changed | D152: Superseded | E152: Superseded | F152: Assumption, Source detail, Resolution | G152: Step 13 became step 10.
A153: Assumptions | B153: ASM-R1-17 | C153: Changed | D153: Open | E153: Open | F153: Source (as in Assumption Ref), Source detail, Question to confirm | G153: F02-BR04 became F02-BR07.
A154: Assumptions | B154: ASM-R1-19 | C154: Changed | D154: Resolved | E154: Resolved | F154: Source detail | G154: F02-BR07 and BR08 became F02-BR10 and F02-BR11.
A155: Assumptions | B155: ASM-R1-23 | C155: Changed | D155: Open | E155: Open | F155: Original gap, Source (as in Assumption Ref), Source detail, Reason, Resolution, Question to confirm | G155: 1.1.9 is labelled next sprint and F01-AC11 was removed.
...
