Workbook

Sheet Product Backlog
A1: EDUCATION ACCOUNT | PRODUCT BACKLOG
A2: Proposed build order: read Product Backlog top-to-bottom within each Target Sprint. Dev updates Status, Owner, Estimate and Notes; final Sprint scope requires team planning.
A3: R1–R10 traceability in column F; evidence in R; proposed Build Sequence in S. Sprint 1 includes R9 payment flows (gateway/charge-data dependent).
A5: ID | B5: Epic | C5: Feature / User Story | D5: Description / User Story | E5: Portal / Actor | F5: Source Requirement(s) | G5: Target Sprint (proposed) | H5: Priority | I5: Requirement basis | J5: Readiness | K5: Dev Status (update) | L5: Owner (update) | M5: Estimate SP (update) | N5: Dependencies | O5: Open question / risk | P5: Acceptance / Demo check | Q5: Dev Notes / Blocker (update) | R5: Build Sequence (proposed)
A6: PB-01 | B6: Technical Enabler | C6: Capacity, concurrency and test baseline | D6: Description: Define the performance and capacity baseline for the HQ, School and Parent portals. Propose concurrency targets and QA load-test scenarios from the client-provided user populations and usage periods; population counts are not confirmed concurrent user targets. | E6: Cross-cutting · Dev / QA | F6: No direct R# (meeting NFR) | G6: Sprint 1 | H6: P2 - Medium | I6: Client estimates + proposed task | J6: Needs team estimate | K6: Not Started | N6: Architecture + expected usage profile | O6: 500 HQ users, 300 schools x ~200 users, ~2M parents are population estimates, NOT concurrency targets. | P6: Proposed concurrency/load assumptions documented and reviewed by team/client. | R6: 1
A7: PB-02 | B7: Core Data | C7: Maintain school, level/cohort, class & student records | D7: As an authorized MOE HQ or School User, I want to maintain the school, level/cohort, class and student records within my permissions, so that the system has accurate school and student information. | E7: Admin · MOE HQ / School | F7: R3 | G7: Sprint 1 | H7: P1 - High | I7: Initial + client clarified | J7: Needs AC | K7: Not Started | N7: School/student data model | O7: Exact HQ/School operations and cross-school scope need refinement. | P7: Authorized users can view/edit permitted records; school users cannot edit school-level master data. | R7: 2
A8: PB-03 | B8: Access Control | C8: HQ vs School role-based permissions | D8: As an MOE HQ administrator, I want HQ and School Users to have access limited by their roles and authorized records, so that school and student data can only be managed by permitted users. | E8: Admin · MOE HQ / School | F8: R3 (clarified in meeting) | G8: Sprint 1 | H8: P1 - High | I8: Client clarified | J8: Needs AC | K8: Not Started | N8: PB-02; user identity/roles | O8: Clarify school record visibility and finer permission matrix. | P8: HQ has broad management access; School role cannot modify unauthorized records. | R8: 3
A9: PB-04 | B9: Core Data | C9: Obtain student data from external source | D9: Description: Retrieve or import student master data from the agreed external source, including name, date of birth, citizenship and address where available. Establish student identifiers and determine how trusted parent/guardian relationships will be sourced; the interface and mapping remain unconfirmed. | E9: Backend / Integration | F9: R1, R3, R8 (supporting enabler) | G9: Sprint 1 | H9: P1 - High | I9: Proposed implementation | J9: Blocked / external | K9: Not Started | N9: External source/API, unique identifiers | O9: Actual provider, API access, keys, schema, refresh and guardian source not confirmed. | P9: Sample student record can be loaded accurately with source and validation documented. | R9: 4
A10: PB-05 | B10: Education Account | C10: Create and activate Education Account at age 7 | D10: As an MOE HQ user, I want an Education Account to be created and activated automatically for an eligible Singapore Citizen at age 7, so that the child's education funding can be administered. | E10: Backend / Admin | F10: R1 | G10: Sprint 1 | H10: P1 - High | I10: Initial + client clarified | J10: Needs AC | K10: Not Started | N10: PB-04; account data design | O10: Age-calculation trigger, backfill, citizenship changes and ledger source not confirmed. | P10: Eligible example has an active account; ineligible example is not auto-created. | R10: 5
A11: PB-06 | B11: Parent Portal | C11: Parent authentication via SingPass | D11: As a parent/guardian, I want to sign in to the e-Service Portal through SingPass, so that I can securely access the services available to me. | E11: e-Service · Parent | F11: R8 | G11: Sprint 1 | H11: P1 - High | I11: Initial requirement | J11: Blocked / external | K11: Not Started | N11: SingPass environment, test identities | O11: Confirm sandbox access and identity attributes required for parent match. | P11: Authorized test parent can sign in and sign out; unauthenticated data access is blocked. | R11: 6
A12: PB-07 | B12: Parent Portal | C12: Authorize parent/guardian to linked children | D12: As a parent/guardian, I want to see only the children I am authorized to represent after signing in, so that I can access their information without seeing other students' records. | E12: e-Service · Parent | F12: R8 (supporting access control) | G12: Sprint 1 | H12: P1 - High | I12: Proposed solution / implied | J12: Needs client decision | K12: Not Started | N12: PB-04, PB-06; trusted guardian mapping | O12: Guardian data source, access for multiple guardians and revocation not confirmed. | P12: A parent sees only linked children and cannot request another child's account. | R12: 7
A13: PB-08 | B13: Parent Portal | C13: View child account, balance & transactions | D13: As a parent/guardian, I want to view my linked child's Education Account details, balance and transaction history, so that I can understand how the education funds have been used. | E13: e-Service · Parent | F13: R8 | G13: Sprint 1 | H13: P1 - High | I13: Initial requirement | J13: Needs AC | K13: Not Started | N13: PB-05, PB-07; ledger/source | O13: Confirm exact fields, source of transaction records and visibility for closed accounts. | P13: Authorized parent sees correct child, balance, transaction list and empty state. | R13: 8
A14: PB-09 | B14: Parent Portal | C14: View outstanding charges | D14: As a parent/guardian, I want to see my linked child's outstanding school charges and the amounts due, so that I know what remains to be paid. | E14: e-Service · Parent | F14: R9 | G14: Sprint 1 | H14: P1 - High | I14: Initial requirement | J14: At risk / dependency | K14: Not Started | N14: PB-07, charge data / PB-13 | O14: For Sprint 1, confirm authoritative or demo charge dataset, due/remaining amount, and which child can see each charge. Billing generation is not yet confirmed. | P14: Parent sees correct charges only for their linked child, with amounts/status and an empty state; can choose a payable charge for one of the R9 payment paths. | R14: 9
A15: PB-10 | B15: Payments | C15: Pay eligible charges using Education Account | D15: As a parent/guardian, I want to pay eligible outstanding school charges using the available balance in my child's Education Account, so that I can use those funds toward school fees. Eligibility, partial-payment and insufficient-funds rules remain open. | E15: e-Service / Backend | F15: R3, R9 | G15: Sprint 1 | H15: P1 - High | I15: Initial requirement | J15: At risk / dependency | K15: Not Started | N15: PB-05, PB-07, PB-08; charge dataset (PB-13 or agreed test fixtures); transactional ledger | O15: P1 clarification: eligible charge categories, sufficient/insufficient balance, full vs partial payment, duplicate submission and settlement rules; validate financial ledger feasibility with Dev. | P15: Given an eligible unpaid charge and sufficient balance, authorized parent pays once; account balance and amount outstanding both reduce exactly once; failures do not alter balances. | R15: 10
A16: PB-11 | B16: Payments | C16: Pay fees via online payment method | D16: As a parent/guardian, I want to pay outstanding school charges through an available online payment method, so that I can settle fees electronically. Supported methods and payment provider are not yet confirmed. | E16: e-Service · Parent | F16: R9 | G16: Sprint 1 | H16: P1 - High | I16: Initial requirement | J16: Blocked / external | K16: Not Started | N16: PB-07, PB-09; charge dataset; selected payment provider/gateway or test sandbox; callbacks | O16: PAYMENT GATE: gateway, permitted methods, test credentials, callbacks, payment confirmation, failed/cancelled payments, refund and reconciliation are not yet defined. | P16: Parent can select an available online method, complete a successful test payment and see outstanding charge updated; failed/cancelled payment remains outstanding and does not double-collect. | R16: 11
A17: PB-12 | B17: Fee Management | C17: Maintain fee types and components | D17: As an authorized administrative user, I want to maintain fee types and their components, so that school charges can be defined consistently. Reusable components such as GST are subject to feasibility and scope confirmation. | E17: Admin · MOE HQ / School | F17: R3 | G17: Sprint 2 | H17: P1 - High | I17: Initial + client examples | J17: Needs AC | K17: Not Started | N17: PB-02; fee/charge data model | O17: Fees, attributes, owners, effective dates; GST reuse suggested if feasible, not mandatory. | P17: User can configure fee type/component and retrieve valid fee definition. | R17: 12
... A30: PB-25 | B30: AI / ML | C30: Predict financial difficulty risk tiers | D30: Description: Develop an ML-based financial difficulty prediction capability that groups cases into Low, Medium and High risk and suggests an assistance tier, subject to an agreed dataset, evaluation approach and human decision responsibilities. | E30: Admin / Backend | F30: R4 (AI Feature) | G30: Unscheduled / trade-off | H30: P3 - Low | I30: Initial AI feature | J30: Blocked / feasibility | K30: Not Started | N30: Historical labeled data, PB-17, ML approach | O30: Training dataset, outcome labels, explainability, bias evaluation and decision authority missing. | P30: Demonstrable validated prediction on agreed test set if feasible. | R30: 25

Sheet Sprint Tracker
A1: SPRINT TRACKER | LIVE BACKLOG STATUS
A2: Counts refresh from Product Backlog → Target Sprint (G) and Dev Status (K). Proposed allocation only; Sprint Planning confirms selection.
A5: Target Sprint | B5: Items | C5: Not Started | D5: In Progress | E5: Blocked | F5: In QA | G5: Done | H5: Completion
A6: Sprint 1 | B6: =COUNTIF('Product Backlog'!$G$6:$G$205,A6) -> 11 | C6: =COUNTIFS('Product Backlog'!$G$6:$G$205,A6,'Product Backlog'!$K$6:$K$205,"Not Started") -> 11 | D6: =COUNTIFS('Product Backlog'!$G$6:$G$205,A6,'Product Backlog'!$K$6:$K$205,"In Progress") -> 0 | E6: =COUNTIFS('Product Backlog'!$G$6:$G$205,A6,'Product Backlog'!$K$6:$K$205,"Blocked") -> 0 | F6: =COUNTIFS('Product Backlog'!$G$6:$G$205,A6,'Product Backlog'!$K$6:$K$205,"In QA") -> 0 | G6: =COUNTIFS('Product Backlog'!$G$6:$G$205,A6,'Product Backlog'!$K$6:$K$205,"Done") -> 0 | H6: =IF(B6=0,0,G6/B6) -> 0
A7: Sprint 2 | B7: =COUNTIF('Product Backlog'!$G$6:$G$205,A7) -> 4 | C7: =COUNTIFS('Product Backlog'!$G$6:$G$205,A7,'Product Backlog'!$K$6:$K$205,"Not Started") -> 4 | D7: =COUNTIFS('Product Backlog'!$G$6:$G$205,A7,'Product Backlog'!$K$6:$K$205,"In Progress") -> 0 | E7: =COUNTIFS('Product Backlog'!$G$6:$G$205,A7,'Product Backlog'!$K$6:$K$205,"Blocked") -> 0 | F7: =COUNTIFS('Product Backlog'!$G$6:$G$205,A7,'Product Backlog'!$K$6:$K$205,"In QA") -> 0 | G7: =COUNTIFS('Product Backlog'!$G$6:$G$205,A7,'Product Backlog'!$K$6:$K$205,"Done") -> 0 | H7: =IF(B7=0,0,G7/B7) -> 0
A8: Sprint 3 | B8: =COUNTIF('Product Backlog'!$G$6:$G$205,A8) -> 6 | C8: =COUNTIFS('Product Backlog'!$G$6:$G$205,A8,'Product Backlog'!$K$6:$K$205,"Not Started") -> 6 | D8: =COUNTIFS('Product Backlog'!$G$6:$G$205,A8,'Product Backlog'!$K$6:$K$205,"In Progress") -> 0 | E8: =COUNTIFS('Product Backlog'!$G$6:$G$205,A8,'Product Backlog'!$K$6:$K$205,"Blocked") -> 0 | F8: =COUNTIFS('Product Backlog'!$G$6:$G$205,A8,'Product Backlog'!$K$6:$K$205,"In QA") -> 0 | G8: =COUNTIFS('Product Backlog'!$G$6:$G$205,A8,'Product Backlog'!$K$6:$K$205,"Done") -> 0 | H8: =IF(B8=0,0,G8/B8) -> 0
A9: Unscheduled / trade-off | B9: =COUNTIF('Product Backlog'!$G$6:$G$205,A9) -> 4 | C9: =COUNTIFS('Product Backlog'!$G$6:$G$205,A9,'Product Backlog'!$K$6:$K$205,"Not Started") -> 4 | D9: =COUNTIFS('Product Backlog'!$G$6:$G$205,A9,'Product Backlog'!$K$6:$K$205,"In Progress") -> 0 | E9: =COUNTIFS('Product Backlog'!$G$6:$G$205,A9,'Product Backlog'!$K$6:$K$205,"Blocked") -> 0 | F9: =COUNTIFS('Product Backlog'!$G$6:$G$205,A9,'Product Backlog'!$K$6:$K$205,"In QA") -> 0 | G9: =COUNTIFS('Product Backlog'!$G$6:$G$205,A9,'Product Backlog'!$K$6:$K$205,"Done") -> 0 | H9: =IF(B9=0,0,G9/B9) -> 0
A12: PROPOSED INCREMENTAL SPRINT GOALS
A14: Sprint | B14: Demo / focus
A15: Sprint 1 | B15: Foundation + SingPass + linked-child account view + R9: view charges, Education Account payment and online payment (gateway-dependent).
A16: Sprint 2 | B16: Complete fee configuration/billing management, top-ups and profile editing; carry over online gateway only if integration prevents S1 delivery.
A17: Sprint 3 | B17: Account closure and a limited FAS end-to-end slice; rest only if team capacity supports it.
A19: PLANNING RISKS / SCOPE BOUNDARIES
A20: High risk: Sprint 1 targets all R9 options but charge source/payment gateway, account ledger and business rules remain unresolved. Confirm via Dev estimates and client clarification.
A21: Unscheduled ≠ cancelled. PB-22–PB-25 remain client-requested capability candidates that require scope/capacity trade-off.
A22: Sprint 1–3 allocation is PO recommendation; Dev owns capacity / feasibility, and Sprint scope is chosen collaboratively.
A25: HOW TO UPDATE
A26: Dev updates backlog columns K (Dev Status), L (Owner), M (Estimate SP), Q (Notes). Change G (Target Sprint) only after team reprioritization.

Sheet Open Questions
A1: CLIENT CLARIFICATIONS | OPEN QUESTIONS
A2: Use Monday's 30-minute session for P1 questions that can cause current Sprint build/test errors. Capture explicit client answers in this sheet.
A5: ID | B5: Urgency | C5: For Sprint | D5: Clarification question / missing decision | E5: Why needed for Dev / QA | F5: Related PBI | G5: Suggested owner | H5: Status (update) | I5: Client answer / decision (update) | J5: Meeting / requirement source
A6: OQ-01 | B6: P1 - Now | C6: Sprint 1 | D6: What is the authoritative student data source/API, identifier, refresh frequency and data schema? | E6: Cannot trust account eligibility or link source records. | F6: PB-04, PB-05 | G6: Client / Architect | H6: Open | J6: Mtg 12:13–13:15
A7: OQ-02 | B7: P1 - Now | C7: Sprint 1 | D7: Where do trusted guardian relationships come from, and which parents/guardians may access each child? | E7: Security and access-control design must be testable. | F7: PB-04, PB-07 | G7: Client / Architect | H7: Open | J7: Mtg 16:41–17:33
A8: OQ-03 | B8: P1 - Now | C8: Sprint 1 | D8: Is SingPass test/sandbox access available, and which identifier maps to a parent? | E8: Parent demo/integration feasibility. | F8: PB-06, PB-07 | G8: Client / Architect | H8: Open | J8: IR #8; Mtg 16:41
A9: OQ-04 | B9: P1 - Now | C9: Sprint 1 | D9: What is the authoritative source of outstanding charges? For Sprint 1, is a test/imported charge dataset acceptable until full billing flow is confirmed? | E9: Blocks R9 view and either payment path; must avoid treating a fixture as production billing. | F9: PB-13, PB-09, PB-10, PB-11 | G9: Client / BA | H9: Open | J9: Mtg 03:37–04:12
A10: OQ-05 | B10: P1 - Now | C10: Sprint 1 | D10: Which data/source is authoritative for Education Account balance and transaction history? | E10: Account balance and transaction source determine whether an Education Account debit can be reliable and testable in Sprint 1. | F10: PB-05, PB-08, PB-10 | G10: Client / Architect | H10: Open | J10: IR #1/#8
A11: OQ-06 | B11: P1 - Now | C11: Sprint 1 | D11: At age 7, exactly how is account opening triggered? Need backfill / changes to citizenship handling? | E11: Eligibility logic and QA edge cases. | F11: PB-05 | G11: Client / BA | H11: Open | J11: IR #1
A12: OQ-07 | B12: P1 - Now | C12: Sprint 1 | D12: Confirm HQ and school user view/edit matrix, including cross-school student records. | E12: Protects school/student data; affects UI and API. | F12: PB-02, PB-03 | G12: Client / BA | H12: Open | J12: Mtg 18:46
A13: OQ-08 | B13: P1 - Now | C13: Sprint 1 | D13: For Sprint 1 R9 payment demos, which confirmed charge dataset and account balances may be used, and must online payment be live or sandbox? | E13: Clarifies release/demo acceptance without representing mocked transactions as integrated payments. | F13: PB-09, PB-10, PB-11 | G13: PO / Client / Dev | H13: Open | J13: Mtg 09:57–11:15
A14: OQ-09 | B14: P2 - Before Sprint 2 | C14: Sprint 2 | D14: Which parent profile fields are editable and where are edits synchronized? | E14: Scope and permission for profile update. | F14: PB-15 | G14: Client / BA | H14: Open | J14: IR #8; Mtg 05:07
A15: OQ-10 | B15: P2 - Before Sprint 2 | C15: Sprint 2 | D15: Which fee types, components and calculation/charging rules are needed? Is shared GST in scope? | E15: Data model and billing rules need examples. | F15: PB-12, PB-13 | G15: Client / BA | H15: Open | J15: Mtg 20:17–23:53
A16: OQ-11 | B16: P1 - Now | C16: Sprint 1 | D16: For R9 Sprint 1, confirm Education Account payment rules (eligible fees, insufficient/partial balance) and online provider/methods, sandbox/API access, callbacks and settlement behavior. | E16: Both R9 payment options target Sprint 1; unconfirmed financial rules/provider may block implementation and QA. | F16: PB-10, PB-11 | G16: Client / Architect | H16: Open | J16: IR #3/#9
A17: OQ-12 | B17: P2 - Before Sprint 2 | C17: Sprint 2 | D17: Exact HQ batch top-up rules, calculation, rerun behavior, authorization and audit? | E17: Prevents unintended duplicate credits. | F17: PB-14 | G17: Client / BA | H17: Open | J17: IR #2
... A22: OQ-17 | B22: P2 - Before Sprint 2 | C22: Sprint 1 | D22: What concurrency targets and response-time thresholds should QA test for each portal? | E22: Population estimates are not performance acceptance criteria. | F22: PB-01 | G22: Architect / QA / Client | H22: Open | J22: Mtg 24:52–27:17

Sheet Client Decisions
A1: CLIENT MEETING | CLARIFIED FACTS & CAUTIONS
A2: Source is an AI-generated transcript: verify ambiguous wording against client as needed. Not every team statement equals a client decision.
A5: ID | B5: Client clarification / evidence | C5: Implication for Dev / QA | D5: Source | E5: Confidence
A6: CD-01 | B6: Education Account is a financial/spending account, NOT a user login account; Singapore Citizens can have it. PR/foreign students may attend schools without one. | C6: Model education account separately from portal identity; fees exist for students without Education Accounts. | D6: Mtg 15:03–16:30 | E6: Client explicitly clarified
A7: CD-02 | B7: Education Account balance should transfer to CPF at closure; the client expects no pending transactions. | C7: Plan closure/CPF workflow; pending transaction handling needs additional design confirmation. | D7: Mtg 11:19–12:13 | E7: Client explicitly clarified
A8: CD-03 | B8: Student source fields suggested: name, date of birth, citizenship, address where available. | C8: Use these as candidate integration fields; actual API payload, identifiers and address availability remain open. | D8: Mtg 12:58–13:15 | E8: Client explicitly clarified
A9: CD-04 | B9: Level and cohort mean essentially the same thing; class is a separate dimension. | C9: Avoid creating independent Level and Cohort concepts without a need. | D9: Mtg 18:06–18:27 | E9: Client explicitly clarified
A10: CD-05 | B10: MOE HQ should manage all listed records; School users can edit from level down. | C10: Start access design with this restriction; precise row-level scope still needs definition. | D10: Mtg 18:33–19:03 | E10: Client explicitly clarified
A11: CD-06 | B11: School enrollment/schooling status and Education Account status are distinct. | C11: Do not automatically open/close the Education Account on school transfer/enrollment status. | D11: Mtg 19:03–19:59 | E11: Client explicitly clarified
A12: CD-07 | B12: Shared GST fee component was welcomed if feasible, rather than strictly required. | C12: Treat component reuse as an enhancement/implementation choice, not a mandatory Sprint 2 contract. | D12: Mtg 20:17–22:03 | E12: Client expressed preference
A13: CD-08 | B13: Fee examples: school/miscellaneous fees, ad hoc activities and damage charges. | C13: Fee data model should support more than one recurring monthly tuition fee. | D13: Mtg 22:33–23:53 | E13: Client gave examples
A14: CD-09 | B14: Client estimates ~500 HQ users, ~300 schools, ~200 School users each, ~2M possible parents; these are NOT concurrency numbers. | C14: Dev/QA must propose and validate concurrent load targets rather than treating population as simultaneous sessions. | D14: Mtg 24:52–25:38 | E14: Client estimate only
A15: CD-10 | B15: HQ/school activity roughly 08:00–19:00; parent portal access around 06:00–02:00; usage may spike around payment dates. | C15: Use for preliminary load profile, not fixed availability/peak SLA. | D15: Mtg 26:25–27:17 | E15: Client estimate only
A16: CD-11 | B16: The client considered the high-level modules broadly present, but said it was too early to confirm detailed design. | C16: Do not treat overview diagrams or BA assumptions as full sign-off. | D16: Mtg 07:39–08:02 | E16: Explicit non-approval
A17: CD-12 | B17: Team proposed Sprint 1 focus on IR #1/#3/#8/#9; client said this was acceptable while questioning backend availability. | C17: Sprint 1 scope here is a proposal and must still be estimated/selected by Developers. | D17: Mtg 08:47–11:15 | E17: Proposed scope discussed

Sheet Read Me
A1: QUICK START | GOOGLE SHEETS BACKLOG
A4: Step | B4: Topic | C4: Instruction | D4: Reminder
A5: 1 | B5: Upload / import | C5: In Google Sheets: File → Import → Upload → select this XLSX. Choose a new spreadsheet or insert sheets. | D5: Formulas, filters and dropdowns are intended to transfer; verify after import.
A6: 2 | B6: Daily Dev tracking | C6: Go to Product Backlog; filter by Target Sprint / Priority. Update K=Dev Status, L=Owner, M=Estimate SP, Q=Notes/Blocker. | D6: Status dropdown: Not Started, Ready for Dev, In Progress, Blocked, In QA, Done, Deferred.
A7: 3 | B7: PO / BA planning | C7: Rows are ordered by proposed implementation sequence: Sprint 1 → Sprint 2 → Sprint 3 → Unscheduled. Within each Sprint, dependencies/enablers come before dependent functions. | D7: Use column S (Build Sequence) to restore order after sorting in Google Sheets. Sequence reflects planning judgment, not a strict serial dependency or delivery promise.
A8: 4 | B8: Clarification | C8: Use Open Questions during 30-minute Monday client clarification meeting. Record answers and close each item after explicit confirmation. | D8: Do not implement design guesses as confirmed requirements.
A9: 5 | B9: Source Requirement traceability | C9: Product Backlog col F maps each PBI to R1–R10 from the client requirement image. Col R preserves original initial-requirement references and meeting timestamps. | D9: Supporting/Proposed/NFR mappings are not confirmed new client requirements. Check col I (Requirement basis) and Open Questions.
A10: 6 | B10: Demo convention | C10: Demo with sample/test data only when explicitly labelled; Education Account debit must be a testable transaction; an online payment without gateway/sandbox must NOT count as Done. | D10: R9 is only fully satisfied when BOTH payment choices and view outstanding charges work to agreed acceptance criteria.
A11: 7 | B11: Sprints | C11: Sprint 1 targets R9 view and two payment paths after core data/auth; Sprint 2 completes fee configuration/charge creation (PB-12/PB-13); Sprint 3 targets closure/FAS. | D11: R9 in Sprint 1 depends on confirmed charge/test data; PB-13 full billing is Sprint 2. Integration gaps may change sequencing following Dev Planning.
A12: 9 | B12: Build sequence | C12: Column S stores a stable proposed build sequence (1–25) matching the physical row order, including unscheduled items. | D12: Parallel implementation is still possible; build order is not a mandatory waterfall schedule.
A13: 10 | B13: Renumbered IDs | C13: PBI IDs were reassigned from PB-01 through PB-25 to match proposed Build Sequence (column S). See ID Mapping for old-to-new references. | D13: Do not use PB IDs from older exports without consulting the mapping tab.
