Workbook

Sheet Summary
A1: Tender Test Cases and Defects: Summary (Training Management: Enrolment, Assessment, Funding)
A2: All counts are formulas over TestCases, Checkpoint and Defects. No test case has been executed.
A4: Test cases by Status
A5: Status | B5: Count | C5: Percent | D5: Meaning
A6: Approve | B6: =COUNTIF(TestCases!$Y$2:$Y$328,A6) -> 90 | C6: =B6/B9 -> 0.27522936 | D6: Expected result comes from the clause, no open assumption
A7: Draft | B7: =COUNTIF(TestCases!$Y$2:$Y$328,A7) -> 233 | C7: =B7/B9 -> 0.71253823 | D7: Needs an assumption to write the expected result
A8: Reject | B8: =COUNTIF(TestCases!$Y$2:$Y$328,A8) -> 4 | C8: =B8/B9 -> 0.012232416 | D8: Clause gives no testable expectation, steps not written
A9: Total | B9: =SUM(B6:B8) -> 327 | C9: =SUM(C6:C8) -> 1
A11: Status by Priority
A12: Priority | B12: Approve | C12: Draft | D12: Reject | E12: Total
A13: Critical | B13: =COUNTIFS(TestCases!$J$2:$J$328,$A13,TestCases!$Y$2:$Y$328,"Approve") -> 21 | C13: =COUNTIFS(TestCases!$J$2:$J$328,$A13,TestCases!$Y$2:$Y$328,"Draft") -> 64 | D13: =COUNTIFS(TestCases!$J$2:$J$328,$A13,TestCases!$Y$2:$Y$328,"Reject") -> 0 | E13: =SUM(B13:D13) -> 85
A14: High | B14: =COUNTIFS(TestCases!$J$2:$J$328,$A14,TestCases!$Y$2:$Y$328,"Approve") -> 27 | C14: =COUNTIFS(TestCases!$J$2:$J$328,$A14,TestCases!$Y$2:$Y$328,"Draft") -> 78 | D14: =COUNTIFS(TestCases!$J$2:$J$328,$A14,TestCases!$Y$2:$Y$328,"Reject") -> 1 | E14: =SUM(B14:D14) -> 106
A15: Medium | B15: =COUNTIFS(TestCases!$J$2:$J$328,$A15,TestCases!$Y$2:$Y$328,"Approve") -> 24 | C15: =COUNTIFS(TestCases!$J$2:$J$328,$A15,TestCases!$Y$2:$Y$328,"Draft") -> 68 | D15: =COUNTIFS(TestCases!$J$2:$J$328,$A15,TestCases!$Y$2:$Y$328,"Reject") -> 1 | E15: =SUM(B15:D15) -> 93
A16: Low | B16: =COUNTIFS(TestCases!$J$2:$J$328,$A16,TestCases!$Y$2:$Y$328,"Approve") -> 18 | C16: =COUNTIFS(TestCases!$J$2:$J$328,$A16,TestCases!$Y$2:$Y$328,"Draft") -> 23 | D16: =COUNTIFS(TestCases!$J$2:$J$328,$A16,TestCases!$Y$2:$Y$328,"Reject") -> 2 | E16: =SUM(B16:D16) -> 43
A17: Total | B17: =SUM(B13:B16) -> 90 | C17: =SUM(C13:C16) -> 233 | D17: =SUM(D13:D16) -> 4 | E17: =SUM(E13:E16) -> 327
A19: Status by Severity (1 is the most severe)
A20: Severity | B20: Approve | C20: Draft | D20: Reject | E20: Total | F20: Meaning
A21: 1 | B21: =COUNTIFS(TestCases!$K$2:$K$328,$A21,TestCases!$Y$2:$Y$328,"Approve") -> 6 | C21: =COUNTIFS(TestCases!$K$2:$K$328,$A21,TestCases!$Y$2:$Y$328,"Draft") -> 45 | D21: =COUNTIFS(TestCases!$K$2:$K$328,$A21,TestCases!$Y$2:$Y$328,"Reject") -> 0 | E21: =SUM(B21:D21) -> 51 | F21: Blocker, or money, funding or compliance break
A22: 2 | B22: =COUNTIFS(TestCases!$K$2:$K$328,$A22,TestCases!$Y$2:$Y$328,"Approve") -> 44 | C22: =COUNTIFS(TestCases!$K$2:$K$328,$A22,TestCases!$Y$2:$Y$328,"Draft") -> 130 | D22: =COUNTIFS(TestCases!$K$2:$K$328,$A22,TestCases!$Y$2:$Y$328,"Reject") -> 1 | E22: =SUM(B22:D22) -> 175 | F22: Critical or major function fails
A23: 3 | B23: =COUNTIFS(TestCases!$K$2:$K$328,$A23,TestCases!$Y$2:$Y$328,"Approve") -> 32 | C23: =COUNTIFS(TestCases!$K$2:$K$328,$A23,TestCases!$Y$2:$Y$328,"Draft") -> 57 | D23: =COUNTIFS(TestCases!$K$2:$K$328,$A23,TestCases!$Y$2:$Y$328,"Reject") -> 3 | E23: =SUM(B23:D23) -> 92 | F23: Normal: wrong result with a workaround
A24: 4 | B24: =COUNTIFS(TestCases!$K$2:$K$328,$A24,TestCases!$Y$2:$Y$328,"Approve") -> 8 | C24: =COUNTIFS(TestCases!$K$2:$K$328,$A24,TestCases!$Y$2:$Y$328,"Draft") -> 1 | D24: =COUNTIFS(TestCases!$K$2:$K$328,$A24,TestCases!$Y$2:$Y$328,"Reject") -> 0 | E24: =SUM(B24:D24) -> 9 | F24: Minor or cosmetic
A25: Total | B25: =SUM(B21:B24) -> 90 | C25: =SUM(C21:C24) -> 233 | D25: =SUM(D21:D24) -> 4 | E25: =SUM(E21:E24) -> 327
A27: Priority by Severity (test cases)
A28: Priority | B28: Severity 1 | C28: Severity 2 | D28: Severity 3 | E28: Severity 4 | F28: Total
A29: Critical | B29: =COUNTIFS(TestCases!$J$2:$J$328,$A29,TestCases!$K$2:$K$328,1) -> 36 | C29: =COUNTIFS(TestCases!$J$2:$J$328,$A29,TestCases!$K$2:$K$328,2) -> 49 | D29: =COUNTIFS(TestCases!$J$2:$J$328,$A29,TestCases!$K$2:$K$328,3) -> 0 | E29: =COUNTIFS(TestCases!$J$2:$J$328,$A29,TestCases!$K$2:$K$328,4) -> 0 | F29: =SUM(B29:E29) -> 85
A30: High | B30: =COUNTIFS(TestCases!$J$2:$J$328,$A30,TestCases!$K$2:$K$328,1) -> 15 | C30: =COUNTIFS(TestCases!$J$2:$J$328,$A30,TestCases!$K$2:$K$328,2) -> 65 | D30: =COUNTIFS(TestCases!$J$2:$J$328,$A30,TestCases!$K$2:$K$328,3) -> 26 | E30: =COUNTIFS(TestCases!$J$2:$J$328,$A30,TestCases!$K$2:$K$328,4) -> 0 | F30: =SUM(B30:E30) -> 106
A31: Medium | B31: =COUNTIFS(TestCases!$J$2:$J$328,$A31,TestCases!$K$2:$K$328,1) -> 0 | C31: =COUNTIFS(TestCases!$J$2:$J$328,$A31,TestCases!$K$2:$K$328,2) -> 61 | D31: =COUNTIFS(TestCases!$J$2:$J$328,$A31,TestCases!$K$2:$K$328,3) -> 31 | E31: =COUNTIFS(TestCases!$J$2:$J$328,$A31,TestCases!$K$2:$K$328,4) -> 1 | F31: =SUM(B31:E31) -> 93
A32: Low | B32: =COUNTIFS(TestCases!$J$2:$J$328,$A32,TestCases!$K$2:$K$328,1) -> 0 | C32: =COUNTIFS(TestCases!$J$2:$J$328,$A32,TestCases!$K$2:$K$328,2) -> 0 | D32: =COUNTIFS(TestCases!$J$2:$J$328,$A32,TestCases!$K$2:$K$328,3) -> 35 | E32: =COUNTIFS(TestCases!$J$2:$J$328,$A32,TestCases!$K$2:$K$328,4) -> 8 | F32: =SUM(B32:E32) -> 43
A33: Total | B33: =SUM(B29:B32) -> 51 | C33: =SUM(C29:C32) -> 175 | D33: =SUM(D29:D32) -> 92 | E33: =SUM(E29:E32) -> 9 | F33: =SUM(F29:F32) -> 327
A35: Test cases by Module and Sprint (a clause in several sprints counts in each)
A36: Module | B36: Sprint 1 | C36: Sprint 2 | D36: Sprint 3 | E36: Unscheduled | F36: Rows
A37: Enrolment | B37: =COUNTIFS(TestCases!$C$2:$C$328,$A37,TestCases!$D$2:$D$328,"*1*") -> 45 | C37: =COUNTIFS(TestCases!$C$2:$C$328,$A37,TestCases!$D$2:$D$328,"*2*") -> 57 | D37: =COUNTIFS(TestCases!$C$2:$C$328,$A37,TestCases!$D$2:$D$328,"*3*") -> 18 | E37: =COUNTIFS(TestCases!$C$2:$C$328,$A37,TestCases!$D$2:$D$328,"Unscheduled") -> 1 | F37: =COUNTIFS(TestCases!$C$2:$C$328,$A37) -> 117
A38: Assessment | B38: =COUNTIFS(TestCases!$C$2:$C$328,$A38,TestCases!$D$2:$D$328,"*1*") -> 7 | C38: =COUNTIFS(TestCases!$C$2:$C$328,$A38,TestCases!$D$2:$D$328,"*2*") -> 3 | D38: =COUNTIFS(TestCases!$C$2:$C$328,$A38,TestCases!$D$2:$D$328,"*3*") -> 64 | E38: =COUNTIFS(TestCases!$C$2:$C$328,$A38,TestCases!$D$2:$D$328,"Unscheduled") -> 0 | F38: =COUNTIFS(TestCases!$C$2:$C$328,$A38) -> 68
A39: Funding | B39: =COUNTIFS(TestCases!$C$2:$C$328,$A39,TestCases!$D$2:$D$328,"*1*") -> 34 | C39: =COUNTIFS(TestCases!$C$2:$C$328,$A39,TestCases!$D$2:$D$328,"*2*") -> 92 | D39: =COUNTIFS(TestCases!$C$2:$C$328,$A39,TestCases!$D$2:$D$328,"*3*") -> 46 | E39: =COUNTIFS(TestCases!$C$2:$C$328,$A39,TestCases!$D$2:$D$328,"Unscheduled") -> 9 | F39: =COUNTIFS(TestCases!$C$2:$C$328,$A39) -> 142
A40: Total | B40: =SUM(B37:B39) -> 86 | C40: =SUM(C37:C39) -> 152 | D40: =SUM(D37:D39) -> 128 | E40: =SUM(E37:E39) -> 10 | F40: =SUM(F37:F39) -> 327
A42: Status by Module
A43: Module | B43: Approve | C43: Draft | D43: Reject | E43: Total
A44: Enrolment | B44: =COUNTIFS(TestCases!$C$2:$C$328,$A44,TestCases!$Y$2:$Y$328,"Approve") -> 36 | C44: =COUNTIFS(TestCases!$C$2:$C$328,$A44,TestCases!$Y$2:$Y$328,"Draft") -> 80 | D44: =COUNTIFS(TestCases!$C$2:$C$328,$A44,TestCases!$Y$2:$Y$328,"Reject") -> 1 | E44: =SUM(B44:D44) -> 117
A45: Assessment | B45: =COUNTIFS(TestCases!$C$2:$C$328,$A45,TestCases!$Y$2:$Y$328,"Approve") -> 24 | C45: =COUNTIFS(TestCases!$C$2:$C$328,$A45,TestCases!$Y$2:$Y$328,"Draft") -> 43 | D45: =COUNTIFS(TestCases!$C$2:$C$328,$A45,TestCases!$Y$2:$Y$328,"Reject") -> 1 | E45: =SUM(B45:D45) -> 68
A46: Funding | B46: =COUNTIFS(TestCases!$C$2:$C$328,$A46,TestCases!$Y$2:$Y$328,"Approve") -> 30 | C46: =COUNTIFS(TestCases!$C$2:$C$328,$A46,TestCases!$Y$2:$Y$328,"Draft") -> 110 | D46: =COUNTIFS(TestCases!$C$2:$C$328,$A46,TestCases!$Y$2:$Y$328,"Reject") -> 2 | E46: =SUM(B46:D46) -> 142
A47: Total | B47: =SUM(B44:B46) -> 90 | C47: =SUM(C44:C46) -> 233 | D47: =SUM(D44:D46) -> 4 | E47: =SUM(E44:E46) -> 327
A49: Status by Test Type
A50: Test Type | B50: Approve | C50: Draft | D50: Reject | E50: Total
A51: Functional | B51: =COUNTIFS(TestCases!$X$2:$X$328,$A51,TestCases!$Y$2:$Y$328,"Approve") -> 87 | C51: =COUNTIFS(TestCases!$X$2:$X$328,$A51,TestCases!$Y$2:$Y$328,"Draft") -> 192 | D51: =COUNTIFS(TestCases!$X$2:$X$328,$A51,TestCases!$Y$2:$Y$328,"Reject") -> 2 | E51: =SUM(B51:D51) -> 281
A52: Integration | B52: =COUNTIFS(TestCases!$X$2:$X$328,$A52,TestCases!$Y$2:$Y$328,"Approve") -> 3 | C52: =COUNTIFS(TestCases!$X$2:$X$328,$A52,TestCases!$Y$2:$Y$328,"Draft") -> 41 | D52: =COUNTIFS(TestCases!$X$2:$X$328,$A52,TestCases!$Y$2:$Y$328,"Reject") -> 2 | E52: =SUM(B52:D52) -> 46
A53: Total | B53: =SUM(B51:B52) -> 90 | C53: =SUM(C51:C52) -> 233 | D53: =SUM(D51:D52) -> 4 | E53: =SUM(E51:E52) -> 327
A55: Status by Lens
A56: Lens | B56: Approve | C56: Draft | D56: Reject | E56: Total
A57: Boundary | B57: =COUNTIFS(TestCases!$I$2:$I$328,$A57,TestCases!$Y$2:$Y$328,"Approve") -> 7 | C57: =COUNTIFS(TestCases!$I$2:$I$328,$A57,TestCases!$Y$2:$Y$328,"Draft") -> 23 | D57: =COUNTIFS(TestCases!$I$2:$I$328,$A57,TestCases!$Y$2:$Y$328,"Reject") -> 0 | E57: =SUM(B57:D57) -> 30
A58: Business Risk | B58: =COUNTIFS(TestCases!$I$2:$I$328,$A58,TestCases!$Y$2:$Y$328,"Approve") -> 6 | C58: =COUNTIFS(TestCases!$I$2:$I$328,$A58,TestCases!$Y$2:$Y$328,"Draft") -> 34 | D58: =COUNTIFS(TestCases!$I$2:$I$328,$A58,TestCases!$Y$2:$Y$328,"Reject") -> 2 | E58: =SUM(B58:D58) -> 42
A59: Data | B59: =COUNTIFS(TestCases!$I$2:$I$328,$A59,TestCases!$Y$2:$Y$328,"Approve") -> 20 | C59: =COUNTIFS(TestCases!$I$2:$I$328,$A59,TestCases!$Y$2:$Y$328,"Draft") -> 21 | D59: =COUNTIFS(TestCases!$I$2:$I$328,$A59,TestCases!$Y$2:$Y$328,"Reject") -> 0 | E59: =SUM(B59:D59) -> 41
A60: Data Integrity | B60: =COUNTIFS(TestCases!$I$2:$I$328,$A60,TestCases!$Y$2:$Y$328,"Approve") -> 7 | C60: =COUNTIFS(TestCases!$I$2:$I$328,$A60,TestCases!$Y$2:$Y$328,"Draft") -> 28 | D60: =COUNTIFS(TestCases!$I$2:$I$328,$A60,TestCases!$Y$2:$Y$328,"Reject") -> 0 | E60: =SUM(B60:D60) -> 35
A61: Failure&Recovery | B61: =COUNTIFS(TestCases!$I$2:$I$328,$A61,TestCases!$Y$2:$Y$328,"Approve") -> 0 | C61: =COUNTIFS(TestCases!$I$2:$I$328,$A61,TestCases!$Y$2:$Y$328,"Draft") -> 7 | D61: =COUNTIFS(TestCases!$I$2:$I$328,$A61,TestCases!$Y$2:$Y$328,"Reject") -> 0 | E61: =SUM(B61:D61) -> 7
A62: Happy Path | B62: =COUNTIFS(TestCases!$I$2:$I$328,$A62,TestCases!$Y$2:$Y$328,"Approve") -> 20 | C62: =COUNTIFS(TestCases!$I$2:$I$328,$A62,TestCases!$Y$2:$Y$328,"Draft") -> 14 | D62: =COUNTIFS(TestCases!$I$2:$I$328,$A62,TestCases!$Y$2:$Y$328,"Reject") -> 0 | E62: =SUM(B62:D62) -> 34
A63: Negative | B63: =COUNTIFS(TestCases!$I$2:$I$328,$A63,TestCases!$Y$2:$Y$328,"Approve") -> 6 | C63: =COUNTIFS(TestCases!$I$2:$I$328,$A63,TestCases!$Y$2:$Y$328,"Draft") -> 27 | D63: =COUNTIFS(TestCases!$I$2:$I$328,$A63,TestCases!$Y$2:$Y$328,"Reject") -> 0 | E63: =SUM(B63:D63) -> 33
A64: Security | B64: =COUNTIFS(TestCases!$I$2:$I$328,$A64,TestCases!$Y$2:$Y$328,"Approve") -> 0 | C64: =COUNTIFS(TestCases!$I$2:$I$328,$A64,TestCases!$Y$2:$Y$328,"Draft") -> 4 | D64: =COUNTIFS(TestCases!$I$2:$I$328,$A64,TestCases!$Y$2:$Y$328,"Reject") -> 0 | E64: =SUM(B64:D64) -> 4
A65: Sequence | B65: =COUNTIFS(TestCases!$I$2:$I$328,$A65,TestCases!$Y$2:$Y$328,"Approve") -> 2 | C65: =COUNTIFS(TestCases!$I$2:$I$328,$A65,TestCases!$Y$2:$Y$328,"Draft") -> 0 | D65: =COUNTIFS(TestCases!$I$2:$I$328,$A65,TestCases!$Y$2:$Y$328,"Reject") -> 0 | E65: =SUM(B65:D65) -> 2
A66: State | B66: =COUNTIFS(TestCases!$I$2:$I$328,$A66,TestCases!$Y$2:$Y$328,"Approve") -> 2 | C66: =COUNTIFS(TestCases!$I$2:$I$328,$A66,TestCases!$Y$2:$Y$328,"Draft") -> 10 | D66: =COUNTIFS(TestCases!$I$2:$I$328,$A66,TestCases!$Y$2:$Y$328,"Reject") -> 0 | E66: =SUM(B66:D66) -> 12
A67: UI | B67: =COUNTIFS(TestCases!$I$2:$I$328,$A67,TestCases!$Y$2:$Y$328,"Approve") -> 0 | C67: =COUNTIFS(TestCases!$I$2:$I$328,$A67,TestCases!$Y$2:$Y$328,"Draft") -> 1 | D67: =COUNTIFS(TestCases!$I$2:$I$328,$A67,TestCases!$Y$2:$Y$328,"Reject") -> 0 | E67: =SUM(B67:D67) -> 1
A68: Workflow | B68: =COUNTIFS(TestCases!$I$2:$I$328,$A68,TestCases!$Y$2:$Y$328,"Approve") -> 20 | C68: =COUNTIFS(TestCases!$I$2:$I$328,$A68,TestCases!$Y$2:$Y$328,"Draft") -> 64 | D68: =COUNTIFS(TestCases!$I$2:$I$328,$A68,TestCases!$Y$2:$Y$328,"Reject") -> 2 | E68: =SUM(B68:D68) -> 86
A69: Total | B69: =SUM(B57:B68) -> 90 | C69: =SUM(C57:C68) -> 233 | D69: =SUM(D57:D68) -> 4 | E69: =SUM(E57:E68) -> 327
A71: Status by Type
A72: Type | B72: Approve | C72: Draft | D72: Reject | E72: Total
A73: positive | B73: =COUNTIFS(TestCases!$L$2:$L$328,$A73,TestCases!$Y$2:$Y$328,"Approve") -> 76 | C73: =COUNTIFS(TestCases!$L$2:$L$328,$A73,TestCases!$Y$2:$Y$328,"Draft") -> 161 | D73: =COUNTIFS(TestCases!$L$2:$L$328,$A73,TestCases!$Y$2:$Y$328,"Reject") -> 0 | E73: =SUM(B73:D73) -> 237
A74: negative | B74: =COUNTIFS(TestCases!$L$2:$L$328,$A74,TestCases!$Y$2:$Y$328,"Approve") -> 7 | C74: =COUNTIFS(TestCases!$L$2:$L$328,$A74,TestCases!$Y$2:$Y$328,"Draft") -> 42 | D74: =COUNTIFS(TestCases!$L$2:$L$328,$A74,TestCases!$Y$2:$Y$328,"Reject") -> 4 | E74: =SUM(B74:D74) -> 53
A75: boundary | B75: =COUNTIFS(TestCases!$L$2:$L$328,$A75,TestCases!$Y$2:$Y$328,"Approve") -> 7 | C75: =COUNTIFS(TestCases!$L$2:$L$328,$A75,TestCases!$Y$2:$Y$328,"Draft") -> 25 | D75: =COUNTIFS(TestCases!$L$2:$L$328,$A75,TestCases!$Y$2:$Y$328,"Reject") -> 0 | E75: =SUM(B75:D75) -> 32
A76: exception | B76: =COUNTIFS(TestCases!$L$2:$L$328,$A76,TestCases!$Y$2:$Y$328,"Approve") -> 0 | C76: =COUNTIFS(TestCases!$L$2:$L$328,$A76,TestCases!$Y$2:$Y$328,"Draft") -> 5 | D76: =COUNTIFS(TestCases!$L$2:$L$328,$A76,TestCases!$Y$2:$Y$328,"Reject") -> 0 | E76: =SUM(B76:D76) -> 5
A77: Total | B77: =SUM(B73:B76) -> 90 | C77: =SUM(C73:C76) -> 233 | D77: =SUM(D73:D76) -> 4 | E77: =SUM(E73:E76) -> 327
A79: Checkpoints by Flag and Module
A80: Flag | B80: Enrolment | C80: Assessment | D80: Funding | E80: Total
A81: Clear | B81: =COUNTIFS(Checkpoint!$G$2:$G$163,$A81,Checkpoint!$E$2:$E$163,"Enrolment") -> 20 | C81: =COUNTIFS(Checkpoint!$G$2:$G$163,$A81,Checkpoint!$E$2:$E$163,"Assessment") -> 17 | D81: =COUNTIFS(Checkpoint!$G$2:$G$163,$A81,Checkpoint!$E$2:$E$163,"Funding") -> 10 | E81: =SUM(B81:D81) -> 47
A82: Assumed | B82: =COUNTIFS(Checkpoint!$G$2:$G$163,$A82,Checkpoint!$E$2:$E$163,"Enrolment") -> 48 | C82: =COUNTIFS(Checkpoint!$G$2:$G$163,$A82,Checkpoint!$E$2:$E$163,"Assessment") -> 24 | D82: =COUNTIFS(Checkpoint!$G$2:$G$163,$A82,Checkpoint!$E$2:$E$163,"Funding") -> 38 | E82: =SUM(B82:D82) -> 110
A83: Conflict | B83: =COUNTIFS(Checkpoint!$G$2:$G$163,$A83,Checkpoint!$E$2:$E$163,"Enrolment") -> 1 | C83: =COUNTIFS(Checkpoint!$G$2:$G$163,$A83,Checkpoint!$E$2:$E$163,"Assessment") -> 0 | D83: =COUNTIFS(Checkpoint!$G$2:$G$163,$A83,Checkpoint!$E$2:$E$163,"Funding") -> 2 | E83: =SUM(B83:D83) -> 3
A84: Blocked | B84: =COUNTIFS(Checkpoint!$G$2:$G$163,$A84,Checkpoint!$E$2:$E$163,"Enrolment") -> 1 | C84: =COUNTIFS(Checkpoint!$G$2:$G$163,$A84,Checkpoint!$E$2:$E$163,"Assessment") -> 0 | D84: =COUNTIFS(Checkpoint!$G$2:$G$163,$A84,Checkpoint!$E$2:$E$163,"Funding") -> 1 | E84: =SUM(B84:D84) -> 2
A85: Total | B85: =SUM(B81:B84) -> 70 | C85: =SUM(C81:C84) -> 41 | D85: =SUM(D81:D84) -> 51 | E85: =SUM(E81:E84) -> 162
A87: Potential defects by Severity and Module
A88: Severity | B88: Enrolment | C88: Assessment | D88: Funding | E88: Total | F88: Meaning
A89: 1 | B89: =COUNTIFS(Defects!$N$2:$N$71,$A89,Defects!$B$2:$B$71,"Enrolment") -> 7 | C89: =COUNTIFS(Defects!$N$2:$N$71,$A89,Defects!$B$2:$B$71,"Assessment") -> 5 | D89: =COUNTIFS(Defects!$N$2:$N$71,$A89,Defects!$B$2:$B$71,"Funding") -> 19 | E89: =SUM(B89:D89) -> 31 | F89: Blocker, or money, funding or compliance break
A90: 2 | B90: =COUNTIFS(Defects!$N$2:$N$71,$A90,Defects!$B$2:$B$71,"Enrolment") -> 6 | C90: =COUNTIFS(Defects!$N$2:$N$71,$A90,Defects!$B$2:$B$71,"Assessment") -> 3 | D90: =COUNTIFS(Defects!$N$2:$N$71,$A90,Defects!$B$2:$B$71,"Funding") -> 17 | E90: =SUM(B90:D90) -> 26 | F90: Critical or major function fails
A91: 3 | B91: =COUNTIFS(Defects!$N$2:$N$71,$A91,Defects!$B$2:$B$71,"Enrolment") -> 4 | C91: =COUNTIFS(Defects!$N$2:$N$71,$A91,Defects!$B$2:$B$71,"Assessment") -> 1 | D91: =COUNTIFS(Defects!$N$2:$N$71,$A91,Defects!$B$2:$B$71,"Funding") -> 3 | E91: =SUM(B91:D91) -> 8 | F91: Normal: wrong result with a workaround
A92: 4 | B92: =COUNTIFS(Defects!$N$2:$N$71,$A92,Defects!$B$2:$B$71,"Enrolment") -> 1 | C92: =COUNTIFS(Defects!$N$2:$N$71,$A92,Defects!$B$2:$B$71,"Assessment") -> 2 | D92: =COUNTIFS(Defects!$N$2:$N$71,$A92,Defects!$B$2:$B$71,"Funding") -> 2 | E92: =SUM(B92:D92) -> 5 | F92: Minor or cosmetic
A93: Total | B93: =SUM(B89:B92) -> 18 | C93: =SUM(C89:C92) -> 11 | D93: =SUM(D89:D92) -> 41 | E93: =SUM(E89:E92) -> 70
A95: Potential defects by Priority (Impact x Urgency) and Severity
A96: Priority | B96: Severity 1 | C96: Severity 2 | D96: Severity 3 | E96: Severity 4 | F96: Total
A97: Critical | B97: =COUNTIFS(Defects!$Q$2:$Q$71,$A97,Defects!$N$2:$N$71,1) -> 31 | C97: =COUNTIFS(Defects!$Q$2:$Q$71,$A97,Defects!$N$2:$N$71,2) -> 15 | D97: =COUNTIFS(Defects!$Q$2:$Q$71,$A97,Defects!$N$2:$N$71,3) -> 0 | E97: =COUNTIFS(Defects!$Q$2:$Q$71,$A97,Defects!$N$2:$N$71,4) -> 0 | F97: =SUM(B97:E97) -> 46
A98: High | B98: =COUNTIFS(Defects!$Q$2:$Q$71,$A98,Defects!$N$2:$N$71,1) -> 0 | C98: =COUNTIFS(Defects!$Q$2:$Q$71,$A98,Defects!$N$2:$N$71,2) -> 11 | D98: =COUNTIFS(Defects!$Q$2:$Q$71,$A98,Defects!$N$2:$N$71,3) -> 0 | E98: =COUNTIFS(Defects!$Q$2:$Q$71,$A98,Defects!$N$2:$N$71,4) -> 0 | F98: =SUM(B98:E98) -> 11
A99: Medium | B99: =COUNTIFS(Defects!$Q$2:$Q$71,$A99,Defects!$N$2:$N$71,1) -> 0 | C99: =COUNTIFS(Defects!$Q$2:$Q$71,$A99,Defects!$N$2:$N$71,2) -> 0 | D99: =COUNTIFS(Defects!$Q$2:$Q$71,$A99,Defects!$N$2:$N$71,3) -> 6 | E99: =COUNTIFS(Defects!$Q$2:$Q$71,$A99,Defects!$N$2:$N$71,4) -> 2 | F99: =SUM(B99:E99) -> 8
A100: Low | B100: =COUNTIFS(Defects!$Q$2:$Q$71,$A100,Defects!$N$2:$N$71,1) -> 0 | C100: =COUNTIFS(Defects!$Q$2:$Q$71,$A100,Defects!$N$2:$N$71,2) -> 0 | D100: =COUNTIFS(Defects!$Q$2:$Q$71,$A100,Defects!$N$2:$N$71,3) -> 2 | E100: =COUNTIFS(Defects!$Q$2:$Q$71,$A100,Defects!$N$2:$N$71,4) -> 3 | F100: =SUM(B100:E100) -> 5
A101: Total | B101: =SUM(B97:B100) -> 31 | C101: =SUM(C97:C100) -> 26 | D101: =SUM(D97:D100) -> 8 | E101: =SUM(E97:E100) -> 5 | F101: =SUM(F97:F100) -> 70
A103: Suggested regression suite for the potential defects
A104: Suite | B104: Count | C104: Rule
A105: Smoke | B105: =COUNTIFS(Defects!$U$2:$U$71,$A105) -> 31 | C105: Severity 1
A106: Regression Core | B106: =COUNTIFS(Defects!$U$2:$U$71,$A106) -> 26 | C106: Severity 2
A107: Regression Extended | B107: =COUNTIFS(Defects!$U$2:$U$71,$A107) -> 13 | C107: Severity 3 or 4
A108: Total | B108: =SUM(B105:B107) -> 70
A110: Legend: Defect Priority = Impact x Urgency (Lesson 4 section 22, ASM-91)
A111: Impact level | B111: Urgency | C111: Priority | D111: Impact level rule
A112: High | B112: High | C112: Critical | D112: High when Severity is 1 or 2
A113: High | B113: Low | C113: High
A114: Low | B114: High | C114: Medium | D114: Low when Severity is 3 or 4
...

Sheet TestCases
A1: TC ID | B1: Requirement (Tender clause) | C1: Module | D1: Sprint | E1: Scenario ID | F1: Scenario Name | G1: Title | H1: Objective | I1: Lens | J1: Priority | K1: Severity | L1: Type | M1: Precondition | N1: Postcondition | O1: Test Data | P1: Steps | Q1: Expected Result | R1: Actual Result | S1: Traceability Requirement | T1: Technique | U1: Checkpoint Ref | V1: Assumption Ref | W1: Dependency Ref | X1: Test Type | Y1: Status | Z1: Reason
A2: TC-SCN-001-01 | B2: 2.2 | C2: Enrolment | D2: 1 | E2: SCN-001 | F2: Resident signs in with SingPass | G2: Resident signs in through SingPass | H2: A Singapore Resident authenticates through SingPass and is signed in. Case: Resident signs in through SingPass | I2: Happy Path | J2: Critical | K2: 1 | L2: positive | M2: 1. A test resident identity exists in the SingPass test service (ASM-01) | N2: Data created or changed by the steps stays in the SIT test data | O2: Test identity: test resident 01 | P2: 1. Open the Learner login URL 2. Select the SingPass option 3. Authenticate with a test resident identity at SingPass 4. Observe the page after authentication | Q2: 1. The System sends the resident to SingPass for authentication 2. After successful authentication the System signs the resident in 3. The learner landing page opens | R2: Not Executed | S2: Tender 2.2 (Enrolment, Sprint 1) | T2: EP | U2: CP-001 | V2: N/A | W2: ASM-01, ASM-03 | X2: Integration | Y2: Approve | Z2: 2.2 states that SingPass integration authenticates Singapore Residents for login
A3: TC-SCN-001-02 | B3: 2.2 | C3: Enrolment | D3: 1 | E3: SCN-001 | F3: Resident signs in with SingPass | G3: SingPass authentication fails | H3: A Singapore Resident authenticates through SingPass and is signed in. Case: SingPass authentication fails | I3: Failure&Recovery | J3: Critical | K3: 2 | L3: negative | M3: 1. A test resident identity exists in the SingPass test service (ASM-01) | N3: Data created or changed by the steps stays in the SIT test data | O3: Test identity: test resident 01 | P3: 1. Open the Learner login URL 2. Select the SingPass option 3. Cancel the authentication at SingPass 4. Observe the page that opens | Q3: 1. The resident is not signed in 2. The login page is shown again | R3: Not Executed | S3: Tender 2.2 (Enrolment, Sprint 1) | T3: EP | U3: CP-001 | V3: ASM-10 | W3: ASM-01, ASM-03 | X3: Integration | Y3: Draft | Z3: 2.2 requires authentication through SingPass. A failed authentication must not sign the user in
A4: TC-SCN-002-01 | B4: 2.4 | C4: Enrolment | D4: 1 | E4: SCN-002 | F4: Sign in with password and OTP | G4: Learner signs in with ID, password and OTP | H4: A user without SingPass or CorpPass signs in with ID, password and a one time password. Case: Learner signs in with ID, password and OTP | I4: Happy Path | J4: Critical | K4: 2 | L4: positive | M4: 1. A Learner account without SingPass exists (ASM-01) | N4: Data created or changed by the steps stays in the SIT test data | O4: Login ID: learner.test01 OTP: the code received by the tester | P4: 1. Open the Learner login URL 2. Enter a valid login ID and password 3. Enter the one time password received 4. Observe the result | Q4: 1. After the password step the System asks for a one time password 2. After the correct OTP the learner is signed in | R4: Not Executed | S4: Tender 2.4 (Enrolment, Sprint 1) | T4: EP | U4: CP-002 | V4: N/A | W4: ASM-01 | X4: Functional | Y4: Approve | Z4: 2.4 requires login ID, password and 2FA through OTP
A5: TC-SCN-002-02 | B5: 2.4 | C5: Enrolment | D5: 1 | E5: SCN-002 | F5: Sign in with password and OTP | G5: Wrong OTP is rejected | H5: A user without SingPass or CorpPass signs in with ID, password and a one time password. Case: Wrong OTP is rejected | I5: Negative | J5: Critical | K5: 2 | L5: negative | M5: 1. A Learner account without SingPass exists (ASM-01) | N5: Data created or changed by the steps stays in the SIT test data | O5: Login ID: learner.test01 OTP: 000000 | P5: 1. Open the Learner login URL 2. Enter a valid login ID and password 3. Enter an incorrect one time password 4. Observe the result | Q5: 1. The learner is not signed in 2. The login page or OTP page stays open | R5: Not Executed | S5: Tender 2.4 (Enrolment, Sprint 1) | T5: EP | U5: CP-002 | V5: ASM-10 | W5: ASM-01 | X5: Functional | Y5: Draft | Z5: 2.4 requires OTP as the second factor. A wrong OTP must not sign the user in
A6: TC-SCN-003-01 | B6: 5.3.1 | C6: Enrolment | D6: 1 | E6: SCN-003 | F6: Learner portal access | G6: Learner sees catalogue, progress, attendance, assessments and payments | H6: A registered learner uses the portal to browse the catalogue and see own course progress, attendance, assessments and payments. Case: Learner sees catalogue, progress, attendance, assessments and payments | I6: Happy Path | J6: High | K6: 3 | L6: positive | M6: 1. A learner with one enrolled course and one payment exists (ASM-01) | N6: No data is changed by this test | O6: Learner: learner.test01 | P6: 1. Sign in as a registered learner with at least one enrolled course 2. Open the course catalogue 3. Open the page that shows the learner's own courses 4. Check that progress, attendance, assessments and payments are shown | Q6: 1. The learner can browse the course catalogue 2. The learner sees own course progress, attendance, assessments and payments in the portal | R6: Not Executed | S6: Tender 5.3.1 (Enrolment, Sprint 1) | T6: EP | U6: CP-003 | V6: N/A | W6: ASM-01 | X6: Functional | Y6: Approve | Z6: 5.3.1 lists catalogue, progress, attendance, assessments and payments as portal access
A7: TC-SCN-004-01 | B7: 6.1.5 | C7: Enrolment | D7: 1 | E7: SCN-004 | F7: Route choice at registration | G7: Learner registers for the credit bearing route | H7: A course offers both a credit bearing and a non credit bearing route. Case: Learner registers for the credit bearing route | I7: Happy Path | J7: Critical | K7: 2 | L7: positive | M7: 1. A course exists with both routes and an open run (ASM-01) | N7: Data created or changed by the steps stays in the SIT test data | O7: Course: Test Course CB01 | P7: 1. Open a course that offers both routes 2. Select the credit bearing route 3. Complete and submit the registration 4. Open the registration record | Q7: 1. The two routes are shown as different options 2. The registration is saved with the credit bearing route | R7: Not Executed | S7: Tender 6.1.5 (Enrolment, Sprint 1) | T7: EP | U7: CP-004 | V7: N/A | W7: ASM-01 | X7: Functional | Y7: Approve | Z7: 6.1.5 requires the two routes to be differentiated and chosen at registration
A8: TC-SCN-004-02 | B8: 6.1.5 | C8: Enrolment | D8: 1 | E8: SCN-004 | F8: Route choice at registration | G8: Learner registers for the non credit bearing route | H8: A course offers both a credit bearing and a non credit bearing route. Case: Learner registers for the non credit bearing route | I8: Happy Path | J8: Critical | K8: 2 | L8: positive | M8: 1. A course exists with both routes and an open run (ASM-01) | N8: Data created or changed by the steps stays in the SIT test data | O8: Course: Test Course CB01 | P8: 1. Open the same course 2. Select the non credit bearing route 3. Complete and submit the registration 4. Open the registration record | Q8: 1. The registration is saved with the non credit bearing route and not with the credit bearing route | R8: Not Executed | S8: Tender 6.1.5 (Enrolment, Sprint 1) | T8: EP | U8: CP-004 | V8: N/A | W8: ASM-01 | X8: Functional | Y8: Approve | Z8: 6.1.5 requires both routes to be selectable
A9: TC-SCN-005-01 | B9: 6.1.6 | C9: Assessment | D9: 3 | E9: SCN-005 | F9: Assessment types and components | G9: Components and subcomponents are configured for an assessment type | H9: Assessment types and their components are configured per course. Case: Components and subcomponents are configured for an assessment type | I9: Data | J9: Low | K9: 3 | L9: positive | M9: 1. A course exists (ASM-01) | N9: Data created or changed by the steps stays in the SIT test data | O9: Assessment: project work with peer evaluation | P9: 1. Sign in as Course Administrator 2. Create an assessment of type project work 3. Add a peer evaluation component and a subcomponent 4. Save 5. Reopen it | Q9: 1. The assessment type is stored 2. The components and the subcomponent are saved and shown | R9: Not Executed | S9: Tender 6.1.6 (Assessment, Sprint 3) | T9: EP | U9: CP-005 | V9: N/A | W9: ASM-01 | X9: Functional | Y9: Approve | Z9: 6.1.6 requires configuration of components and subcomponents
A10: TC-SCN-006-01 | B10: 6.3.1 | C10: Funding | D10: 1 | E10: SCN-006 | F10: Fee profile creation | G10: Fee profile is created for self sponsored learners | H10: Fee profiles are created for each sponsorship type. Case: Fee profile is created for self sponsored learners | I10: Data | J10: Critical | K10: 2 | L10: positive | M10: 1. A test course exists (ASM-01) | N10: The profile can be selected for a course | O10: Profile: Self Profile 01 Fee: 1000 | P10: 1. Sign in as Finance Administrator 2. Create a fee profile named Self Profile 01 for self sponsored learners 3. Enter the course fee 4. Save 5. Reopen it | Q10: 1. The profile is saved for self sponsored learners with the entered fee | R10: Not Executed | S10: Tender 6.3.1 (Funding, Sprint 1) | T10: EP | U10: CP-006 | V10: N/A | W10: ASM-01 | X10: Functional | Y10: Approve | Z10: 6.3.1 requires a profile for self sponsored cases
A11: TC-SCN-006-02 | B11: 6.3.1 | C11: Funding | D11: 1 | E11: SCN-006 | F11: Fee profile creation | G11: Fee profile is created for company sponsored learners | H11: Fee profiles are created for each sponsorship type. Case: Fee profile is created for company sponsored learners | I11: Data | J11: Critical | K11: 2 | L11: positive | M11: 1. A test course exists (ASM-01) | N11: Data created or changed by the steps stays in the SIT test data | O11: Profile: Company Profile 01 Fee: 1000 | P11: 1. Sign in as Finance Administrator 2. Create a fee profile named Company Profile 01 for company sponsorship 3. Enter the course fee 4. Save 5. Reopen it | Q11: 1. The profile is saved for company sponsorship with the entered fee | R11: Not Executed | S11: Tender 6.3.1 (Funding, Sprint 1) | T11: EP | U11: CP-006 | V11: N/A | W11: ASM-01 | X11: Functional | Y11: Approve | Z11: 6.3.1 requires a profile for company sponsorships
A12: TC-SCN-007-01 | B12: 6.3.2 | C12: Funding | D12: 1 | E12: SCN-007 | F12: Fee and GST calculation | G12: Fee and GST are calculated on a course fee of 1000 | H12: The fee and the GST follow the configured rules. Case: Fee and GST are calculated on a course fee of 1000 | I12: Data Integrity | J12: Critical | K12: 1 | L12: positive | M12: 1. A fee profile with the rule (ASM-01) | N12: Data created or changed by the steps stays in the SIT test data | O12: Fee: 1000 GST rate: 9 percent | P12: 1. Create a calculation rule with GST 9 percent 2. Apply it to a course fee of 1000 3. Open the fee calculation | Q12: 1. The GST is 90.00 and the total is 1090.00 | R12: Not Executed | S12: Tender 6.3.2 (Funding, Sprint 1) | T12: EP | U12: CP-007 | V12: ASM-60 | W12: ASM-01 | X12: Functional | Y12: Draft | Z12: 6.3.2 requires the rules. The rate is configured by the tester
A13: TC-SCN-007-02 | B13: 6.3.2 | C13: Funding | D13: 1 | E13: SCN-007 | F13: Fee and GST calculation | G13: GST is rounded to the cent | H13: The fee and the GST follow the configured rules. Case: GST is rounded to the cent | I13: Boundary | J13: Critical | K13: 2 | L13: boundary | M13: 1. A fee profile with the rule (ASM-01) | N13: Data created or changed by the steps stays in the SIT test data | O13: Fee: 10.05 GST rate: 9 percent | P13: 1. Apply the rule to a fee of 10.05 2. Open the fee calculation | Q13: 1. The GST is 0.90 (0.9045 rounded to the cent) and the total is 10.95 | R13: Not Executed | S13: Tender 6.3.2 (Funding, Sprint 1) | T13: BVA | U13: CP-007 | V13: ASM-60 | W13: ASM-01 | X13: Functional | Y13: Draft | Z13: 6.3.2 requires automatic calculation. The rounding is assumed
... A328: TC-SCN-162-01 | B328: 18.4.5 | C328: Funding | D328: Unscheduled | E328: SCN-162 | F328: Latest PSEA requirements | G328: Verify the System meets the latest MOE PSEA integration requirements | H328: The latest requirements are met. Case: Verify the System meets the latest MOE PSEA integration requirements | I328: Workflow | J328: Low | K328: 3 | L328: negative | M328: N/A | N328: N/A | O328: N/A | P328: N/A | Q328: N/A | R328: Not Executed | S328: Tender 18.4.5 (Funding, Sprint Unscheduled) | T328: N/A | U328: CP-162 | V328: N/A | W328: ASM-01 | X328: Integration | Y328: Reject | Z328: The clause says always enhanced and latest and gives no requirement, version or date to test against

Sheet Scenarios
A1: Scenario ID | B1: Checkpoint | C1: Requirement (Tender clause) | D1: Module | E1: Sprint | F1: Lens | G1: Technique | H1: Title | I1: Condition | J1: Evidence | K1: Open ASM or NEG | L1: Test cases | M1: Approve | N1: Draft | O1: Reject | P1: Status
A2: SCN-001 | B2: CP-001 | C2: 2.2 | D2: Enrolment | E2: 1 | F2: Happy Path | G2: EP | H2: Resident signs in with SingPass | I2: A Singapore Resident authenticates through SingPass and is signed in | J2: Tender 2.2: "The System shall provide integration with SingPass for authentication of Singapore Residents for login." | K2: ASM-03, ASM-10 | L2: =COUNTIFS(TestCases!$E$2:$E$328,$A2) -> 2 | M2: =COUNTIFS(TestCases!$E$2:$E$328,$A2,TestCases!$Y$2:$Y$328,"Approve") -> 1 | N2: =COUNTIFS(TestCases!$E$2:$E$328,$A2,TestCases!$Y$2:$Y$328,"Draft") -> 1 | O2: =COUNTIFS(TestCases!$E$2:$E$328,$A2,TestCases!$Y$2:$Y$328,"Reject") -> 0 | P2: =IF(M2=L2,"Approve",IF(O2=L2,"Reject","Draft")) -> Draft
A3: SCN-002 | B3: CP-002 | C3: 2.4 | D3: Enrolment | E3: 1 | F3: Happy Path | G3: EP | H3: Sign in with password and OTP | I3: A user without SingPass or CorpPass signs in with ID, password and a one time password | J3: Tender 2.4: "The System shall cater for credential login ID, password and 2FA through One Time Password (OTP) for Learners, Corporate Customers and external users (external trainers, both local & overseas) who cannot be authenticated using SingPass and CorpPass for login." | K3: ASM-10 | L3: =COUNTIFS(TestCases!$E$2:$E$328,$A3) -> 2 | M3: =COUNTIFS(TestCases!$E$2:$E$328,$A3,TestCases!$Y$2:$Y$328,"Approve") -> 1 | N3: =COUNTIFS(TestCases!$E$2:$E$328,$A3,TestCases!$Y$2:$Y$328,"Draft") -> 1 | O3: =COUNTIFS(TestCases!$E$2:$E$328,$A3,TestCases!$Y$2:$Y$328,"Reject") -> 0 | P3: =IF(M3=L3,"Approve",IF(O3=L3,"Reject","Draft")) -> Draft
A4: SCN-003 | B4: CP-003 | C4: 5.3.1 | D4: Enrolment | E4: 1 | F4: Workflow | G4: EP | H4: Learner portal access | I4: A registered learner uses the portal to browse the catalogue and see own course progress, attendance, assessments and payments | J4: Tender 5.3.1: "Learners shall have access to browse the course catalogue, their course progress including attendance, assessments, payments and make requests via a portal. SingPass MyInfo integration should be done to allow users to retrieve personal particulars information easily." | K4: N/A | L4: =COUNTIFS(TestCases!$E$2:$E$328,$A4) -> 1 | M4: =COUNTIFS(TestCases!$E$2:$E$328,$A4,TestCases!$Y$2:$Y$328,"Approve") -> 1 | N4: =COUNTIFS(TestCases!$E$2:$E$328,$A4,TestCases!$Y$2:$Y$328,"Draft") -> 0 | O4: =COUNTIFS(TestCases!$E$2:$E$328,$A4,TestCases!$Y$2:$Y$328,"Reject") -> 0 | P4: =IF(M4=L4,"Approve",IF(O4=L4,"Reject","Draft")) -> Approve
A5: SCN-004 | B5: CP-004 | C5: 6.1.5 | D5: Enrolment | E5: 1 | F5: Data | G5: EP | H5: Route choice at registration | I5: A course offers both a credit bearing and a non credit bearing route | J5: Tender 6.1.5: "The System shall allow the differentiation between Credit Bearing and Non-Credit Bearing routes to a course and allow learners to pursue register accordingly." | K5: N/A | L5: =COUNTIFS(TestCases!$E$2:$E$328,$A5) -> 2 | M5: =COUNTIFS(TestCases!$E$2:$E$328,$A5,TestCases!$Y$2:$Y$328,"Approve") -> 2 | N5: =COUNTIFS(TestCases!$E$2:$E$328,$A5,TestCases!$Y$2:$Y$328,"Draft") -> 0 | O5: =COUNTIFS(TestCases!$E$2:$E$328,$A5,TestCases!$Y$2:$Y$328,"Reject") -> 0 | P5: =IF(M5=L5,"Approve",IF(O5=L5,"Reject","Draft")) -> Approve
A6: SCN-005 | B6: CP-005 | C6: 6.1.6 | D6: Assessment | E6: 3 | F6: Data | G6: EP | H6: Assessment types and components | I6: Assessment types and their components are configured per course | J6: Tender 6.1.6: "The System shall have the capability to differentiate the different courses and types of assessments created and allow configuration of assessment components and subcomponents. This would include peer evaluation, multiple choice questions, project work, etc." | K6: N/A | L6: =COUNTIFS(TestCases!$E$2:$E$328,$A6) -> 1 | M6: =COUNTIFS(TestCases!$E$2:$E$328,$A6,TestCases!$Y$2:$Y$328,"Approve") -> 1 | N6: =COUNTIFS(TestCases!$E$2:$E$328,$A6,TestCases!$Y$2:$Y$328,"Draft") -> 0 | O6: =COUNTIFS(TestCases!$E$2:$E$328,$A6,TestCases!$Y$2:$Y$328,"Reject") -> 0 | P6: =IF(M6=L6,"Approve",IF(O6=L6,"Reject","Draft")) -> Approve
A7: SCN-006 | B7: CP-006 | C7: 6.3.1 | D7: Funding | E7: 1 | F7: Data | G7: EP | H7: Fee profile creation | I7: Fee profiles are created for each sponsorship type | J7: Tender 6.3.1: "The System shall allow course fee profile creation for self-sponsored and company sponsorships cases." | K7: N/A | L7: =COUNTIFS(TestCases!$E$2:$E$328,$A7) -> 2 | M7: =COUNTIFS(TestCases!$E$2:$E$328,$A7,TestCases!$Y$2:$Y$328,"Approve") -> 2 | N7: =COUNTIFS(TestCases!$E$2:$E$328,$A7,TestCases!$Y$2:$Y$328,"Draft") -> 0 | O7: =COUNTIFS(TestCases!$E$2:$E$328,$A7,TestCases!$Y$2:$Y$328,"Reject") -> 0 | P7: =IF(M7=L7,"Approve",IF(O7=L7,"Reject","Draft")) -> Approve
A8: SCN-007 | B8: CP-007 | C8: 6.3.2 | D8: Funding | E8: 1 | F8: Data Integrity | G8: BVA | H8: Fee and GST calculation | I8: The fee and the GST follow the configured rules | J8: Tender 6.3.2: "The System shall allow the creation of rules for calculation of course fees and GST." | K8: ASM-60 | L8: =COUNTIFS(TestCases!$E$2:$E$328,$A8) -> 2 | M8: =COUNTIFS(TestCases!$E$2:$E$328,$A8,TestCases!$Y$2:$Y$328,"Approve") -> 0 | N8: =COUNTIFS(TestCases!$E$2:$E$328,$A8,TestCases!$Y$2:$Y$328,"Draft") -> 2 | O8: =COUNTIFS(TestCases!$E$2:$E$328,$A8,TestCases!$Y$2:$Y$328,"Reject") -> 0 | P8: =IF(M8=L8,"Approve",IF(O8=L8,"Reject","Draft")) -> Draft
A9: SCN-008 | B9: CP-008 | C9: 6.3.3 | D9: Funding | E9: 2 | F9: Business Risk | G9: DecisionTable | H9: Fee change by case | I9: Each case changes the fee and needs approval | J9: Tender 6.3.3: "The System shall allow fee changes and approval in cases including but not limited to: // 1) Withdrawals // 2) Leave of Absence (LOA) // 3) Deferrals // 4) Termination" | K9: ASM-61 | L9: =COUNTIFS(TestCases!$E$2:$E$328,$A9) -> 5 | M9: =COUNTIFS(TestCases!$E$2:$E$328,$A9,TestCases!$Y$2:$Y$328,"Approve") -> 0 | N9: =COUNTIFS(TestCases!$E$2:$E$328,$A9,TestCases!$Y$2:$Y$328,"Draft") -> 5 | O9: =COUNTIFS(TestCases!$E$2:$E$328,$A9,TestCases!$Y$2:$Y$328,"Reject") -> 0 | P9: =IF(M9=L9,"Approve",IF(O9=L9,"Reject","Draft")) -> Draft
A10: SCN-009 | B10: CP-009 | C10: 6.3.4 | D10: Funding | E10: 2 | F10: Workflow | G10: EP | H10: Payment processes | I10: Applicant and sponsor payments follow their own process | J10: Tender 6.3.4: "The System shall allow different payment processes for: 1) Applicant Payments, 2) Sponsor Payments." | K10: N/A | L10: =COUNTIFS(TestCases!$E$2:$E$328,$A10) -> 2 | M10: =COUNTIFS(TestCases!$E$2:$E$328,$A10,TestCases!$Y$2:$Y$328,"Approve") -> 2 | N10: =COUNTIFS(TestCases!$E$2:$E$328,$A10,TestCases!$Y$2:$Y$328,"Draft") -> 0 | O10: =COUNTIFS(TestCases!$E$2:$E$328,$A10,TestCases!$Y$2:$Y$328,"Reject") -> 0 | P10: =IF(M10=L10,"Approve",IF(O10=L10,"Reject","Draft")) -> Approve
A11: SCN-010 | B11: CP-010 | C11: 6.3.5 | D11: Funding | E11: 3 | F11: Business Risk | G11: EP | H11: Fees for reschedule and reassessment | I11: A fee is generated when a class or an assessment is rescheduled | J11: Tender 6.3.5: "The System shall have the capability to generate fees in cases including but not limited to: // 1) Rescheduling; // 2) Reassessment." | K11: ASM-61 | L11: =COUNTIFS(TestCases!$E$2:$E$328,$A11) -> 2 | M11: =COUNTIFS(TestCases!$E$2:$E$328,$A11,TestCases!$Y$2:$Y$328,"Approve") -> 0 | N11: =COUNTIFS(TestCases!$E$2:$E$328,$A11,TestCases!$Y$2:$Y$328,"Draft") -> 2 | O11: =COUNTIFS(TestCases!$E$2:$E$328,$A11,TestCases!$Y$2:$Y$328,"Reject") -> 0 | P11: =IF(M11=L11,"Approve",IF(O11=L11,"Reject","Draft")) -> Draft
A12: SCN-011 | B12: CP-011 | C12: 6.3.6 | D12: Funding | E12: 1,2,3 | F12: Business Risk | G12: DecisionTable | H12: Fee by criteria | I12: The fee payable changes with the learner or company criteria | J12: Tender 6.3.6: "The System shall have the capability to generate fees payable with automatic calculation based on criteria including but not limited to: // 1) Nationality/citizenship of candidates; // 2) Age/Date of Birth; // 3) Income; // 4) Alumni status // 5) Alumni credits // 6) Company SME ..." | K12: ASM-62, ASM-71 | L12: =COUNTIFS(TestCases!$E$2:$E$328,$A12) -> 6 | M12: =COUNTIFS(TestCases!$E$2:$E$328,$A12,TestCases!$Y$2:$Y$328,"Approve") -> 0 | N12: =COUNTIFS(TestCases!$E$2:$E$328,$A12,TestCases!$Y$2:$Y$328,"Draft") -> 6 | O12: =COUNTIFS(TestCases!$E$2:$E$328,$A12,TestCases!$Y$2:$Y$328,"Reject") -> 0 | P12: =IF(M12=L12,"Approve",IF(O12=L12,"Reject","Draft")) -> Draft
A13: SCN-012 | B13: CP-012 | C13: 6.3.7 | D13: Funding | E13: 2 | F13: Business Risk | G13: EP | H13: Fee structure setup and approval | I13: A fee structure is set up and approved by a checker and an approver | J13: Tender 6.3.7: "The System shall have the capability to setup various course fee structures and associated administration fee, volume discount, material fee, reassessment fee, registration fee, course exemption fee, etc including but not limited to: 1) Installment payments; 2) Late payments. The..." | K13: ASM-63, ASM-73 | L13: =COUNTIFS(TestCases!$E$2:$E$328,$A13) -> 5 | M13: =COUNTIFS(TestCases!$E$2:$E$328,$A13,TestCases!$Y$2:$Y$328,"Approve") -> 1 | N13: =COUNTIFS(TestCases!$E$2:$E$328,$A13,TestCases!$Y$2:$Y$328,"Draft") -> 4 | O13: =COUNTIFS(TestCases!$E$2:$E$328,$A13,TestCases!$Y$2:$Y$328,"Reject") -> 0 | P13: =IF(M13=L13,"Approve",IF(O13=L13,"Reject","Draft")) -> Draft
... A163: SCN-162 | B163: CP-162 | C163: 18.4.5 | D163: Funding | E163: Unscheduled | F163: Workflow | G163: EP | H163: Latest PSEA requirements | I163: The latest requirements are met | J163: Tender 18.4.5: "The System shall be always enhanced and updated with the latest MOE PSEA integration requirements." | K163: NEG-08 | L163: =COUNTIFS(TestCases!$E$2:$E$328,$A163) -> 1 | M163: =COUNTIFS(TestCases!$E$2:$E$328,$A163,TestCases!$Y$2:$Y$328,"Approve") -> 0 | N163: =COUNTIFS(TestCases!$E$2:$E$328,$A163,TestCases!$Y$2:$Y$328,"Draft") -> 0 | O163: =COUNTIFS(TestCases!$E$2:$E$328,$A163,TestCases!$Y$2:$Y$328,"Reject") -> 1 | P163: =IF(M163=L163,"Approve",IF(O163=L163,"Reject","Draft")) -> Reject

Sheet Checkpoint
A1: CP ID | B1: Location in Tender | C1: Requirement (Tender clause) | D1: Point to test | E1: Module | F1: Sprint | G1: Flag | H1: Test case can be generated | I1: Open ASM or NEG and Dependency | J1: Expected test case status | K1: Short reason | L1: TC IDs | M1: Defect IDs | N1: Approve | O1: Draft | P1: Reject
A2: CP-001 | B2: Tender row 24 | C2: 2.2 | D2: Singapore Residents are authenticated through SingPass for login | E2: Enrolment | F2: 1 | G2: Clear | H2: =IF(COUNTIFS(TestCases!$U$2:$U$328,$A2,TestCases!$Y$2:$Y$328,"<>Reject")>0,"Yes","No") -> Yes | I2: ASM-03, ASM-10 | J2: Approve | K2: The expected result is read from the clause text | L2: TC-SCN-001-01, TC-SCN-001-02 | M2: DEF-001 | N2: =COUNTIFS(TestCases!$U$2:$U$328,$A2,TestCases!$Y$2:$Y$328,"Approve") -> 1 | O2: =COUNTIFS(TestCases!$U$2:$U$328,$A2,TestCases!$Y$2:$Y$328,"Draft") -> 1 | P2: =COUNTIFS(TestCases!$U$2:$U$328,$A2,TestCases!$Y$2:$Y$328,"Reject") -> 0
A3: CP-002 | B3: Tender row 26 | C3: 2.4 | D3: Learners, Corporate Customers and external users who cannot use SingPass or CorpPass log in with ID, password and OTP | E3: Enrolment | F3: 1 | G3: Assumed | H3: =IF(COUNTIFS(TestCases!$U$2:$U$328,$A3,TestCases!$Y$2:$Y$328,"<>Reject")>0,"Yes","No") -> Yes | I3: ASM-10 | J3: Draft | K3: Draft cases need ASM-10 to write the expected result | L3: TC-SCN-002-01, TC-SCN-002-02 | M3: N/A | N3: =COUNTIFS(TestCases!$U$2:$U$328,$A3,TestCases!$Y$2:$Y$328,"Approve") -> 1 | O3: =COUNTIFS(TestCases!$U$2:$U$328,$A3,TestCases!$Y$2:$Y$328,"Draft") -> 1 | P3: =COUNTIFS(TestCases!$U$2:$U$328,$A3,TestCases!$Y$2:$Y$328,"Reject") -> 0
A4: CP-003 | B4: Tender row 180 | C4: 5.3.1 | D4: Registered learners browse the catalogue, their progress, attendance, assessments and payments, and make requests in the portal | E4: Enrolment | F4: 1 | G4: Clear | H4: =IF(COUNTIFS(TestCases!$U$2:$U$328,$A4,TestCases!$Y$2:$Y$328,"<>Reject")>0,"Yes","No") -> Yes | I4: N/A | J4: Approve | K4: The expected result is read from the clause text | L4: TC-SCN-003-01 | M4: N/A | N4: =COUNTIFS(TestCases!$U$2:$U$328,$A4,TestCases!$Y$2:$Y$328,"Approve") -> 1 | O4: =COUNTIFS(TestCases!$U$2:$U$328,$A4,TestCases!$Y$2:$Y$328,"Draft") -> 0 | P4: =COUNTIFS(TestCases!$U$2:$U$328,$A4,TestCases!$Y$2:$Y$328,"Reject") -> 0
A5: CP-004 | B5: Tender row 202 | C5: 6.1.5 | D5: Credit bearing and non credit bearing routes are different and learners register for the route they choose | E5: Enrolment | F5: 1 | G5: Clear | H5: =IF(COUNTIFS(TestCases!$U$2:$U$328,$A5,TestCases!$Y$2:$Y$328,"<>Reject")>0,"Yes","No") -> Yes | I5: N/A | J5: Approve | K5: The expected result is read from the clause text | L5: TC-SCN-004-01, TC-SCN-004-02 | M5: N/A | N5: =COUNTIFS(TestCases!$U$2:$U$328,$A5,TestCases!$Y$2:$Y$328,"Approve") -> 2 | O5: =COUNTIFS(TestCases!$U$2:$U$328,$A5,TestCases!$Y$2:$Y$328,"Draft") -> 0 | P5: =COUNTIFS(TestCases!$U$2:$U$328,$A5,TestCases!$Y$2:$Y$328,"Reject") -> 0
A6: CP-005 | B6: Tender row 203 | C6: 6.1.6 | D6: Assessments of different courses and types are differentiated and components and subcomponents are configurable (peer evaluation, multiple choice, project work) | E6: Assessment | F6: 3 | G6: Clear | H6: =IF(COUNTIFS(TestCases!$U$2:$U$328,$A6,TestCases!$Y$2:$Y$328,"<>Reject")>0,"Yes","No") -> Yes | I6: N/A | J6: Approve | K6: The expected result is read from the clause text | L6: TC-SCN-005-01 | M6: N/A | N6: =COUNTIFS(TestCases!$U$2:$U$328,$A6,TestCases!$Y$2:$Y$328,"Approve") -> 1 | O6: =COUNTIFS(TestCases!$U$2:$U$328,$A6,TestCases!$Y$2:$Y$328,"Draft") -> 0 | P6: =COUNTIFS(TestCases!$U$2:$U$328,$A6,TestCases!$Y$2:$Y$328,"Reject") -> 0
A7: CP-006 | B7: Tender row 222 | C7: 6.3.1 | D7: Course fee profiles are created for self sponsored and company sponsored cases | E7: Funding | F7: 1 | G7: Clear | H7: =IF(COUNTIFS(TestCases!$U$2:$U$328,$A7,TestCases!$Y$2:$Y$328,"<>Reject")>0,"Yes","No") -> Yes | I7: N/A | J7: Approve | K7: The expected result is read from the clause text | L7: TC-SCN-006-01, TC-SCN-006-02 | M7: N/A | N7: =COUNTIFS(TestCases!$U$2:$U$328,$A7,TestCases!$Y$2:$Y$328,"Approve") -> 2 | O7: =COUNTIFS(TestCases!$U$2:$U$328,$A7,TestCases!$Y$2:$Y$328,"Draft") -> 0 | P7: =COUNTIFS(TestCases!$U$2:$U$328,$A7,TestCases!$Y$2:$Y$328,"Reject") -> 0
A8: CP-007 | B8: Tender row 223 | C8: 6.3.2 | D8: Rules for calculation of course fees and GST are created | E8: Funding | F8: 1 | G8: Assumed | H8: =IF(COUNTIFS(TestCases!$U$2:$U$328,$A8,TestCases!$Y$2:$Y$328,"<>Reject")>0,"Yes","No") -> Yes | I8: ASM-60 | J8: Draft | K8: Draft cases need ASM-60 to write the expected result | L8: TC-SCN-007-01, TC-SCN-007-02 | M8: DEF-002 | N8: =COUNTIFS(TestCases!$U$2:$U$328,$A8,TestCases!$Y$2:$Y$328,"Approve") -> 0 | O8: =COUNTIFS(TestCases!$U$2:$U$328,$A8,TestCases!$Y$2:$Y$328,"Draft") -> 2 | P8: =COUNTIFS(TestCases!$U$2:$U$328,$A8,TestCases!$Y$2:$Y$328,"Reject") -> 0
A9: CP-008 | B9: Tender rows 224 to 228 | C9: 6.3.3 | D9: Fee changes and approval for withdrawals, leave of absence, deferrals and termination | E9: Funding | F9: 2 | G9: Assumed | H9: =IF(COUNTIFS(TestCases!$U$2:$U$328,$A9,TestCases!$Y$2:$Y$328,"<>Reject")>0,"Yes","No") -> Yes | I9: ASM-61 | J9: Draft | K9: Draft cases need ASM-61 to write the expected result | L9: TC-SCN-008-01, TC-SCN-008-02, TC-SCN-008-03, TC-SCN-008-04, TC-SCN-008-05 | M9: DEF-003 | N9: =COUNTIFS(TestCases!$U$2:$U$328,$A9,TestCases!$Y$2:$Y$328,"Approve") -> 0 | O9: =COUNTIFS(TestCases!$U$2:$U$328,$A9,TestCases!$Y$2:$Y$328,"Draft") -> 5 | P9: =COUNTIFS(TestCases!$U$2:$U$328,$A9,TestCases!$Y$2:$Y$328,"Reject") -> 0
A10: CP-009 | B10: Tender row 229 | C10: 6.3.4 | D10: Different payment processes for applicant payments and sponsor payments | E10: Funding | F10: 2 | G10: Clear | H10: =IF(COUNTIFS(TestCases!$U$2:$U$328,$A10,TestCases!$Y$2:$Y$328,"<>Reject")>0,"Yes","No") -> Yes | I10: N/A | J10: Approve | K10: The expected result is read from the clause text | L10: TC-SCN-009-01, TC-SCN-009-02 | M10: N/A | N10: =COUNTIFS(TestCases!$U$2:$U$328,$A10,TestCases!$Y$2:$Y$328,"Approve") -> 2 | O10: =COUNTIFS(TestCases!$U$2:$U$328,$A10,TestCases!$Y$2:$Y$328,"Draft") -> 0 | P10: =COUNTIFS(TestCases!$U$2:$U$328,$A10,TestCases!$Y$2:$Y$328,"Reject") -> 0
A11: CP-010 | B11: Tender rows 230 to 232 | C11: 6.3.5 | D11: Fees are generated for rescheduling and reassessment | E11: Funding | F11: 3 | G11: Assumed | H11: =IF(COUNTIFS(TestCases!$U$2:$U$328,$A11,TestCases!$Y$2:$Y$328,"<>Reject")>0,"Yes","No") -> Yes | I11: ASM-61 | J11: Draft | K11: Draft cases need ASM-61 to write the expected result | L11: TC-SCN-010-01, TC-SCN-010-02 | M11: N/A | N11: =COUNTIFS(TestCases!$U$2:$U$328,$A11,TestCases!$Y$2:$Y$328,"Approve") -> 0 | O11: =COUNTIFS(TestCases!$U$2:$U$328,$A11,TestCases!$Y$2:$Y$328,"Draft") -> 2 | P11: =COUNTIFS(TestCases!$U$2:$U$328,$A11,TestCases!$Y$2:$Y$328,"Reject") -> 0
A12: CP-011 | B12: Tender rows 233 to 240 | C12: 6.3.6 | D12: Fees payable are calculated automatically by nationality, age, income, alumni status, alumni credits, company SME status and MOE teacher | E12: Funding | F12: 1,2,3 | G12: Assumed | H12: =IF(COUNTIFS(TestCases!$U$2:$U$328,$A12,TestCases!$Y$2:$Y$328,"<>Reject")>0,"Yes","No") -> Yes | I12: ASM-62, ASM-71 | J12: Draft | K12: Draft cases need ASM-62, ASM-71 to write the expected result | L12: TC-SCN-011-01, TC-SCN-011-02, TC-SCN-011-03, TC-SCN-011-04, TC-SCN-011-05, TC-SCN-011-06 | M12: DEF-004, DEF-005 | N12: =COUNTIFS(TestCases!$U$2:$U$328,$A12,TestCases!$Y$2:$Y$328,"Approve") -> 0 | O12: =COUNTIFS(TestCases!$U$2:$U$328,$A12,TestCases!$Y$2:$Y$328,"Draft") -> 6 | P12: =COUNTIFS(TestCases!$U$2:$U$328,$A12,TestCases!$Y$2:$Y$328,"Reject") -> 0
A13: CP-012 | B13: Tender row 241 | C13: 6.3.7 | D13: Fee structures with administration, volume discount, material, reassessment, registration and exemption fees, installments, late payments and checker and approver | E13: Funding | F13: 2 | G13: Assumed | H13: =IF(COUNTIFS(TestCases!$U$2:$U$328,$A13,TestCases!$Y$2:$Y$328,"<>Reject")>0,"Yes","No") -> Yes | I13: ASM-63, ASM-73 | J13: Draft | K13: Draft cases need ASM-63, ASM-73 to write the expected result | L13: TC-SCN-012-01, TC-SCN-012-02, TC-SCN-012-03, TC-SCN-012-04, TC-SCN-012-05 | M13: DEF-006 | N13: =COUNTIFS(TestCases!$U$2:$U$328,$A13,TestCases!$Y$2:$Y$328,"Approve") -> 1 | O13: =COUNTIFS(TestCases!$U$2:$U$328,$A13,TestCases!$Y$2:$Y$328,"Draft") -> 4 | P13: =COUNTIFS(TestCases!$U$2:$U$328,$A13,TestCases!$Y$2:$Y$328,"Reject") -> 0
... A163: CP-162 | B163: Tender row 969 | C163: 18.4.5 | D163: The System is always enhanced and updated with the latest MOE PSEA integration requirements | E163: Funding | F163: Unscheduled | G163: Blocked | H163: =IF(COUNTIFS(TestCases!$U$2:$U$328,$A163,TestCases!$Y$2:$Y$328,"<>Reject")>0,"Yes","No") -> No | I163: NEG-08 | J163: Reject | K163: No expected result can be written from this clause | L163: TC-SCN-162-01 | M163: N/A | N163: =COUNTIFS(TestCases!$U$2:$U$328,$A163,TestCases!$Y$2:$Y$328,"Approve") -> 0 | O163: =COUNTIFS(TestCases!$U$2:$U$328,$A163,TestCases!$Y$2:$Y$328,"Draft") -> 0 | P163: =COUNTIFS(TestCases!$U$2:$U$328,$A163,TestCases!$Y$2:$Y$328,"Reject") -> 1

Sheet Defects
A1: Defect ID | B1: Module | C1: Sprint | D1: Tender clause | E1: Flow step (draft) | F1: Related TC IDs | G1: Summary | H1: Environment | I1: Preconditions | J1: Steps to Reproduce | K1: Expected Result | L1: Potential Actual Result (hypothetical) | M1: Business impact | N1: Severity | O1: Impact level | P1: Urgency | Q1: Priority | R1: Triage rationale | S1: Evidence | T1: Status | U1: Suggested regression suite
A2: DEF-001 | B2: Enrolment | C2: 1 | D2: 2.2 | E2: 1 Login and MyInfo | F2: TC-SCN-001-01 | G2: [Login] Resident is not signed in after successful SingPass authentication, the login page reloads | H2: SIT (assumed, ASM-01) | I2: 1. A test resident identity exists in the SingPass test service | J2: 1. Open the Learner login URL 2. Select the SingPass option 3. Authenticate with a test resident identity at SingPass 4. Observe the page after authentication | K2: 1. The System sends the resident to SingPass for authentication 2. After successful authentication the System signs the resident in 3. The learner landing page opens | L2: The login page loads again after SingPass returns success; no session is created | M2: Residents cannot reach the learner portal, so self enrolment cannot start | N2: 1 | O2: =IF(N2<=2,"High","Low") -> High | P2: High | Q2: =IF(O2="High",IF(P2="High","Critical","High"),IF(P2="High","Medium","Low")) -> Critical | R2: Blocks the first step of Self-Enrol. Severity 1: Blocker, or money, funding or compliance break. Urgency High by ASM-92. | S2: Tender 2.2: "The System shall provide integration with SingPass for authentication of Singapore Residents for login." | T2: Potential | U2: =IF(N2=1,"Smoke",IF(N2=2,"Regression Core","Regression Extended")) -> Smoke
A3: DEF-002 | B3: Funding | C3: 1 | D3: 6.3.2 | E3: 6 Net fee and invoice | F3: TC-SCN-007-01 | G3: [Funding] GST is charged twice on the course fee | H3: SIT (assumed, ASM-01) | I3: 1. A fee profile with the rule | J3: 1. Create a calculation rule with GST 9 percent 2. Apply it to a course fee of 1000 3. Open the fee calculation | K3: 1. The GST is 90.00 and the total is 1090.00 | L3: The GST is 180.00 and the total is 1180.00 for a fee of 1000 with a rate of 9 percent | M3: The learner is overcharged and the finance records are wrong | N3: 1 | O3: =IF(N3<=2,"High","Low") -> High | P3: High | Q3: =IF(O3="High",IF(P3="High","Critical","High"),IF(P3="High","Medium","Low")) -> Critical | R3: Money is calculated wrongly on every invoice. Severity 1: Blocker, or money, funding or compliance break. Urgency High by ASM-92. | S3: Tender 6.3.2: "The System shall allow the creation of rules for calculation of course fees and GST." | T3: Potential | U3: =IF(N3=1,"Smoke",IF(N3=2,"Regression Core","Regression Extended")) -> Smoke
A4: DEF-003 | B4: Funding | C4: 2 | D4: 6.3.3 | E4: 4 Grant eligibility and fee | F4: TC-SCN-008-05 | G4: [Funding] Fee change of a withdrawal is applied before the approver approves | H4: SIT (assumed, ASM-01) | I4: 1. A paid enrolment and a configured rule | J4: 1. Withdraw a paid learner 2. Submit the fee change 3. Open the fee before the approval | K4: 1. The fee is unchanged until the approver approves | L4: The fee is already changed while the request is pending approval | M4: A fee is reduced without the required approval, an audit finding | N4: 1 | O4: =IF(N4<=2,"High","Low") -> High | P4: High | Q4: =IF(O4="High",IF(P4="High","Critical","High"),IF(P4="High","Medium","Low")) -> Critical | R4: Control for money is bypassed. Severity 1: Blocker, or money, funding or compliance break. Urgency High by ASM-92. | S4: Tender 6.3.3: "The System shall allow fee changes and approval in cases including but not limited to: // 1) Withdrawals // 2) Leave of Absence (LOA) // 3) Deferrals // 4) Termination" | T4: Potential | U4: =IF(N4=1,"Smoke",IF(N4=2,"Regression Core","Regression Extended")) -> Smoke
A5: DEF-004 | B5: Funding | C5: 1,2,3 | D5: 6.3.6 | E5: 4 Grant eligibility and fee | F5: TC-SCN-011-02 | G5: [Funding] Learner at the age limit gets the fee of the younger band | H5: SIT (assumed, ASM-01) | I5: 1. An age limit of 40 is configured | J5: 1. Register a learner exactly at the configured age limit and one a year younger 2. Open the fee payable of each | K5: 1. The learner at the limit and the younger learner each get the fee configured for their age band | L5: The learner aged exactly 40 is charged the fee of the below 40 band | M5: The learner is charged the wrong fee at the boundary | N5: 2 | O5: =IF(N5<=2,"High","Low") -> High | P5: High | Q5: =IF(O5="High",IF(P5="High","Critical","High"),IF(P5="High","Medium","Low")) -> Critical | R5: Boundary error on a money rule. Severity 2: Critical or major function fails. Urgency High by ASM-92. | S5: Tender 6.3.6: "The System shall have the capability to generate fees payable with automatic calculation based on criteria including but not limited to: // 1) Nationality/citizenship of candidates; // 2) Age/Date of Birth; // 3) Income; // 4) Alumni status // 5) Alumni credits // 6) Company SME ..." | T5: Potential | U5: =IF(N5=1,"Smoke",IF(N5=2,"Regression Core","Regression Extended")) -> Regression Core
A6: DEF-005 | B6: Funding | C6: 1,2,3 | D6: 6.3.6 | E6: 4 Grant eligibility and fee | F6: TC-SCN-011-05 | G6: [Funding] SME company is charged the fee of a non SME company | H6: SIT (assumed, ASM-01) | I6: 1. An SME rule is configured | J6: 1. Register a learner for an SME company and a learner for a non SME company 2. Open the fee payable of each | K6: 1. The SME company gets the fee configured for SME status and the other does not | L6: The fee payable of the SME company equals the full fee | M6: The company loses the SME entitlement and complains | N6: 2 | O6: =IF(N6<=2,"High","Low") -> High | P6: High | Q6: =IF(O6="High",IF(P6="High","Critical","High"),IF(P6="High","Medium","Low")) -> Critical | R6: Wrong fee for one group of customers. Severity 2: Critical or major function fails. Urgency High by ASM-92. | S6: Tender 6.3.6: "The System shall have the capability to generate fees payable with automatic calculation based on criteria including but not limited to: // 1) Nationality/citizenship of candidates; // 2) Age/Date of Birth; // 3) Income; // 4) Alumni status // 5) Alumni credits // 6) Company SME ..." | T6: Potential | U6: =IF(N6=1,"Smoke",IF(N6=2,"Regression Core","Regression Extended")) -> Regression Core
A7: DEF-006 | B7: Funding | C7: 2 | D7: 6.3.7 | E7: 4 Grant eligibility and fee | F7: TC-SCN-012-05 | G7: [Funding] The user who prepared a fee structure can approve it | H7: SIT (assumed, ASM-01) | I7: 1. A fee structure prepared by one user | J7: 1. Prepare a fee structure 2. Try to approve it with the same user | K7: 1. The approval is refused for the same user | L7: The same user approves the own setup and it becomes active | M7: Check and balance is lost and fees can be changed without a second person | N7: 1 | O7: =IF(N7<=2,"High","Low") -> High | P7: High | Q7: =IF(O7="High",IF(P7="High","Critical","High"),IF(P7="High","Medium","Low")) -> Critical | R7: Audit control fails on fee setup. Severity 1: Blocker, or money, funding or compliance break. Urgency High by ASM-92. | S7: Tender 6.3.7: "The System shall have the capability to setup various course fee structures and associated administration fee, volume discount, material fee, reassessment fee, registration fee, course exemption fee, etc including but not limited to: 1) Installment payments; 2) Late payments. The..." | T7: Potential | U7: =IF(N7=1,"Smoke",IF(N7=2,"Regression Core","Regression Extended")) -> Smoke
A8: DEF-007 | B8: Funding | C8: 1,2 | D8: 6.4.2 | E8: 4 Grant eligibility and fee | F8: TC-SCN-014-04 | G8: [Funding] Group discount is not applied to the third member of a group | H8: SIT (assumed, ASM-01) | I8: 1. A configured group discount | J8: 1. Configure a group discount 2. Enrol a group 3. Open the fee of each member | K8: 1. The group discount is applied to each member of the group | L8: The first two members get the discount and the third pays the full fee | M8: Some learners are overcharged | N8: 2 | O8: =IF(N8<=2,"High","Low") -> High | P8: High | Q8: =IF(O8="High",IF(P8="High","Critical","High"),IF(P8="High","Medium","Low")) -> Critical | R8: Part of a group is charged wrongly. Severity 2: Critical or major function fails. Urgency High by ASM-92. | S8: Tender 6.4.2: "The System shall allow the Course Administrators to configure various types of discounts with complex and multi-tier hierarchical business rules and eligibility criteria, which include: // 1) Special discount, e.g. staff, alumni, Singapore citizens, etc // 2) Promotional discount..." | T8: Potential | U8: =IF(N8=1,"Smoke",IF(N8=2,"Regression Core","Regression Extended")) -> Regression Core
A9: DEF-008 | B9: Funding | C9: 2,3 | D9: 6.4.3 | E9: 4 Grant eligibility and fee | F9: TC-SCN-015-01 | G9: [Funding] Alumni Course Credit is deducted after the SSG grant instead of before | H9: SIT (assumed, ASM-01) | I9: 1. A course with an SSG grant and an alumnus with credit | J9: 1. Enrol an alumnus with a credit of 200 on a course of fee 1000 with an SSG grant 2. Open the fee calculation | K9: 1. The credit of 200 is deducted from the full fee of 1000 first 2. The SSG grant and the subsidy are then computed on the reduced fee | L9: The grant is computed on the full fee of 1000 and the credit is then deducted | M9: The net fee and the grant claimed from SSG are wrong | N9: 1 | O9: =IF(N9<=2,"High","Low") -> High | P9: High | Q9: =IF(O9="High",IF(P9="High","Critical","High"),IF(P9="High","Medium","Low")) -> Critical | R9: The order is stated in the Tender and affects the funding claim. Severity 1: Blocker, or money, funding or compliance break. Urgency High by ASM-92. | S9: Tender 6.4.3: "The System shall allow automation for application of grant, subsidies, SFC, SFC (mid-career) top up, ETSS, credits, discounts, PSEA, Alumni Course Credit (ACC), and Additional Funding Support (AFS applicable for SkillsFuture Career Transition Programme) for fee calculation. // Fo..." | T9: Potential | U9: =IF(N9=1,"Smoke",IF(N9=2,"Regression Core","Regression Extended")) -> Smoke
A10: DEF-009 | B10: Funding | C10: 2,3 | D10: 6.4.3 | E10: 4 Grant eligibility and fee | F10: TC-SCN-015-05 | G10: [Funding] A non eligible learner receives the SSG grant | H10: SIT (assumed, ASM-01) | I10: 1. An ineligible learner | J10: 1. Enrol an ineligible learner in an SSG funded course 2. Open the fee calculation | K10: 1. No grant or subsidy is applied and the full fee is shown | L10: The fee shows the SSG grant for an ineligible learner | M10: SSG funds are claimed without entitlement, a compliance break | N10: 1 | O10: =IF(N10<=2,"High","Low") -> High | P10: High | Q10: =IF(O10="High",IF(P10="High","Critical","High"),IF(P10="High","Medium","Low")) -> Critical | R10: Funding compliance break. Severity 1: Blocker, or money, funding or compliance break. Urgency High by ASM-92. | S10: Tender 6.4.3: "The System shall allow automation for application of grant, subsidies, SFC, SFC (mid-career) top up, ETSS, credits, discounts, PSEA, Alumni Course Credit (ACC), and Additional Funding Support (AFS applicable for SkillsFuture Career Transition Programme) for fee calculation. // Fo..." | T10: Potential | U10: =IF(N10=1,"Smoke",IF(N10=2,"Regression Core","Regression Extended")) -> Smoke
A11: DEF-010 | B11: Funding | C11: 2 | D11: 6.4.4 | E11: 7 Outcome based funding | F11: TC-SCN-016-02 | G11: [Funding] Learner with 74 percent attendance is marked eligible for SSG funding | H11: SIT (assumed, ASM-01) | I11: 1. A completed SSG funded course and a learner | J11: 1. Set attendance to 74 percent and the result to pass 2. Run the funding decision 3. Open the funding status | K11: 1. The learner is not eligible for the SSG funding | L11: The learner with 74 percent attendance and a pass is shown as funded | M11: SSG funding is claimed for a learner who does not qualify | N11: 1 | O11: =IF(N11<=2,"High","Low") -> High | P11: High | Q11: =IF(O11="High",IF(P11="High","Critical","High"),IF(P11="High","Medium","Low")) -> Critical | R11: Compliance break that can lead to a claw back. Severity 1: Blocker, or money, funding or compliance break. Urgency High by ASM-92. | S11: Tender 6.4.4: "The System shall support automated outcome based SkillsFuture Singapore (SSG) funding based on the following requirements: // 1) Minimum 75% attendance // 2) Passing the assessment" | T11: Potential | U11: =IF(N11=1,"Smoke",IF(N11=2,"Regression Core","Regression Extended")) -> Smoke
A12: DEF-011 | B12: Funding | C12: 2 | D12: 6.4.4 | E12: 7 Outcome based funding | F12: TC-SCN-016-03 | G12: [Funding] Learner who failed the assessment is marked eligible for SSG funding | H12: SIT (assumed, ASM-01) | I12: 1. A completed SSG funded course and a learner | J12: 1. Set attendance to 100 percent and the result to fail 2. Run the funding decision 3. Open the funding status | K12: 1. The learner is not eligible for the SSG funding | L12: The learner with 100 percent attendance and a fail is shown as funded | M12: Funding is claimed without a pass | N12: 1 | O12: =IF(N12<=2,"High","Low") -> High | P12: High | Q12: =IF(O12="High",IF(P12="High","Critical","High"),IF(P12="High","Medium","Low")) -> Critical | R12: Compliance break. Severity 1: Blocker, or money, funding or compliance break. Urgency High by ASM-92. | S12: Tender 6.4.4: "The System shall support automated outcome based SkillsFuture Singapore (SSG) funding based on the following requirements: // 1) Minimum 75% attendance // 2) Passing the assessment" | T12: Potential | U12: =IF(N12=1,"Smoke",IF(N12=2,"Regression Core","Regression Extended")) -> Smoke
A13: DEF-012 | B13: Funding | C13: 2 | D13: 6.4.5 | E13: 7 Outcome based funding | F13: TC-SCN-017-01 | G13: [Funding] Block grant is drawn down twice for one completed course | H13: SIT (assumed, ASM-01) | I13: 1. A completed funded course and a test endpoint | J13: 1. Complete an SSG funded course 2. Wait for the integration to run 3. Check the TPGateway test endpoint | K13: 1. The block grant of the completed course is drawn down through TPGateway | L13: The TPGateway test endpoint receives two draw downs for the same course | M13: Grant is over claimed | N13: 1 | O13: =IF(N13<=2,"High","Low") -> High | P13: High | Q13: =IF(O13="High",IF(P13="High","Critical","High"),IF(P13="High","Medium","Low")) -> Critical | R13: Money and compliance. Severity 1: Blocker, or money, funding or compliance break. Urgency High by ASM-92. | S13: Tender 6.4.5: "The System shall support the integration with Training Partners Gateway’s (TPGateway) Financial Management System for automated drawing down of block grants for completed courses." | T13: Potential | U13: =IF(N13=1,"Smoke",IF(N13=2,"Regression Core","Regression Extended")) -> Smoke
... A71: DEF-070 | B71: Funding | C71: 2 | D71: 18.3.3 | E71: 6 Net fee and invoice | F71: TC-SCN-160-01 | G71: [Funding] PSEA claim status stays submitted after the MOE file shows disbursed | H71: SIT (assumed, ASM-01) | I71: 1. A submitted PSEA claim and a status file | J71: 1. Load a MOE status file that shows a claim as disbursed 2. Open the PSEA claim | K71: 1. The claim status is disbursed | L71: The status is not updated | M71: The learner and finance see a wrong status | N71: 2 | O71: =IF(N71<=2,"High","Low") -> High | P71: High | Q71: =IF(O71="High",IF(P71="High","Critical","High"),IF(P71="High","Medium","Low")) -> Critical | R71: Status is wrong. Severity 2: Critical or major function fails. Urgency High by ASM-92. | S71: Tender 18.3.3: "The System shall automatically track and update the PSEA Fund Disbursement status based on the payment disbursement file or status received from MOE." | T71: Potential | U71: =IF(N71=1,"Smoke",IF(N71=2,"Regression Core","Regression Extended")) -> Regression Core

Sheet Assumptions
A1: ASM ID | B1: Type | C1: Requirement | D1: Original gap | E1: Assumption | F1: Nearest evidence | G1: Reason | H1: If the input differs | I1: State | J1: Affected TCs | K1: Question to confirm | L1: Resolution
A2: ASM-01 | B2: Dependency | C2: All clauses | D2: The Tender does not describe test environments, roles or sign in | E2: The SIT environment is ready, one account exists for each role named in a test (Learner, Corporate Customer, Course Administrator, Finance Administrator, System Administrator, Trainer) and the tester is signed in with that role | F2: Tender clause text only; no environment section | G2: Level 1: a test cannot start without an environment and a role. This is a condition of every test case, not a Tender requirement | H2: If sign in or roles differ, add a login step to the precondition of the affected test cases | I2: Open | J2: All test cases (327) | K2: Which SIT environment and which role accounts will the tester use?
A3: ASM-03 | B3: Dependency | C3: 2.2, 2.4, 8.2.5, 8.5.16, 18.1.2, 18.2.1, 18.2.2, 6.4.5, 9.1.4, 10.2.9 | D3: External systems are named but their test endpoints are not described | E3: SingPass, MyInfo, CorpPass, SSG, TPGateway, SFC gateway and PSEA are reachable in SIT through test endpoints or stubs | F3: Tender section 18, clauses on integration | G3: Level 1: integration clauses cannot be tested without a test counterpart | H3: If no test endpoint exists, the integration test cases are blocked and move to Reject | I3: Open | J3: TC-SCN-001-01, TC-SCN-001-02, TC-SCN-017-01, TC-SCN-017-02, TC-SCN-056-01, TC-SCN-056-02, TC-SCN-069-01, TC-SCN-069-02, TC-SCN-084-01, TC-SCN-084-02, TC-SCN-104-01, TC-SCN-104-02, TC-SCN-106-01, TC-SCN-112-01, TC-SCN-119-01, TC-SCN-132-01, TC-SCN-132-02, TC-SCN-151-01, TC-SCN-151-02, TC-SCN-152-01, TC-SCN-152-02, TC-SCN-152-03, TC-SCN-153-01, TC-SCN-154-01, TC-SCN-154-02, TC-SCN-155-01, TC-SCN-156-01, TC-SCN-157-01, TC-SCN-157-02 | K3: Which external test endpoints or stubs exist in SIT?
A4: ASM-10 | B4: Assumption | C4: 2.2, 2.4 | D4: The Tender does not state the message or page shown when authentication fails | E4: When authentication fails the user is not signed in and stays on or returns to the login page. The wording of the message is not checked | F4: Tender 2.2 and 2.4 only state that authentication is provided | G4: Level 1: not signing in is the least that a failed authentication must do. A message text would be invented | H4: If the Tender owner defines the message, add the exact text to Expected Result | I4: Open | J4: TC-SCN-001-02, TC-SCN-002-02 | K4: What does the user see when SingPass or OTP authentication fails?
A5: ASM-11 | B5: Assumption | C5: 8.1.4, 8.2.6 | D5: The Tender lists validation types but gives no limits or messages | E5: Validation uses the field rules configured for the registration form under test. The test case checks that each listed validation type exists, not the specific limit | F5: Tender 8.1.4: mandatory field, data type, format, minimum and maximum length, range, consistency, look up | G5: Level 1: no field limits appear in the Tender | H5: If limits are defined, add boundary values to Test Data | I5: Open | J5: TC-SCN-041-01, TC-SCN-041-02, TC-SCN-041-03 | K5: What are the field rules of the registration form?
A6: ASM-12 | B6: Assumption | C6: 8.2.7 | D6: The Tender does not state how long an application can stay incomplete or when reminders are sent | E6: The stipulated time and reminder timing are configured by the Administrator for the test and are not fixed by the Tender | F6: Tender 8.2.6 and 8.2.7 use the words stipulated time and automatic reminders | G6: Level 1: no duration is given | H6: If a duration is defined, use it as boundary data | I6: Open | J6: TC-SCN-057-01, TC-SCN-058-01, TC-SCN-077-01 | K6: What is the stipulated time and the reminder schedule?
A7: ASM-13 | B7: Assumption | C7: 8.1.10, 8.1.11 | D7: The Tender does not state the default minimum or maximum | E7: Minimum and maximum learner numbers are set by the Administrator for each course run. The test uses small values chosen by the tester | F7: Tender 8.1.10 | G7: Level 1: only the capability to configure is stated | H7: None for expected results | I7: Open | J7: TC-SCN-047-01, TC-SCN-047-02 | K7: What are the allowed ranges for minimum and maximum?
A8: ASM-14 | B8: Assumption | C8: 7.1.1 | D8: The Tender does not state what happens when a learner tries to register outside the registration period | E8: Registration is not accepted outside the configured period. The wording shown to the learner is not checked | F8: Tender 7.1.1 item 4 Course registration period configuration | G8: Level 1: a period that does not stop registration has no meaning | H8: If the Tender owner defines the message, add it to Expected Result | I8: Open | J8: TC-SCN-034-01 | K8: What does the learner see when registration is closed?
A9: ASM-15 | B9: Assumption | C9: 8.1.1 | D9: The Tender does not name the workflow statuses or approvers | E9: The workflow has at least a submitted step and an approved step, and each change is shown in a status history. Status names are not checked | F9: Tender 8.1.1 set up of different workflows for approval with status tracking | G9: Level 1: status tracking implies a visible status per step | H9: If statuses are defined, replace the Expected Result with the exact names | I9: Open | J9: TC-SCN-038-01 | K9: What are the workflow statuses and approvers per course level?
A10: ASM-16 | B10: Assumption | C10: 8.1.3 | D10: The Tender gives no file layout for batch import | E10: The import accepts a file prepared with the columns of the registration form. The exact format is not checked | F10: Tender 8.1.3 import functions for batch registration | G10: Level 1: a file layout is needed to run the test | H10: If a template exists, use it as Test Data | I10: Open | J10: TC-SCN-040-01 | K10: Is there an import template?
A11: ASM-17 | B11: Assumption | C11: 8.1.11, 8.5.3 | D11: The Tender does not define first come first serve when two applications arrive at the same time | E11: Application time is the time the application is submitted. Equal times are not tested | F11: Tender 8.1.11 prioritize the applicants on a first come first serve basis | G11: Level 1: submit time is the only observable time | H11: If another time is defined, change the order of test data | I11: Open | J11: TC-SCN-048-01, TC-SCN-091-02 | K11: Which time decides the order?
A12: ASM-18 | B12: Assumption | C12: 8.1.12, 8.5.3 | D12: The Tender does not say whether the learner or the Administrator confirms the other course | E12: The channelled application is confirmed on the other course after the channel action when seats exist | F12: Tender 8.1.12 channel the applications on the waitlist to another course for confirmation | G12: Level 1: confirmation without a seat is meaningless | H12: If the learner must accept, add the acceptance step | I12: Open | J12: TC-SCN-049-01, TC-SCN-091-03 | K12: Who confirms the channelled application?
A13: ASM-19 | B13: Assumption | C13: 8.2.2 | D13: The Tender does not give the wording of the PDPA declaration or the Terms and Conditions | E13: The declaration and consent are shown as acknowledgement controls that the applicant must select before submitting. The text is not checked | F13: Tender 8.2.2 PDPA declaration and consent captured; acknowledgement of Terms and Conditions | G13: Level 1: capture implies a recorded choice | H13: If consent can be optional, remove the block test | I13: Open | J13: TC-SCN-053-01, TC-SCN-053-02, TC-SCN-053-03 | K13: Is the PDPA consent mandatory to submit?
... A70: ASM-95 | B70: Assumption | C70: All test cases | D70: The sample workbook gives Priority but no rule for it, and the user asked to keep it next to the new Severity | E70: Priority is the order in which a test case is run. It starts from the Severity (1 is Critical, 2 is High, 3 is Medium, 4 is Low) and moves one level up when the clause is delivered in Sprint 1, because it is needed first, and one level down when the clause is delivered only in Sprint 3 or is unscheduled. Severity is the impact if the test fails | F70: User request of 2026-10-06 and Tender column Sprint # | G70: Level 1: a rule is needed so that the two columns are not copies | H70: If the team sets Priority another way, overwrite the Priority column. Severity does not change | I70: Open | J70: Workbook level | K70: How does the team set Priority?
A72: Rules applied
A73: Status | C73: Approve: the expected result is read from the clause, only test data is chosen. Draft: the expected result needs an assumption. Reject: the clause gives no testable expectation, so steps and results are not written
A74: Priority and Severity | C74: Priority (Critical, High, Medium, Low) is kept from the sample and is the order of running (ASM-95). Severity is 1 to 4, 1 is the most severe, and is the impact if the test fails (ASM-90)
A75: Defect priority | C75: Impact x Urgency from Lesson 4 section 22 (ASM-91, ASM-92). Priority and Suggested regression suite are formulas on the Defects sheet
A76: Defect summary | C76: [Module] Action + Symptom + Condition, from Lesson 4
A77: Evidence chain | C77: Checkpoint (CP) to Scenario (SCN) to Test case (TC), as in the sample workbook. Every test case holds the Tender clause as its only requirement source
A78: Execution | C78: No test case was executed. Actual Result is Not Executed. The defects are potential and need execution to be confirmed
A80: References
A81: Tender_requirements_0232.xlsx | C81: Only requirement source. Verbatim clause text and Sprint # (see the Clause Overview and Sprint sheets)
A82: Student_Registration_System_TestCases 2.xlsx | C82: Template for columns, Status logic and the CP, SCN, TC chain
A83: Lesson 4 Defect Management (course) | C83: Severity and Priority, Impact x Urgency, defect summary format, regression
A84: SIT Test Case Sample.pdf and UAT Test Case Sample.pdf | C84: Column set for the group assignment, not used for this workbook

Sheet Negotiation
A1: ID | B1: Type | C1: Tender clause | D1: Content | E1: Temporary handling | F1: Why it cannot be decided from the input | G1: Question for the Tender owner | H1: Impact | I1: Related TCs | J1: State | K1: Resolution
A2: NEG-01 | B2: Dependency | C2: 6.4.4 | D2: 6.4.4 is in Sprint 2 but the attendance and the assessment results it needs are delivered in Sprint 3 (sections 10.1 and 10.2) | E2: Draft test cases that set the attendance and the result as test data in Sprint 2 | F2: The Tender gives no way to get attendance and results before Sprint 3 | G2: Is the outcome based funding of Sprint 2 tested with attendance and results entered as data, or moved to Sprint 3? | H2: Outcome based funding tests of 6.4.4 and step 7 of the flow | I2: TC-SCN-016-01, TC-SCN-016-02, TC-SCN-016-03 | J2: Open
A3: NEG-02 | B3: Conflict | C3: 6.4.7 | D3: The base of the 5 percent cap and the meaning of almost fully utilized in 6.4.7 | E3: Draft test cases with the assumption of ASM-66, one Reject case for the base | F3: The clause has no base for the percentage and no threshold | G3: 5 percent of what and when is the cap almost fully utilized? | H3: Cap tests of 6.4.7 and 8.7.1 | I3: TC-SCN-019-01, TC-SCN-019-02, TC-SCN-019-03, TC-SCN-019-04 | J3: Open
A4: NEG-03 | B4: Conflict | C4: 8.5.1 | D4: The subject and the criteria of 8.5.1 | E4: Treat 8.5.1 as capacity based auto confirmation in order of application (ASM-33) | F4: The sentence is incomplete, so the requirement cannot be read as one rule | G4: What does 8.5.1 require the System to do and under which conditions? | H4: Auto confirmation tests of Sprint 2 and Self-Enrol step 5 | I4: TC-SCN-089-01, TC-SCN-089-02 | J4: Open
A5: NEG-04 | B5: Blocked | C5: 8.5.15 | D5: The meaning of park and post and the workflow for independent review in enrolment | E5: Test case Reject, steps not written | F5: A new workflow would have to be invented to have an expectation | G5: What does park and post do in enrolment, which role reviews and what is the Sprint #? | H5: Auditor requirement for enrolment, no test possible | I5: TC-SCN-103-01 | J5: Open
A6: NEG-05 | B6: Conflict | C6: 8.7.1 | D6: What happens when the cap of 8.7.1 is reached | E6: Draft test cases with the assumption of ASM-78 | F6: The clause configures the cap but not the effect of reaching it | G6: Is the registration blocked or flagged when the cap is reached? | H6: Cap boundary tests of 8.7.1 | I6: TC-SCN-107-01, TC-SCN-107-02, TC-SCN-107-03, TC-SCN-107-04 | J6: Open
A7: NEG-06 | B7: Data issue | C7: 9.1.12 | D7: Row 515 of 9.1.12 has the date 2026-03-02 in the Sprint # cell instead of a sprint number | E7: Sprint 2 is used for the clause, as the other rows of 9.1.12 say 2 | F7: A date cannot be read as a sprint without guessing | G7: Which sprint does item 4 of 9.1.12 (remarks for SFC and alumni credits) belong to? | H7: Remark check of 9.1.12 | I7: TC-SCN-114-01, TC-SCN-114-02, TC-SCN-114-03 | J7: Open
A8: NEG-07 | B8: Blocked | C8: 18.1.2 | D8: The eCert integration, item 7 of 18.1.2, has no Sprint # and no description | E8: Test case Reject, steps not written | F8: No data, direction or result is stated for eCert | G8: What does the eCert integration send and in which sprint? | H8: eCert integration test of Sprint 3 | I8: TC-SCN-154-01, TC-SCN-154-02, TC-SCN-154-03 | J8: Open
A9: NEG-08 | B9: Blocked | C9: 18.4.5 | D9: The latest MOE PSEA requirements of 18.4.5 have no version, date or sprint | E9: Test case Reject, steps not written | F9: No expected result can be written from this clause | G9: Which MOE PSEA requirement version applies and from which sprint? | H9: PSEA tests of 18.3.1 to 18.3.3 | I9: TC-SCN-162-01 | J9: Open

Sheet Regression TestCases
A1: ="Table 1. New test cases for the Self-Enrol + Funding feature: "&COUNTA(A3:A28)&" test cases" -> Table 1. New test cases for the Self-Enrol + Funding feature: 26 test cases
A2: TC ID | B2: Requirement (Tender clause) | C2: Module | D2: Sprint | E2: Scenario ID | F2: Scenario Name | G2: Title | H2: Objective | I2: Lens | J2: Priority | K2: Severity | L2: Type | M2: Precondition | N2: Postcondition | O2: Test Data | P2: Steps | Q2: Expected Result | R2: Actual Result | S2: Traceability Requirement | T2: Technique | U2: Checkpoint Ref | V2: Assumption Ref | W2: Dependency Ref | X2: Test Type | Y2: Flow step | Z2: Impact | AA2: Why in regression | AB2: Regression suite | AC2: Status | AD2: Reason
A3: TC-SCN-R01-01 | B3: 8.2.13 | C3: Funding | D3: 2 | E3: SCN-R01 | F3: Self-enrolment journey end to end | G3: Resident self-enrols in an SSG funded course and receives a seat and the net fee invoice | H3: Self-enrolment journey end to end. Case: Resident self-enrols in an SSG funded course and receives a seat and the net fee invoice | I3: Happy Path | J3: Critical | K3: 1 | L3: positive | M3: 1. A test resident exists in SingPass and MyInfo (ASM-03) 2. An SSG funded run with free seats and no blacklist or prerequisite for the resident | N3: Data created or changed by the steps stays in the SIT test data | O3: Resident 01, SSG funded run with 5 seats | P3: 1. Sign in with SingPass as Resident 01 2. Open the registration form and check the MyInfo fields 3. Submit the application 4. Open the seat status and the fee overview 5. Open the invoice | Q3: 1. The checks pass in the order of the flow 2. The seat is confirmed 3. The fee overview equals the net fee on the invoice | R3: Not Executed | S3: Tender 8.2.13 (Funding, Sprint 2); Tender 8.2.5 (Enrolment, Sprint 1); Tender 8.2.14 (Enrolment, Sprint 2); Tender 8.5.1 (Enrolment, Sprint 2); Tender 9.1.9 (Funding, Sprint 2) | T3: EP | U3: CP-064 | V3: ASM-98 | W3: ASM-01, ASM-03 | X3: Integration | Y3: 4 Grant eligibility and fee | Z3: New | AA3: New test case written for the feature. The grant and fee are computed and shown at once, and the same amounts flow to the seat, the invoice and the funding claim | AB3: =IF(AC3="Reject","Not ready",IF(Z3="Possible",IF(K3=1,"Core","Extended"),IF(K3=1,"Smoke",IF(K3=2,"Core","Extended")))) -> Smoke | AC3: Draft | AD3: The steps follow the flow assumed in ASM-98. Each step is covered by its own clause
A4: TC-SCN-R01-02 | B4: 8.2.9 | C4: Funding | D4: 2 | E4: SCN-R01 | F4: Self-enrolment journey end to end | G4: Company sponsored learner self-enrols and the sponsor is invoiced | H4: Self-enrolment journey end to end. Case: Company sponsored learner self-enrols and the sponsor is invoiced | I4: Happy Path | J4: Critical | K4: 1 | L4: positive | M4: 1. A company with a valid UEN exists (ASM-32) 2. A run with free seats | N4: Data created or changed by the steps stays in the SIT test data | O4: Learner 02, company 03, SME declaration yes | P4: 1. Sign in as Learner 02 2. Register as company sponsored and give the company details 3. Make the SME declaration 4. Submit the application 5. Open the invoice | Q4: 1. The seat is confirmed 2. The invoice goes to company 03 with the SME funding applied 3. The learner has no payment due | R4: Not Executed | S4: Tender 8.2.9 (Funding, Sprint 1); Tender 8.2.16 (Funding, Sprint 2); Tender 6.3.4 (Funding, Sprint 2); Tender 9.1.9 (Funding, Sprint 2) | T4: EP | U4: CP-060 | V4: ASM-32, ASM-98 | W4: ASM-01 | X4: Integration | Y4: 4 Grant eligibility and fee | Z4: New | AA4: New test case written for the feature. The grant and fee are computed and shown at once, and the same amounts flow to the seat, the invoice and the funding claim | AB4: =IF(AC4="Reject","Not ready",IF(Z4="Possible",IF(K4=1,"Core","Extended"),IF(K4=1,"Smoke",IF(K4=2,"Core","Extended")))) -> Smoke | AC4: Draft | AD4: The steps follow the flow assumed in ASM-98. The sponsor path is read from 8.2.9 and 6.3.4
A5: TC-SCN-R01-03 | B5: 8.2.5 | C5: Enrolment | D5: 1 | E5: SCN-R01 | F5: Self-enrolment journey end to end | G5: Learner self-enrols when MyInfo is not available and types the personal fields | H5: Self-enrolment journey end to end. Case: Learner self-enrols when MyInfo is not available and types the personal fields | I5: Failure&Recovery | J5: High | K5: 3 | L5: exception | M5: 1. The MyInfo test endpoint is switched off (ASM-23) | N5: Data created or changed by the steps stays in the SIT test data | O5: Resident 04, MyInfo test endpoint off | P5: 1. Sign in with SingPass as Resident 04 2. Open the registration form 3. Type the personal fields 4. Submit the application | Q5: 1. The form opens with empty personal fields 2. The typed values are accepted and the flow continues | R5: Not Executed | S5: Tender 8.2.5 (Enrolment, Sprint 1); Tender 8.2.4 (Enrolment, Sprint 1) | T5: EP | U5: CP-056 | V5: ASM-23, ASM-98 | W5: ASM-01, ASM-03 | X5: Integration | Y5: 1 Login and MyInfo | Z5: New | AA5: New test case written for the feature. Self-enrol makes this sign in the only way in, so a failure here stops every later step | AB5: =IF(AC5="Reject","Not ready",IF(Z5="Possible",IF(K5=1,"Core","Extended"),IF(K5=1,"Smoke",IF(K5=2,"Core","Extended")))) -> Extended | AC5: Draft | AD5: ASM-23 assumes the form still opens when MyInfo is down. Continuing the flow is assumed in ASM-98
A6: TC-SCN-R02-01 | B6: 8.2.5 | C6: Enrolment | D6: 2 | E6: SCN-R02 | F6: Checks before a seat is given | G6: Fee band follows the MyInfo values of the current sign in | H6: Checks before a seat is given. Case: Fee band follows the MyInfo values of the current sign in | I6: Data Integrity | J6: Critical | K6: 1 | L6: positive | M6: 1. A test resident with different age in the account and in MyInfo (ASM-62) | N6: Data created or changed by the steps stays in the SIT test data | O6: Resident 03: account age 45, MyInfo age 35, age limit 40 | P6: 1. Sign in with SingPass as Resident 03 2. Open the registration form of an SSG funded course run 3. Read the age and the fee payable shown | Q6: 1. The age shown is 35 2. The fee payable and the grant are those of the band that includes age 35 | R6: Not Executed | S6: Tender 8.2.5 (Enrolment, Sprint 1); Tender 6.3.6 (Funding, Sprint 1,2,3) | T6: EP | U6: CP-056 | V6: ASM-62, ASM-98 | W6: ASM-01, ASM-03 | X6: Integration | Y6: 1 Login and MyInfo | Z6: New | AA6: New test case written for the feature. Self-enrol makes this sign in the only way in, so a failure here stops every later step | AB6: =IF(AC6="Reject","Not ready",IF(Z6="Possible",IF(K6=1,"Core","Extended"),IF(K6=1,"Smoke",IF(K6=2,"Core","Extended")))) -> Smoke | AC6: Draft | AD6: 8.2.5 requires MyInfo data in the form and 6.3.6 requires the fee by age. Which value wins is assumed in ASM-98
A7: TC-SCN-R02-02 | B7: 8.6.2 | C7: Enrolment | D7: 3 | E7: SCN-R02 | F7: Checks before a seat is given | G7: Synced blacklist record blocks the next self-enrolment | H7: Checks before a seat is given. Case: Synced blacklist record blocks the next self-enrolment | I7: Sequence | J7: High | K7: 1 | L7: negative | M7: 1. A blacklist sync test file exists in SIT (ASM-38) | N7: Data created or changed by the steps stays in the SIT test data | O7: Person: blacklisted person 03 (SSG, synced after the first registration) | P7: 1. Register Person 03 for run A and note the result 2. Run the SSG blacklist sync with a record for Person 03 3. Register Person 03 for run B 4. Observe the result | Q7: 1. The second registration is not enrolled 2. A reason for the blacklist is shown to the learner | R7: Not Executed | S7: Tender 8.6.2 (Enrolment, Sprint 3); Tender 8.2.14 (Enrolment, Sprint 2) | T7: StateTransition | U7: CP-106 | V7: ASM-38, ASM-98 | W7: ASM-01, ASM-03 | X7: Integration | Y7: 2 Blacklist check | Z7: New | AA7: New test case written for the feature. No staff review the application, so this check is the only gate against blacklisted learners and organisations | AB7: =IF(AC7="Reject","Not ready",IF(Z7="Possible",IF(K7=1,"Core","Extended"),IF(K7=1,"Smoke",IF(K7=2,"Core","Extended")))) -> Smoke | AC7: Draft | AD7: 8.6.2 requires the sync and 8.2.14 requires the check. Using the synced record at the next registration is assumed in ASM-98
A8: TC-SCN-R02-03 | B8: 8.6.2 | C8: Enrolment | D8: 3 | E8: SCN-R02 | F8: Checks before a seat is given | G8: Blacklisted sponsoring company is not enrolled | H8: Checks before a seat is given. Case: Blacklisted sponsoring company is not enrolled | I8: Business Risk | J8: Medium | K8: 2 | L8: negative | M8: 1. A blacklisted company record exists (ASM-38) | N8: Data created or changed by the steps stays in the SIT test data | O8: Company: blacklisted company 01; Learner 12 | P8: 1. Self-enrol Learner 12 as company sponsored with blacklisted company 01 2. Observe the result | Q8: 1. The System finds the company on the blacklist 2. The application is not enrolled | R8: Not Executed | S8: Tender 8.6.2 (Enrolment, Sprint 3); Tender 8.2.9 (Funding, Sprint 1) | T8: DecisionTable | U8: CP-106 | V8: ASM-38, ASM-98 | W8: ASM-01 | X8: Integration | Y8: 2 Blacklist check | Z8: New | AA8: New test case written for the feature. No staff review the application, so this check is the only gate against blacklisted learners and organisations | AB8: =IF(AC8="Reject","Not ready",IF(Z8="Possible",IF(K8=1,"Core","Extended"),IF(K8=1,"Smoke",IF(K8=2,"Core","Extended")))) -> Core | AC8: Draft | AD8: 8.6.2 names company sponsored applicants and 8.2.9 captures the company. Checking the company at self-enrolment is assumed in ASM-98
A9: TC-SCN-R02-04 | B9: 8.5.1 | C9: Enrolment | D9: 2 | E9: SCN-R02 | F9: Checks before a seat is given | G9: Seat is not confirmed when the prerequisite check fails | H9: Checks before a seat is given. Case: Seat is not confirmed when the prerequisite check fails | I9: Workflow | J9: Critical | K9: 1 | L9: negative | M9: 1. A course with a prerequisite is configured (ASM-35) | N9: Data created or changed by the steps stays in the SIT test data | O9: Learner 05 without the prerequisite, seats remaining: 5 | P9: 1. Self-enrol Learner 05 in the course run 2. Open the prerequisite check result 3. Open the status of the application and the seats left | Q9: 1. The prerequisite check fails 2. The application is not confirmed 3. The seats left stay 5 | R9: Not Executed | S9: Tender 8.5.1 (Enrolment, Sprint 2); Tender 8.2.20 (Enrolment, Sprint 2) | T9: DecisionTable | U9: CP-089 | V9: ASM-35, ASM-98 | W9: ASM-01 | X9: Integration | Y9: 3 Prerequisite and restriction check | Z9: New | AA9: New test case written for the feature. No staff enrol the learner, so these checks alone keep out learners who do not qualify or who apply twice | AB9: =IF(AC9="Reject","Not ready",IF(Z9="Possible",IF(K9=1,"Core","Extended"),IF(K9=1,"Smoke",IF(K9=2,"Core","Extended")))) -> Smoke | AC9: Draft | AD9: 8.2.20 requires the validation and 8.5.1 requires auto confirmation by capacity. The order of the two checks is assumed in ASM-98
A10: TC-SCN-R02-05 | B10: 8.4.1 | C10: Enrolment | D10: 2 | E10: SCN-R02 | F10: Checks before a seat is given | G10: Course with shortlisting is not auto confirmed | H10: Checks before a seat is given. Case: Course with shortlisting is not auto confirmed | I10: Workflow | J10: High | K10: 2 | L10: negative | M10: 1. Shortlisting criteria are configured (ASM-30) | N10: Data created or changed by the steps stays in the SIT test data | O10: Learner 19 without pre-assessment; course with shortlisting | P10: 1. Self-enrol Learner 19 in the course with shortlisting 2. Open the status of the application | Q10: 1. The application is pending shortlisting 2. The seat is not confirmed | R10: Not Executed | S10: Tender 8.4.1 (Enrolment, Sprint 2); Tender 8.5.1 (Enrolment, Sprint 2) | T10: DecisionTable | U10: CP-086 | V10: ASM-30, ASM-98 | W10: ASM-01 | X10: Integration | Y10: 3 Prerequisite and restriction check | Z10: New | AA10: New test case written for the feature. No staff enrol the learner, so these checks alone keep out learners who do not qualify or who apply twice | AB10: =IF(AC10="Reject","Not ready",IF(Z10="Possible",IF(K10=1,"Core","Extended"),IF(K10=1,"Smoke",IF(K10=2,"Core","Extended")))) -> Core | AC10: Draft | AD10: 8.4.1 sets shortlisting and 8.5.1 confirms by capacity. Shortlisting taking priority is assumed in ASM-98
A11: TC-SCN-R03-01 | B11: 8.5.1 | C11: Enrolment | D11: 2 | E11: SCN-R03 | F11: Seat confirmation under self-enrolment | G11: The last seat goes to one of two simultaneous applications | H11: Seat confirmation under self-enrolment. Case: The last seat goes to one of two simultaneous applications | I11: Business Risk | J11: Critical | K11: 1 | L11: negative | M11: 1. A course run with a maximum of 2 learners and 1 enrolled (ASM-13) | N11: Data created or changed by the steps stays in the SIT test data | O11: Run with maximum 2, 1 seat left; Learner 06 and Learner 07 | P11: 1. Open the form for Learner 06 and Learner 07 2. Submit both at the same time 3. Open the enrolment list and the waitlist | Q11: 1. One learner is confirmed first by application time 2. The other learner is on the waitlist 3. The enrolment list holds 2 learners | R11: Not Executed | S11: Tender 8.5.1 (Enrolment, Sprint 2); Tender 8.1.10 (Enrolment, Sprint 1) | T11: StateTransition | U11: CP-089 | V11: ASM-13, ASM-98 | W11: ASM-01 | X11: Integration | Y11: 5 Seat confirm or waitlist | Z11: New | AA11: New test case written for the feature. Many learners register at the same time, so seat confirmation and the waitlist run more often and without staff help | AB11: =IF(AC11="Reject","Not ready",IF(Z11="Possible",IF(K11=1,"Core","Extended"),IF(K11=1,"Smoke",IF(K11=2,"Core","Extended")))) -> Smoke | AC11: Draft | AD11: 8.5.1 requires first come first serve and 8.1.10 sets the maximum. Equal submit times are assumed in ASM-98
A12: TC-SCN-R03-02 | B12: 8.5.3 | C12: Enrolment | D12: 2 | E12: SCN-R03 | F12: Seat confirmation under self-enrolment | G12: Seat is released when the grant check fails | H12: Seat confirmation under self-enrolment. Case: Seat is released when the grant check fails | I12: Failure&Recovery | J12: High | K12: 2 | L12: exception | M12: 1. A full run with Learner 14 waitlisted (ASM-17) | N12: Data created or changed by the steps stays in the SIT test data | O12: Learner 13 (grant check fails); Learner 14 waitlisted | P12: 1. Self-enrol Learner 13 so that the grant check fails 2. Cancel the application at the fee step 3. Open the seats and the waitlist | Q12: 1. The seat of Learner 13 is released 2. Learner 14 is notified of the free seat | R12: Not Executed | S12: Tender 8.5.3 (Enrolment, Sprint 2); Tender 8.2.13 (Funding, Sprint 2) | T12: StateTransition | U12: CP-091 | V12: ASM-17, ASM-98 | W12: ASM-01 | X12: Integration | Y12: 5 Seat confirm or waitlist | Z12: New | AA12: New test case written for the feature. Many learners register at the same time, so seat confirmation and the waitlist run more often and without staff help | AB12: =IF(AC12="Reject","Not ready",IF(Z12="Possible",IF(K12=1,"Core","Extended"),IF(K12=1,"Smoke",IF(K12=2,"Core","Extended")))) -> Core | AC12: Draft | AD12: 8.5.3 requires the waitlist and notification and 8.2.13 requires the grant check. Releasing the seat after a failed check is assumed in ASM-98
A13: TC-SCN-R03-03 | B13: 8.5.16 | C13: Enrolment | D13: 2 | E13: SCN-R03 | F13: Seat confirmation under self-enrolment | G13: Enrolment is sent to TPGateway only after the seat is confirmed | H13: Seat confirmation under self-enrolment. Case: Enrolment is sent to TPGateway only after the seat is confirmed | I13: Integration | J13: Critical | K13: 1 | L13: negative | M13: 1. TPGateway is reachable through a test endpoint (ASM-03) | N13: Data created or changed by the steps stays in the SIT test data | O13: Learner 10 on the waitlist; TPGateway test endpoint | P13: 1. Self-enrol Learner 10 on a full run 2. Open the TPGateway log for Learner 10 3. Free a seat and open the log again | Q13: 1. No record is sent while the learner is waitlisted 2. One record is sent after the promotion | R13: Not Executed | S13: Tender 8.5.16 (Enrolment, Sprint 2); Tender 8.5.3 (Enrolment, Sprint 2) | T13: StateTransition | U13: CP-104 | V13: ASM-98 | W13: ASM-01, ASM-03 | X13: Integration | Y13: 5 Seat confirm or waitlist | Z13: New | AA13: New test case written for the feature. Many learners register at the same time, so seat confirmation and the waitlist run more often and without staff help | AB13: =IF(AC13="Reject","Not ready",IF(Z13="Possible",IF(K13=1,"Core","Extended"),IF(K13=1,"Smoke",IF(K13=2,"Core","Extended")))) -> Smoke | AC13: Draft | AD13: 8.5.16 requires the enrolment interface and 8.5.3 requires the waitlist. Sending only on confirmation is assumed in ASM-98
A14: TC-SCN-R03-04 | B14: 8.1.10 | C14: Enrolment | D14: 2 | E14: SCN-R03 | F14: Seat confirmation under self-enrolment | G14: Seats count down by one for each self-enrolment and stop at the maximum | H14: Seat confirmation under self-enrolment. Case: Seats count down by one for each self-enrolment and stop at the maximum | I14: Boundary | J14: Critical | K14: 1 | L14: boundary | M14: 1. A course run with a maximum of 2 learners (ASM-13) | N14: Data created or changed by the steps stays in the SIT test data | O14: Run with maximum 2; Learner 26, 27, 28 | P14: 1. Self-enrol Learner 26 2. Self-enrol Learner 27 3. Self-enrol Learner 28 4. Open the enrolment list and the waitlist | Q14: 1. Learner 26 and Learner 27 are confirmed 2. Learner 28 is on the waitlist | R14: Not Executed | S14: Tender 8.1.10 (Enrolment, Sprint 1); Tender 8.5.1 (Enrolment, Sprint 2) | T14: BVA | U14: CP-047 | V14: ASM-13, ASM-98 | W14: ASM-01 | X14: Integration | Y14: 5 Seat confirm or waitlist | Z14: New | AA14: New test case written for the feature. Many learners register at the same time, so seat confirmation and the waitlist run more often and without staff help | AB14: =IF(AC14="Reject","Not ready",IF(Z14="Possible",IF(K14=1,"Core","Extended"),IF(K14=1,"Smoke",IF(K14=2,"Core","Extended")))) -> Smoke | AC14: Draft | AD14: 8.1.10 sets the maximum and 8.5.1 confirms by capacity. The sequence is the boundary of the maximum
... A28: TC-SCN-R08-02 | B28: 8.1.14 | C28: Enrolment | D28: 3 | E28: SCN-R08 | F28: Draft, notification and message content | G28: Course date format is the same in the message and the invoice | H28: Draft, notification and message content. Case: Course date format is the same in the message and the invoice | I28: UI | J28: Low | K28: 4 | L28: positive | M28: 1. A confirmed enrolment with an invoice (ASM-01) | N28: Data created or changed by the steps stays in the SIT test data | O28: Learner 25, one confirmed enrolment | P28: 1. Open the outcome message of Learner 25 2. Open the invoice 3. Compare the course dates | Q28: 1. The course date has the same format in both documents | R28: Not Executed | S28: Tender 8.1.14 (Enrolment, Sprint 3); Tender 9.1.9 (Funding, Sprint 2) | T28: EP | U28: CP-051 | V28: ASM-98 | W28: ASM-01 | X28: Integration | Y28: 5 Seat confirm or waitlist | Z28: New | AA28: New test case written for the feature. Many learners register at the same time, so seat confirmation and the waitlist run more often and without staff help | AB28: =IF(AC28="Reject","Not ready",IF(Z28="Possible",IF(K28=1,"Core","Extended"),IF(K28=1,"Smoke",IF(K28=2,"Core","Extended")))) -> Extended | AC28: Draft | AD28: 8.1.14 requires the outcome notification. A common date format is assumed in ASM-98
A30: ="Table 2. Existing test cases to retest because the feature affects them or may affect them: "&COUNTA(A32:A256)&" test cases (Direct "&COUNTIF(Z32:Z256,"Direct")&", Possible "&COUNTIF(Z32:Z256,"Possible")&")" -> Table 2. Existing test cases to retest because the feature affects them or may affect them: 225 test cases (Direct 167, Possible 58)
A31: TC ID | B31: Requirement (Tender clause) | C31: Module | D31: Sprint | E31: Scenario ID | F31: Scenario Name | G31: Title | H31: Objective | I31: Lens | J31: Priority | K31: Severity | L31: Type | M31: Precondition | N31: Postcondition | O31: Test Data | P31: Steps | Q31: Expected Result | R31: Actual Result | S31: Traceability Requirement | T31: Technique | U31: Checkpoint Ref | V31: Assumption Ref | W31: Dependency Ref | X31: Test Type | Y31: Flow step | Z31: Impact | AA31: Why in regression | AB31: Regression suite | AC31: Status | AD31: Reason
A32: TC-SCN-001-01 | B32: 2.2 | C32: Enrolment | D32: 1 | E32: SCN-001 | F32: Resident signs in with SingPass | G32: Resident signs in through SingPass | H32: A Singapore Resident authenticates through SingPass and is signed in. Case: Resident signs in through SingPass | I32: Happy Path | J32: Critical | K32: 1 | L32: positive | M32: 1. A test resident identity exists in the SingPass test service (ASM-01) | N32: Data created or changed by the steps stays in the SIT test data | O32: Test identity: test resident 01 | P32: 1. Open the Learner login URL 2. Select the SingPass option 3. Authenticate with a test resident identity at SingPass 4. Observe the page after authentication | Q32: 1. The System sends the resident to SingPass for authentication 2. After successful authentication the System signs the resident in 3. The learner landing page opens | R32: Not Executed | S32: Tender 2.2 (Enrolment, Sprint 1) | T32: EP | U32: CP-001 | V32: N/A | W32: ASM-01, ASM-03 | X32: Integration | Y32: 1 Login and MyInfo | Z32: Direct | AA32: Self-enrol makes this sign in the only way in, so a failure here stops every later step | AB32: =IF(AC32="Reject","Not ready",IF(Z32="Possible",IF(K32=1,"Core","Extended"),IF(K32=1,"Smoke",IF(K32=2,"Core","Extended")))) -> Smoke | AC32: Approve | AD32: 2.2 states that SingPass integration authenticates Singapore Residents for login
A33: TC-SCN-001-02 | B33: 2.2 | C33: Enrolment | D33: 1 | E33: SCN-001 | F33: Resident signs in with SingPass | G33: SingPass authentication fails | H33: A Singapore Resident authenticates through SingPass and is signed in. Case: SingPass authentication fails | I33: Failure&Recovery | J33: Critical | K33: 2 | L33: negative | M33: 1. A test resident identity exists in the SingPass test service (ASM-01) | N33: Data created or changed by the steps stays in the SIT test data | O33: Test identity: test resident 01 | P33: 1. Open the Learner login URL 2. Select the SingPass option 3. Cancel the authentication at SingPass 4. Observe the page that opens | Q33: 1. The resident is not signed in 2. The login page is shown again | R33: Not Executed | S33: Tender 2.2 (Enrolment, Sprint 1) | T33: EP | U33: CP-001 | V33: ASM-10 | W33: ASM-01, ASM-03 | X33: Integration | Y33: 1 Login and MyInfo | Z33: Direct | AA33: Self-enrol makes this sign in the only way in, so a failure here stops every later step | AB33: =IF(AC33="Reject","Not ready",IF(Z33="Possible",IF(K33=1,"Core","Extended"),IF(K33=1,"Smoke",IF(K33=2,"Core","Extended")))) -> Core | AC33: Draft | AD33: 2.2 requires authentication through SingPass. A failed authentication must not sign the user in
A34: TC-SCN-055-01 | B34: 8.2.4 | C34: Enrolment | D34: 1 | E34: SCN-055 | F34: Login with existing account | G34: Existing account fills the registration form | H34: A registrant with an account logs in to register. Case: Existing account fills the registration form | I34: Happy Path | J34: Critical | K34: 2 | L34: positive | M34: 1. The registrant has an account with name and contact data (ASM-01) | N34: Data created or changed by the steps stays in the SIT test data | O34: Account: learner.test01 | P34: 1. Open a course run 2. Select Register 3. Log in with an existing account 4. Observe the registration form | Q34: 1. The registrant is able to log in with the existing account 2. The registration form shows the information from the account | R34: Not Executed | S34: Tender 8.2.4 (Enrolment, Sprint 1) | T34: EP | U34: CP-055 | V34: N/A | W34: ASM-01 | X34: Functional | Y34: 1 Login and MyInfo | Z34: Direct | AA34: Self-enrol makes this sign in the only way in, so a failure here stops every later step | AB34: =IF(AC34="Reject","Not ready",IF(Z34="Possible",IF(K34=1,"Core","Extended"),IF(K34=1,"Smoke",IF(K34=2,"Core","Extended")))) -> Core | AC34: Approve | AD34: 8.2.4 requires login with an existing account and population of information
A35: TC-SCN-056-01 | B35: 8.2.5 | C35: Enrolment | D35: 1 | E35: SCN-056 | F35: MyInfo data in the form | G35: MyInfo verified data fills the form | H35: A learner with MyInfo verified data starts a registration. Case: MyInfo verified data fills the form | I35: Data | J35: Critical | K35: 2 | L35: positive | M35: 1. A test resident has MyInfo test data and an account (ASM-01) | N35: No data is changed by this test | O35: Test resident 01 | P35: 1. Sign in with SingPass as a test resident 2. Open the registration form of a course run 3. Compare the personal fields with the MyInfo test data | Q35: 1. The personal fields are filled from the account 2. The filled values equal the MyInfo test data | R35: Not Executed | S35: Tender 8.2.5 (Enrolment, Sprint 1) | T35: EP | U35: CP-056 | V35: ASM-20 | W35: ASM-01, ASM-03 | X35: Integration | Y35: 1 Login and MyInfo | Z35: Direct | AA35: Self-enrol makes this sign in the only way in, so a failure here stops every later step | AB35: =IF(AC35="Reject","Not ready",IF(Z35="Possible",IF(K35=1,"Core","Extended"),IF(K35=1,"Smoke",IF(K35=2,"Core","Extended")))) -> Core | AC35: Draft | AD35: 8.2.5 requires the data verified by MyInfo to populate the form. Which fields is not stated
A36: TC-SCN-056-02 | B36: 8.2.5 | C36: Enrolment | D36: 1 | E36: SCN-056 | F36: MyInfo data in the form | G36: MyInfo is unavailable during registration | H36: A learner with MyInfo verified data starts a registration. Case: MyInfo is unavailable during registration | I36: Failure&Recovery | J36: High | K36: 3 | L36: exception | M36: 1. MyInfo test endpoint is off (ASM-01) | N36: No data is changed by this test | O36: Test resident 01 | P36: 1. Switch the MyInfo test endpoint off 2. Sign in as a test resident 3. Open the registration form | Q36: 1. The registration form still opens 2. The personal fields are not filled from MyInfo and can be entered by the learner | R36: Not Executed | S36: Tender 8.2.5 (Enrolment, Sprint 1) | T36: EP | U36: CP-056 | V36: ASM-23 | W36: ASM-01, ASM-03 | X36: Integration | Y36: 1 Login and MyInfo | Z36: Direct | AA36: Self-enrol makes this sign in the only way in, so a failure here stops every later step | AB36: =IF(AC36="Reject","Not ready",IF(Z36="Possible",IF(K36=1,"Core","Extended"),IF(K36=1,"Smoke",IF(K36=2,"Core","Extended")))) -> Extended | AC36: Draft | AD36: 8.2.15 requires structured fields. A MyInfo outage should not block registration. The Tender does not say so
A37: TC-SCN-155-01 | B37: 18.2.1 | C37: Enrolment | D37: 1 | E37: SCN-155 | F37: MyInfo integration | G37: System retrieves data from MyInfo | H37: The System reads data from MyInfo. Case: System retrieves data from MyInfo | I37: Data | J37: Critical | K37: 2 | L37: positive | M37: 1. A MyInfo test identity exists (ASM-01) | N37: No data is changed by this test | O37: Test resident 01 | P37: 1. Sign in with SingPass as a test resident 2. Authorise the MyInfo data retrieval 3. Observe the data shown | Q37: 1. The System retrieves the learner data from MyInfo 2. The retrieved data is shown in the portal | R37: Not Executed | S37: Tender 18.2.1 (Enrolment, Sprint 1) | T37: EP | U37: CP-155 | V37: N/A | W37: ASM-01, ASM-03 | X37: Integration | Y37: 1 Login and MyInfo | Z37: Direct | AA37: Self-enrol makes this sign in the only way in, so a failure here stops every later step | AB37: =IF(AC37="Reject","Not ready",IF(Z37="Possible",IF(K37=1,"Core","Extended"),IF(K37=1,"Smoke",IF(K37=2,"Core","Extended")))) -> Core | AC37: Draft | AD37: 18.2.1 requires integration with MyInfo
A38: TC-SCN-156-01 | B38: 18.2.2 | C38: Enrolment | D38: 1 | E38: SCN-156 | F38: SingPass integration | G38: SingPass session ends with the System session | H38: The System authenticates through SingPass. Case: SingPass session ends with the System session | I38: Security | J38: Critical | K38: 2 | L38: positive | M38: 1. A SingPass test identity exists (ASM-01) | N38: No data is changed by this test | O38: Test resident 01 | P38: 1. Sign in with SingPass 2. Sign out of the System 3. Press the browser back button 4. Observe the page | Q38: 1. The System session ends after sign out 2. The back button does not show a signed in page | R38: Not Executed | S38: Tender 18.2.2 (Enrolment, Sprint 1) | T38: EP | U38: CP-156 | V38: N/A | W38: ASM-01, ASM-03 | X38: Integration | Y38: 1 Login and MyInfo | Z38: Direct | AA38: Self-enrol makes this sign in the only way in, so a failure here stops every later step | AB38: =IF(AC38="Reject","Not ready",IF(Z38="Possible",IF(K38=1,"Core","Extended"),IF(K38=1,"Smoke",IF(K38=2,"Core","Extended")))) -> Core | AC38: Draft | AD38: 18.2.2 requires SingPass integration. Session end is part of safe authentication but is not stated
A39: TC-SCN-065-01 | B39: 8.2.14 | C39: Enrolment | D39: 2 | E39: SCN-065 | F39: Blacklist check at registration | G39: Applicant on the SSG blacklist is flagged | H39: An applicant is checked against both blacklists. Case: Applicant on the SSG blacklist is flagged | I39: Business Risk | J39: Critical | K39: 1 | L39: negative | M39: 1. A blacklist record exists (ASM-01) | N39: Data created or changed by the steps stays in the SIT test data | O39: Person: blacklisted person 01 (SSG) | P39: 1. Add a test person to the SSG blacklist record 2. Register the person for a course run 3. Observe the result | Q39: 1. The System finds the applicant on the SSG blacklist 2. The applicant is not enrolled | R39: Not Executed | S39: Tender 8.2.14 (Enrolment, Sprint 2) | T39: DecisionTable | U39: CP-065 | V39: ASM-28 | W39: ASM-01 | X39: Functional | Y39: 2 Blacklist check | Z39: Direct | AA39: No staff review the application, so this check is the only gate against blacklisted learners and organisations | AB39: =IF(AC39="Reject","Not ready",IF(Z39="Possible",IF(K39=1,"Core","Extended"),IF(K39=1,"Smoke",IF(K39=2,"Core","Extended")))) -> Smoke | AC39: Draft | AD39: 8.2.14 requires the check against the SSG blacklist
A40: TC-SCN-065-02 | B40: 8.2.14 | C40: Enrolment | D40: 2 | E40: SCN-065 | F40: Blacklist check at registration | G40: Applicant on the School blacklist is flagged | H40: An applicant is checked against both blacklists. Case: Applicant on the School blacklist is flagged | I40: Business Risk | J40: Critical | K40: 1 | L40: negative | M40: 1. A blacklist record exists (ASM-01) | N40: Data created or changed by the steps stays in the SIT test data | O40: Person: blacklisted person 02 (School) | P40: 1. Add a test person to the School blacklist 2. Register the person 3. Observe the result | Q40: 1. The System finds the applicant on the School blacklist 2. The applicant is not enrolled | R40: Not Executed | S40: Tender 8.2.14 (Enrolment, Sprint 2) | T40: DecisionTable | U40: CP-065 | V40: ASM-28 | W40: ASM-01 | X40: Functional | Y40: 2 Blacklist check | Z40: Direct | AA40: No staff review the application, so this check is the only gate against blacklisted learners and organisations | AB40: =IF(AC40="Reject","Not ready",IF(Z40="Possible",IF(K40=1,"Core","Extended"),IF(K40=1,"Smoke",IF(K40=2,"Core","Extended")))) -> Smoke | AC40: Draft | AD40: 8.2.14 requires the check against the School blacklist
A41: TC-SCN-065-03 | B41: 8.2.14 | C41: Enrolment | D41: 2 | E41: SCN-065 | F41: Blacklist check at registration | G41: Applicant not on any list gets a fee overview | H41: An applicant is checked against both blacklists. Case: Applicant not on any list gets a fee overview | I41: Happy Path | J41: High | K41: 2 | L41: positive | M41: 1. A course run with a fee exists (ASM-01) | N41: Data created or changed by the steps stays in the SIT test data | O41: Person: clean person 01 | P41: 1. Register a person who is on no blacklist 2. Open the fee overview | Q41: 1. The System computes the overview of the course fee for the registration | R41: Not Executed | S41: Tender 8.2.14 (Enrolment, Sprint 2) | T41: EP | U41: CP-065 | V41: N/A | W41: ASM-01 | X41: Functional | Y41: 2 Blacklist check | Z41: Direct | AA41: No staff review the application, so this check is the only gate against blacklisted learners and organisations | AB41: =IF(AC41="Reject","Not ready",IF(Z41="Possible",IF(K41=1,"Core","Extended"),IF(K41=1,"Smoke",IF(K41=2,"Core","Extended")))) -> Core | AC41: Approve | AD41: 8.2.14 requires the fee overview computation
A42: TC-SCN-105-01 | B42: 8.6.1 | C42: Enrolment | D42: 3 | E42: SCN-105 | F42: Blacklist and screening | G42: Individual on the blacklist is screened at registration | H42: Registrations are screened against the blacklists and suspensions. Case: Individual on the blacklist is screened at registration | I42: Business Risk | J42: High | K42: 1 | L42: negative | M42: 1. A blacklisted person exists (ASM-01) | N42: Data created or changed by the steps stays in the SIT test data | O42: Person: blacklisted person 01 | P42: 1. Blacklist a person 2. Register the person 3. Observe the result | Q42: 1. The registration is screened and the person is flagged as blacklisted | R42: Not Executed | S42: Tender 8.6.1 (Enrolment, Sprint 3) | T42: DecisionTable | U42: CP-105 | V42: ASM-38 | W42: ASM-01 | X42: Functional | Y42: 2 Blacklist check | Z42: Direct | AA42: No staff review the application, so this check is the only gate against blacklisted learners and organisations | AB42: =IF(AC42="Reject","Not ready",IF(Z42="Possible",IF(K42=1,"Core","Extended"),IF(K42=1,"Smoke",IF(K42=2,"Core","Extended")))) -> Smoke | AC42: Draft | AD42: 8.6.1 item 1 Blacklist individual
A43: TC-SCN-105-02 | B43: 8.6.1 | C43: Enrolment | D43: 3 | E43: SCN-105 | F43: Blacklist and screening | G43: Organisation on the blacklist is screened | H43: Registrations are screened against the blacklists and suspensions. Case: Organisation on the blacklist is screened | I43: Business Risk | J43: High | K43: 1 | L43: negative | M43: 1. A blacklisted organisation exists (ASM-01) | N43: Data created or changed by the steps stays in the SIT test data | O43: Organisation: Blacklisted Company 01 | P43: 1. Blacklist an organisation 2. Register a learner sponsored by it 3. Observe the result | Q43: 1. The registration is screened and flagged | R43: Not Executed | S43: Tender 8.6.1 (Enrolment, Sprint 3) | T43: DecisionTable | U43: CP-105 | V43: ASM-38 | W43: ASM-01 | X43: Functional | Y43: 2 Blacklist check | Z43: Direct | AA43: No staff review the application, so this check is the only gate against blacklisted learners and organisations | AB43: =IF(AC43="Reject","Not ready",IF(Z43="Possible",IF(K43=1,"Core","Extended"),IF(K43=1,"Smoke",IF(K43=2,"Core","Extended")))) -> Smoke | AC43: Draft | AD43: 8.6.1 item 2 Blacklist organisations
... A256: TC-SCN-135-03 | B256: 10.2.12 | C256: Assessment | D256: 3 | E256: SCN-135 | F256: Release of marks | G256: Marks are shown when release is on | H256: The release setting controls what the learner sees. Case: Marks are shown when release is on | I256: Happy Path | J256: Medium | K256: 2 | L256: positive | M256: 1. A course with marks and release on (ASM-01) | N256: Data created or changed by the steps stays in the SIT test data | O256: Learner: learner.test01 | P256: 1. Set the release of marks to on 2. Sign in as the learner 3. Open the result | Q256: 1. The learner sees the marks | R256: Not Executed | S256: Tender 10.2.12 (Assessment, Sprint 3) | T256: DecisionTable | U256: CP-135 | V256: N/A | W256: ASM-01 | X256: Functional | Y256: 7 Outcome based funding | Z256: Possible | AA256: The status Completed without released marks is read by the funding decision of 6.4.4 | AB256: =IF(AC256="Reject","Not ready",IF(Z256="Possible",IF(K256=1,"Core","Extended"),IF(K256=1,"Smoke",IF(K256=2,"Core","Extended")))) -> Extended | AC256: Approve | AD256: 10.2.12 allows marks to be released

Sheet Regression Defects
A1: ="Table 1. New defects caused by the feature: "&COUNTA(A3:A22)&" potential defects" -> Table 1. New defects caused by the feature: 20 potential defects
A2: Defect ID | B2: Module | C2: Sprint | D2: Tender clause | E2: Flow step | F2: Related TC IDs | G2: Other clauses | H2: Summary | I2: Severity | J2: Impact level | K2: Urgency | L2: Priority | M2: Status | N2: Suggested regression suite | O2: Environment | P2: Preconditions | Q2: Steps to Reproduce | R2: Expected Result | S2: Potential Actual Result (hypothetical) | T2: Business impact | U2: Triage rationale | V2: Evidence
A3: DEF-071 | B3: Enrolment | C3: 2 | D3: 8.2.5 | E3: 1 Login and MyInfo | F3: TC-SCN-R02-01 | G3: 6.3.6 | H3: [Registration] Fee band and grant use the age saved in the account instead of the MyInfo age of this sign in | I3: 1 | J3: =IF(I3<=2,"High","Low") -> High | K3: High | L3: =IF(J3="High",IF(K3="High","Critical","High"),IF(K3="High","Medium","Low")) -> Critical | M3: Potential | N3: =IF(I3=1,"Smoke",IF(I3=2,"Regression Core","Regression Extended")) -> Smoke | O3: SIT (assumed, ASM-01) | P3: 1. A test resident whose account holds an old date of birth (age 45) 2. MyInfo test data with the current date of birth (age 35) 3. An age limit of 40 is configured (ASM-62) | Q3: 1. Sign in with SingPass as the test resident 2. Open the registration form of an SSG funded course run 3. Compare the age and nationality fields with the MyInfo test data 4. Open the fee payable and the grant shown | R3: 1. The age and nationality equal the MyInfo test data 2. The fee and the grant are those of the band of age 35 | S3: The form keeps the date of birth saved in the account and the fee and grant of the band of age 45 are shown | T3: The learner is charged and funded under the wrong band and no staff member checks it | U3: Wrong money and funding for every learner whose data changed. Severity 1: Blocker, or money, funding or compliance break. Urgency High by ASM-92. | V3: Tender 8.2.5: "The System shall populate applicant’s personal information (verified by SingPass MyInfo) from user account to registration form." Tender 6.3.6: "The System shall have the capability to generate fees payable with automatic calculation based on criteria including but not limited to: // 1) Nationality/citizenship of candidates; // 2) Age/Date of Birth;"
A4: DEF-072 | B4: Enrolment | C4: 3 | D4: 8.6.2 | E4: 2 Blacklist check | F4: TC-SCN-R02-02 | G4: 8.2.14 | H4: [Registration] Applicant added to the SSG blacklist by the sync is still enrolled on the next self-enrolment | I4: 1 | J4: =IF(I4<=2,"High","Low") -> High | K4: High | L4: =IF(J4="High",IF(K4="High","Critical","High"),IF(K4="High","Medium","Low")) -> Critical | M4: Potential | N4: =IF(I4=1,"Smoke",IF(I4=2,"Regression Core","Regression Extended")) -> Smoke | O4: SIT (assumed, ASM-01) | P4: 1. A test person who is not on the blacklist 2. A synced SSG blacklist record for the same person is loaded after the person registered once | Q4: 1. Register the person for a course run and note the result 2. Load the SSG blacklist record of the person through the sync 3. Register the person for another course run 4. Observe the result | R4: 1. The System finds the person on the synced SSG blacklist 2. The second registration is not enrolled | S4: The second registration is enrolled because the check reads the list kept from the first registration | T4: A barred person is enrolled and funded, an audit finding | U4: The check and the sync are delivered in different Sprints, so a stale list is likely. Severity 1: Blocker, or money, funding or compliance break. Urgency High by ASM-92. | V4: Tender 8.6.2: "The System shall have the capability to sync to SSG given’s blacklist records, as well as the finance payment records for potential enrolled company sponsored applicants if they are blacklisted for CET courses (due to earlier non-payments)." Tender 8.2.14: "The System shall check if applicants are in the SSG and Schools’ blacklisting and compute the overview of course fee for registration."
A5: DEF-073 | B5: Enrolment | C5: 2 | D5: 8.5.1 | E5: 3 Prerequisite and restriction check | F5: TC-SCN-R02-04 | G5: 8.2.20 | H5: [Enrolment] Seat is confirmed for an applicant who fails the prerequisite check | I5: 1 | J5: =IF(I5<=2,"High","Low") -> High | K5: High | L5: =IF(J5="High",IF(K5="High","Critical","High"),IF(K5="High","Medium","Low")) -> Critical | M5: Potential | N5: =IF(I5=1,"Smoke",IF(I5=2,"Regression Core","Regression Extended")) -> Smoke | O5: SIT (assumed, ASM-01) | P5: 1. A course with a prerequisite course 2. A test learner who has not completed the prerequisite 3. Seats remain on the course run | Q5: 1. Self-enrol the learner in the course run 2. Observe the prerequisite check result 3. Observe the status of the application | R5: 1. The prerequisite check fails 2. The seat is not confirmed and the application is not enrolled | S5: The application is confirmed because seat confirmation does not wait for the prerequisite result | T5: The class holds an unqualified learner and the results are not valid | U5: Seat confirmation can run ahead of the check when nobody reviews the application. Severity 1: Blocker, or money, funding or compliance break. Urgency High by ASM-92. | V5: Tender 8.5.1: "The System shall have the capability based on capacity-based auto confirmation and on first-come-first-serve basis." Tender 8.2.20: "The System shall validate the prerequisites and enrolment criteria of courses and programmes during application registration."
A6: DEF-074 | B6: Enrolment | C6: 2 | D6: 8.5.1 | E6: 5 Seat confirm or waitlist | F6: TC-SCN-R03-01 | G6: 8.1.10 | H6: [Enrolment] The last seat is confirmed for two learners who submit at the same time | I6: 1 | J6: =IF(I6<=2,"High","Low") -> High | K6: High | L6: =IF(J6="High",IF(K6="High","Critical","High"),IF(K6="High","Medium","Low")) -> Critical | M6: Potential | N6: =IF(I6=1,"Smoke",IF(I6=2,"Regression Core","Regression Extended")) -> Smoke | O6: SIT (assumed, ASM-01) | P6: 1. A course run with a maximum of 2 learners and 1 seat left 2. Two test learners ready to submit | Q6: 1. Open the registration form for both learners 2. Submit both applications at the same time 3. Open the enrolment list and the waitlist | R6: 1. One learner is confirmed 2. The other learner goes to the waitlist 3. The enrolment list holds 2 learners | S6: Both learners are confirmed and the enrolment list holds 3 learners | T6: The run is over capacity, and seats and funding are wrong | U6: Many learners register without staff, so the same moment is likely. Severity 1: Blocker, or money, funding or compliance break. Urgency High by ASM-92. | V6: Tender 8.5.1: "The System shall have the capability based on capacity-based auto confirmation and on first-come-first-serve basis." Tender 8.1.10: "The System shall have the capability to configure and set up a minimum and maximum number of Learners for each course or assessment."
A7: DEF-075 | B7: Enrolment | C7: 2 | D7: 8.5.3 | E7: 5 Seat confirm or waitlist | F7: TC-SCN-R04-01 | G7: 6.4.3 | H7: [Enrolment] Waitlisted learner is promoted to a seat but is charged the full fee without the grant | I7: 1 | J7: =IF(I7<=2,"High","Low") -> High | K7: High | L7: =IF(J7="High",IF(K7="High","Critical","High"),IF(K7="High","Medium","Low")) -> Critical | M7: Potential | N7: =IF(I7=1,"Smoke",IF(I7=2,"Regression Core","Regression Extended")) -> Smoke | O7: SIT (assumed, ASM-01) | P7: 1. A full SSG funded course run with a waitlisted eligible learner 2. A seat is freed | Q7: 1. Free a seat on the run 2. Observe the promotion of the waitlisted learner 3. Open the fee payable and the grant of the learner | R7: 1. The learner is promoted 2. The grant eligibility is checked again at promotion 3. The net fee includes the grant | S7: The learner is promoted and the fee shows the full course fee with no grant | T7: The learner is overcharged and the claim to SSG is missing | U7: The grant check ran at application and is not repeated at promotion. Severity 1: Blocker, or money, funding or compliance break. Urgency High by ASM-92. | V7: Tender 8.5.3: "The System shall allow the capability to automatically put Learners on a waitlist if the class is full and notify candidates when seats are available and channel them to another course." Tender 6.4.3: "The System shall allow automation for application of grant, subsidies, SFC, SFC (mid-career) top up, ETSS, credits, discounts, PSEA, Alumni Course Credit (ACC), and Additional Funding Support (AFS applicable for SkillsFuture Career Transition Programme) for fee calculation."
A8: DEF-076 | B8: Funding | C8: 3 | D8: 6.4.3 | E8: 6 Net fee and invoice | F8: TC-SCN-R05-01 | G8: 8.2.18, 12.2.3 | H8: [Funding] Net fee becomes negative when the SSG grant, SFC and Alumni Course Credit together exceed the course fee | I8: 1 | J8: =IF(I8<=2,"High","Low") -> High | K8: High | L8: =IF(J8="High",IF(K8="High","Critical","High"),IF(K8="High","Medium","Low")) -> Critical | M8: Potential | N8: =IF(I8=1,"Smoke",IF(I8=2,"Regression Core","Regression Extended")) -> Smoke | O8: SIT (assumed, ASM-01) | P8: 1. A course with a full fee of 1000 2. An eligible learner with an SSG grant of 700, an SFC of 400 and an alumni credit of 500 (cap 50 percent) | Q8: 1. Self-enrol the learner and apply the SSG grant, the SFC and the alumni credit 2. Open the net fee payable 3. Open the invoice | R8: 1. The alumni credit is limited to 500 2. The net fee is not below 0 3. The invoice shows no negative total | S8: The net fee shows minus 600 and the invoice total is negative | T8: The School owes money to the learner and the finance records are wrong | U8: Three automatic deductions are applied with no staff check of the total. Severity 1: Blocker, or money, funding or compliance break. Urgency High by ASM-92. | V8: Tender 6.4.3: "The System shall allow automation for application of grant, subsidies, SFC, SFC (mid-career) top up, ETSS, credits, discounts, PSEA, Alumni Course Credit (ACC), and Additional Funding Support (AFS applicable for SkillsFuture Career Transition Programme) for fee calculation." Tender 8.2.18: "The System shall facilitate applicants to check on the available Skills Future Credit (SFC) including SFC (mid-career) top-up." Tender 12.2.3: "The System shall automatically track the total utilisatoin of Alumni Course Credit (ACC) and be able to cap the total ACC utilization at the specified (for example 50%) percentage of the full course fee."
A9: DEF-077 | B9: Funding | C9: 2 | D9: 6.3.3 | E9: 6 Net fee and invoice | F9: TC-SCN-R06-01 | G9: 8.1.5 | H9: [Funding] Withdrawal requested in the portal and approved does not reverse the SSG grant | I9: 1 | J9: =IF(I9<=2,"High","Low") -> High | K9: High | L9: =IF(J9="High",IF(K9="High","Critical","High"),IF(K9="High","Medium","Low")) -> Critical | M9: Potential | N9: =IF(I9=1,"Smoke",IF(I9=2,"Regression Core","Regression Extended")) -> Smoke | O9: SIT (assumed, ASM-01) | P9: 1. A paid, grant funded self-enrolment 2. The learner requests withdrawal in the self-service portal and an approver approves | Q9: 1. Submit the withdrawal request as the learner 2. Approve it as the approver 3. Open the fee change, the credit note and the grant claim of the learner | R9: 1. The fee change is applied after the approval 2. A credit note is issued 3. The grant claim is reversed or reduced | S9: The credit note is issued and the grant claim stays at the original amount | T9: SSG funds are claimed for a learner who withdrew, a compliance break | U9: Withdrawal in the portal starts the fee change, and the grant is a separate item. Severity 1: Blocker, or money, funding or compliance break. Urgency High by ASM-92. | V9: Tender 6.3.3: "The System shall allow fee changes and approval in cases including but not limited to: // 1) Withdrawals" Tender 8.1.5: "The System shall allow learners to review offer decisions, appeals, request change of programme/courses, request for leave of absence, request for withdrawal, request for deferment, request for waiver, etc. via a self-service portal."
A10: DEF-078 | B10: Enrolment | C10: 2 | D10: 8.5.16 | E10: 5 Seat confirm or waitlist | F10: TC-SCN-R03-03 | G10: 8.5.3 | H10: [Enrolment] Waitlisted learner is sent to TPGateway as enrolled | I10: 1 | J10: =IF(I10<=2,"High","Low") -> High | K10: High | L10: =IF(J10="High",IF(K10="High","Critical","High"),IF(K10="High","Medium","Low")) -> Critical | M10: Potential | N10: =IF(I10=1,"Smoke",IF(I10=2,"Regression Core","Regression Extended")) -> Smoke | O10: SIT (assumed, ASM-01) | P10: 1. A full course run with a waitlisted learner 2. The TPGateway test endpoint is on | Q10: 1. Self-enrol a learner on a full run so that the learner goes to the waitlist 2. Open the TPGateway record of the learner | R10: 1. No enrolment record is sent for the waitlisted learner 2. A record is sent after the seat is confirmed | S10: An enrolment record with the status confirmed is sent while the learner is still on the waitlist | T10: SSG holds a wrong enrolment and a claim can follow, a compliance break | U10: The interface fires on registration instead of on confirmation. Severity 1: Blocker, or money, funding or compliance break. Urgency High by ASM-92. | V10: Tender 8.5.16: "The System shall have the capability to automatically interface Enrolments to Training Partners Gateway (TPGateway)." Tender 8.5.3: "The System shall allow the capability to automatically put Learners on a waitlist if the class is full and notify candidates when seats are available and channel them to another course."
A11: DEF-079 | B11: Funding | C11: 3 | D11: 6.4.4 | E11: 7 Outcome based funding | F11: TC-SCN-R07-01 | G11: 10.2.12 | H11: [Funding] Learner with the status Completed but no released marks is funded as a pass | I11: 1 | J11: =IF(I11<=2,"High","Low") -> High | K11: High | L11: =IF(J11="High",IF(K11="High","Critical","High"),IF(K11="High","Medium","Low")) -> Critical | M11: Potential | N11: =IF(I11=1,"Smoke",IF(I11=2,"Regression Core","Regression Extended")) -> Smoke | O11: SIT (assumed, ASM-01) | P11: 1. A completed SSG funded course with attendance 90 percent 2. The setting to show Completed without releasing marks is on 3. The learner failed the assessment | Q11: 1. Set the result of the learner to fail 2. Show the status Completed without releasing marks 3. Run the funding decision 4. Open the funding status | R11: 1. The learner is not eligible for the funding | S11: The learner is marked eligible because the status Completed is read as passed | T11: SSG funding is claimed without a pass, a compliance break | U11: The status shown to the learner is reused by the funding rule. Severity 1: Blocker, or money, funding or compliance break. Urgency High by ASM-92. | V11: Tender 6.4.4: "The System shall support automated outcome based SkillsFuture Singapore (SSG) funding based on the following requirements: // 1) Minimum 75% attendance // 2) Passing the assessment" Tender 10.2.12: "The System shall have a user configuration setting to show the status as completed without the release of any assessment marks if required."
A12: DEF-080 | B12: Enrolment | C12: 3 | D12: 8.6.2 | E12: 2 Blacklist check | F12: TC-SCN-R02-03 | G12: 8.2.9 | H12: [Registration] Company sponsored learner is enrolled although the sponsoring company is blacklisted for non payment | I12: 2 | J12: =IF(I12<=2,"High","Low") -> High | K12: Low | L12: =IF(J12="High",IF(K12="High","Critical","High"),IF(K12="High","Medium","Low")) -> High | M12: Potential | N12: =IF(I12=1,"Smoke",IF(I12=2,"Regression Core","Regression Extended")) -> Regression Core | O12: SIT (assumed, ASM-01) | P12: 1. A company on the blacklist of earlier non payment 2. A learner who registers as company sponsored with that company | Q12: 1. Self-enrol the learner as company sponsored with the blacklisted company details 2. Observe the result of the blacklist check | R12: 1. The System finds the company on the blacklist 2. The application is not enrolled | S12: The application is enrolled because only the person is checked and the company is not | T12: Non paying companies enrol again and revenue is lost | U12: The company name is typed by the learner and no staff compare it. Severity 2: Critical or major function fails. Urgency Low by ASM-92. | V12: Tender 8.6.2: "The System shall have the capability to sync to SSG given’s blacklist records, as well as the finance payment records for potential enrolled company sponsored applicants if they are blacklisted for CET courses (due to earlier non-payments)." Tender 8.2.9: "The System shall allow individual learners to register as self-sponsored or company sponsored and have the capability to provide costing accordingly. For company sponsored, the System shall allow learner to provide the company details such as company name, address, and contact person, etc."
A13: DEF-081 | B13: Enrolment | C13: 2 | D13: 8.5.3 | E13: 5 Seat confirm or waitlist | F13: TC-SCN-R03-02 | G13: 8.2.13 | H13: [Enrolment] Seat stays held for a learner whose grant check failed and the waitlist does not move | I13: 2 | J13: =IF(I13<=2,"High","Low") -> High | K13: High | L13: =IF(J13="High",IF(K13="High","Critical","High"),IF(K13="High","Medium","Low")) -> Critical | M13: Potential | N13: =IF(I13=1,"Smoke",IF(I13=2,"Regression Core","Regression Extended")) -> Regression Core | O13: SIT (assumed, ASM-01) | P13: 1. A full run with a waitlisted learner 2. A learner who holds the last seat and fails the grant check | Q13: 1. Self-enrol the learner who fails the grant check 2. Cancel the application at the fee step 3. Open the seats and the waitlist | R13: 1. The seat is released 2. The first waitlisted learner is notified | S13: The seat stays held and the waitlisted learner is not notified | T13: Seats stay empty and the waitlisted learner is lost | U13: A half done self-enrolment keeps its seat with no staff to release it. Severity 2: Critical or major function fails. Urgency High by ASM-92. | V13: Tender 8.5.3: "The System shall allow the capability to automatically put Learners on a waitlist if the class is full and notify candidates when seats are available and channel them to another course." Tender 8.2.13: "The System shall facilitate and check the eligibility of SSG grant for applicants and compute the course fee for registration."
A14: DEF-082 | B14: Funding | C14: 2 | D14: 9.1.9 | E14: 6 Net fee and invoice | F14: TC-SCN-R05-02 | G14: 8.5.3 | H14: [Funding] Invoice is generated for a learner who is only on the waitlist | I14: 2 | J14: =IF(I14<=2,"High","Low") -> High | K14: High | L14: =IF(J14="High",IF(K14="High","Critical","High"),IF(K14="High","Medium","Low")) -> Critical | M14: Potential | N14: =IF(I14=1,"Smoke",IF(I14=2,"Regression Core","Regression Extended")) -> Regression Core | O14: SIT (assumed, ASM-01) | P14: 1. A full run and a learner who self-enrols and goes to the waitlist | Q14: 1. Self-enrol the learner on the full run 2. Open the invoices of the learner | R14: 1. No invoice is generated before the seat is confirmed | S14: An invoice for the full net fee is generated at once | T14: The learner is asked to pay for a seat that is not held, and credit notes follow | U14: Invoicing starts at registration, not at confirmation. Severity 2: Critical or major function fails. Urgency High by ASM-92. | V14: Tender 9.1.9: "The System shall have the capability to automatically generate all billing items in the Learner’s invoice provisioned under the course fee setup when the Learner’s profiles fall within eligible criteria for auto application." Tender 8.5.3: "The System shall allow the capability to automatically put Learners on a waitlist if the class is full and notify candidates when seats are available and channel them to another course."
... A22: DEF-090 | B22: Enrolment | C22: 3 | D22: 8.1.14 | E22: 5 Seat confirm or waitlist | F22: TC-SCN-R08-02 | G22: 9.1.9 | H22: [Enrolment] Outcome message shows the course date in a different format from the invoice | I22: 4 | J22: =IF(I22<=2,"High","Low") -> Low | K22: Low | L22: =IF(J22="High",IF(K22="High","Critical","High"),IF(K22="High","Medium","Low")) -> Low | M22: Potential | N22: =IF(I22=1,"Smoke",IF(I22=2,"Regression Core","Regression Extended")) -> Regression Extended | O22: SIT (assumed, ASM-01) | P22: 1. A confirmed self-enrolment with an invoice | Q22: 1. Open the outcome message of the enrolment 2. Open the invoice 3. Compare the course dates | R22: 1. The course date has the same format in both documents | S22: The message shows 01/02/2027 and the invoice shows 2 Feb 2027 | T22: Cosmetic, the learner still understands the date | U22: Format only. Severity 4: Minor or cosmetic. Urgency Low by ASM-92. | V22: Tender 8.1.14: "The System shall have the capability to notify Learners and Corporate Customers of the outcome of the application, enrolment, withdrawal, deferment, course switching processing, whenever applicable." Tender 9.1.9: "The System shall have the capability to automatically generate all billing items in the Learner’s invoice provisioned under the course fee setup when the Learner’s profiles fall within eligible criteria for auto application."
A24: ="Table 2. Existing defects changed by the feature: "&COUNTA(A26:A36)&" defects, severity and priority before and after" -> Table 2. Existing defects changed by the feature: 11 defects, severity and priority before and after
A25: Defect ID | B25: Module | C25: Sprint | D25: Tender clause | E25: Flow step | F25: Related TC IDs | G25: Change | H25: Summary | I25: Severity before | J25: Severity after | K25: Urgency before | L25: Urgency after | M25: Priority before | N25: Priority after | O25: Status | P25: Suggested regression suite (after) | Q25: Why the feature changes it | R25: New triage rationale | S25: Evidence
A26: DEF-025 | B26: Funding | C26: 2 | D26: 8.1.8 | E26: 6 Net fee and invoice | F26: TC-SCN-045-02 | G26: ="Severity "&I26&" to "&J26 -> Severity 2 to 1 | H26: [Funding] Withdrawn paid application does not generate a credit note | I26: 2 | J26: 1 | K26: High | L26: High | M26: =IF(I26<=2,IF(K26="High","Critical","High"),IF(K26="High","Medium","Low")) -> Critical | N26: =IF(J26<=2,IF(L26="High","Critical","High"),IF(L26="High","Medium","Low")) -> Critical | O26: Potential | P26: =IF(J26=1,"Smoke",IF(J26=2,"Regression Core","Regression Extended")) -> Smoke | Q26: A learner can withdraw in the portal without staff. A missing credit note leaves paid money with the System and nobody sees it before the learner complains, so the harm is money | R26: Raised by the feature (ASM-101). Severity 1: Blocker, or money, funding or compliance break. Urgency High by ASM-92. | S26: Tender 8.1.8: "The System shall have the capability to automatically trigger finance functions upon changes to course application, including but not limited to: // 1) Invoicing // 2) Credit Notes 3) Refunds."
A27: DEF-029 | B27: Enrolment | C27: 1 | D27: 8.2.5 | E27: 1 Login and MyInfo | F27: TC-SCN-056-01 | G27: ="Severity "&I27&" to "&J27 -> Severity 3 to 2 | H27: [Registration] MyInfo data is not filled and the form opens empty for a signed in resident | I27: 3 | J27: 2 | K27: High | L27: High | M27: =IF(I27<=2,IF(K27="High","Critical","High"),IF(K27="High","Medium","Low")) -> Medium | N27: =IF(J27<=2,IF(L27="High","Critical","High"),IF(L27="High","Medium","Low")) -> Critical | O27: Potential | P27: =IF(J27=1,"Smoke",IF(J27=2,"Regression Core","Regression Extended")) -> Regression Core | Q27: MyInfo data is the only source of age and nationality for the fee and grant checks. An empty form stops the learner or leads to typed values, and no staff help | R27: Raised by the feature (ASM-101). Severity 2: Critical or major function fails. Urgency High by ASM-92. | S27: Tender 8.2.5: "The System shall populate applicant’s personal information (verified by SingPass MyInfo) from user account to registration form."
A28: DEF-032 | B28: Funding | C28: 2 | D28: 8.2.13 | E28: 4 Grant eligibility and fee | F28: TC-SCN-064-01 | G28: ="Severity "&I28&" to "&J28 -> Severity 2 to 1 | H28: [Funding] Computed fee at registration ignores the SSG grant for an eligible applicant | I28: 2 | J28: 1 | K28: High | L28: High | M28: =IF(I28<=2,IF(K28="High","Critical","High"),IF(K28="High","Medium","Low")) -> Critical | N28: =IF(J28<=2,IF(L28="High","Critical","High"),IF(L28="High","Medium","Low")) -> Critical | O28: Potential | P28: =IF(J28=1,"Smoke",IF(J28=2,"Regression Core","Regression Extended")) -> Smoke | Q28: The fee computed at registration is the amount the learner accepts without staff review. Ignoring the grant is a wrong amount charged | R28: Raised by the feature (ASM-101). Severity 1: Blocker, or money, funding or compliance break. Urgency High by ASM-92. | S28: Tender 8.2.13: "The System shall facilitate and check the eligibility of SSG grant for applicants and compute the course fee for registration."
A29: DEF-034 | B29: Funding | C29: 2 | D29: 8.2.16 | E29: 4 Grant eligibility and fee | F29: TC-SCN-067-01 | G29: ="Severity "&I29&" to "&J29 -> Severity 3 to 2 | H29: [Funding] SME declaration is not saved with the application | I29: 3 | J29: 2 | K29: High | L29: High | M29: =IF(I29<=2,IF(K29="High","Critical","High"),IF(K29="High","Medium","Low")) -> Medium | N29: =IF(J29<=2,IF(L29="High","Critical","High"),IF(L29="High","Medium","Low")) -> Critical | O29: Potential | P29: =IF(J29=1,"Smoke",IF(J29=2,"Regression Core","Regression Extended")) -> Regression Core | Q29: Without staff, the SME declaration is the only record that the SME verification of 8.3.12 can read | R29: Raised by the feature (ASM-101). Severity 2: Critical or major function fails. Urgency High by ASM-92. | S29: Tender 8.2.16: "The System shall facilitate company sponsored applicants to do SME declaration."
A30: DEF-036 | B30: Funding | C30: 1 | D30: 8.2.18 | E30: 4 Grant eligibility and fee | F30: TC-SCN-069-01 | G30: ="Severity "&I30&" to "&J30 -> Severity 2 to 1 | H30: [Funding] SFC balance shown is not refreshed after a previous use | I30: 2 | J30: 1 | K30: High | L30: High | M30: =IF(I30<=2,IF(K30="High","Critical","High"),IF(K30="High","Medium","Low")) -> Critical | N30: =IF(J30<=2,IF(L30="High","Critical","High"),IF(L30="High","Medium","Low")) -> Critical | O30: Potential | P30: =IF(J30=1,"Smoke",IF(J30=2,"Regression Core","Regression Extended")) -> Smoke | Q30: The learner applies the SFC amount without staff review. A stale balance lets the learner use credit that is not there | R30: Raised by the feature (ASM-101). Severity 1: Blocker, or money, funding or compliance break. Urgency High by ASM-92. | S30: Tender 8.2.18: "The System shall facilitate applicants to check on the available Skills Future Credit (SFC) including SFC (mid-career) top-up."
A31: DEF-037 | B31: Funding | C31: 3 | D31: 8.2.19 | E31: 4 Grant eligibility and fee | F31: TC-SCN-070-02 | G31: ="Severity "&I31&" to "&J31 -> Severity 2 to 1 | H31: [Funding] Net fee in the overview differs from the net fee on the invoice | I31: 2 | J31: 1 | K31: Low | L31: High | M31: =IF(I31<=2,IF(K31="High","Critical","High"),IF(K31="High","Medium","Low")) -> High | N31: =IF(J31<=2,IF(L31="High","Critical","High"),IF(L31="High","Medium","Low")) -> Critical | O31: Potential | P31: =IF(J31=1,"Smoke",IF(J31=2,"Regression Core","Regression Extended")) -> Smoke | Q31: The overview is the fee the learner agrees to. A different amount on the invoice breaks that agreement and is a money error | R31: Raised by the feature (ASM-101). Severity 1: Blocker, or money, funding or compliance break. Urgency High by ASM-92. | S31: Tender 8.2.19: "The System shall provide an overview of course fees, taking into consideration SFC, SSG grant, & Alumni Credits."
A32: DEF-041 | B32: Enrolment | C32: 2 | D32: 8.5.3 | E32: 5 Seat confirm or waitlist | F32: TC-SCN-091-02 | G32: ="Severity "&I32&" to "&J32 -> Severity 3 to 2 | H32: [Enrolment] No notification is sent when a seat is freed for a waitlisted applicant | I32: 3 | J32: 2 | K32: High | L32: High | M32: =IF(I32<=2,IF(K32="High","Critical","High"),IF(K32="High","Medium","Low")) -> Medium | N32: =IF(J32<=2,IF(L32="High","Critical","High"),IF(L32="High","Medium","Low")) -> Critical | O32: Potential | P32: =IF(J32=1,"Smoke",IF(J32=2,"Regression Core","Regression Extended")) -> Regression Core | Q32: The notice is the only way a self-enrolling learner learns that a seat is free. Without staff to call, seats stay empty | R32: Raised by the feature (ASM-101). Severity 2: Critical or major function fails. Urgency High by ASM-92. | S32: Tender 8.5.3: "The System shall allow the capability to automatically put Learners on a waitlist if the class is full and notify candidates when seats are available and channel them to another course."
A33: DEF-042 | B33: Enrolment | C33: 2 | D33: 8.5.5 | E33: 3 Prerequisite and restriction check | F33: TC-SCN-093-01 | G33: ="Severity "&I33&" to "&J33 -> Severity 2 to 1 | H33: [Enrolment] Learner outside the age limit is enrolled | I33: 2 | J33: 1 | K33: High | L33: High | M33: =IF(I33<=2,IF(K33="High","Critical","High"),IF(K33="High","Medium","Low")) -> Critical | N33: =IF(J33<=2,IF(L33="High","Critical","High"),IF(L33="High","Medium","Low")) -> Critical | O33: Potential | P33: =IF(J33=1,"Smoke",IF(J33=2,"Regression Core","Regression Extended")) -> Smoke | Q33: Without staff review, the age restriction is enforced only by the System. A miss enrols an unqualified learner, which is a compliance break | R33: Raised by the feature (ASM-101). Severity 1: Blocker, or money, funding or compliance break. Urgency High by ASM-92. | S33: Tender 8.5.5: "The System shall include the capability to configure and set up enrolment restriction based on criteria including but not limited to: // 1) Age; // 2) Course/Assessment Prerequisites; // 3) Penalty; // 4) Capacity of course/assessment."
A34: DEF-045 | B34: Enrolment | C34: 3 | D34: 8.6.1 | E34: 2 Blacklist check | F34: TC-SCN-105-02 | G34: ="Severity "&I34&" to "&J34 -> Severity 2 to 1 | H34: [Enrolment] Registration from a blacklisted organisation is accepted without a flag | I34: 2 | J34: 1 | K34: Low | L34: High | M34: =IF(I34<=2,IF(K34="High","Critical","High"),IF(K34="High","Medium","Low")) -> High | N34: =IF(J34<=2,IF(L34="High","Critical","High"),IF(L34="High","Medium","Low")) -> Critical | O34: Potential | P34: =IF(J34=1,"Smoke",IF(J34=2,"Regression Core","Regression Extended")) -> Smoke | Q34: The flag has no reader when no staff handle the registration, so the blacklisted organisation is enrolled | R34: Raised by the feature (ASM-101). Severity 1: Blocker, or money, funding or compliance break. Urgency High by ASM-92. | S34: Tender 8.6.1: "The System shall allow the function of automated Penalty Management including but not limited to: // 1) Blacklist individual by SkillsFuture Singapore and Training provider Continuing Education and Training (CET) units; // 2) Blacklist Organizations by Continuing Education and Tr..."
A35: DEF-065 | B35: Funding | C35: 3 | D35: 12.2.1 | E35: 4 Grant eligibility and fee | F35: TC-SCN-148-01 | G35: ="Severity "&I35&" to "&J35 -> Severity 2 to 1 | H35: [Funding] Alumni credit balance is not reduced after the credit is used | I35: 2 | J35: 1 | K35: Low | L35: High | M35: =IF(I35<=2,IF(K35="High","Critical","High"),IF(K35="High","Medium","Low")) -> High | N35: =IF(J35<=2,IF(L35="High","Critical","High"),IF(L35="High","Medium","Low")) -> Critical | O35: Potential | P35: =IF(J35=1,"Smoke",IF(J35=2,"Regression Core","Regression Extended")) -> Smoke | Q35: A balance that is not reduced lets the learner reuse the credit on each self-enrolment, with no staff check | R35: Raised by the feature (ASM-101). Severity 1: Blocker, or money, funding or compliance break. Urgency High by ASM-92. | S35: Tender 12.2.1: "The System shall be able to automatically track alumni course credit balance for Continuing Education and Training (CET) programmes/courses and maintain alumni credit balance for billing."
A36: DEF-067 | B36: Funding | C36: 1,2,3 | D36: 18.1.2 | E36: 4 Grant eligibility and fee | F36: TC-SCN-152-01 | G36: ="Severity "&I36&" to "&J36 -> Severity 2 to 1 | H36: [Funding] Grant is taken from a fixed value when the Grant Calculator is down | I36: 2 | J36: 1 | K36: High | L36: High | M36: =IF(I36<=2,IF(K36="High","Critical","High"),IF(K36="High","Medium","Low")) -> Critical | N36: =IF(J36<=2,IF(L36="High","Critical","High"),IF(L36="High","Medium","Low")) -> Critical | O36: Potential | P36: =IF(J36=1,"Smoke",IF(J36=2,"Regression Core","Regression Extended")) -> Smoke | Q36: A fixed grant value is applied to every self-enrolling learner without warning. A wrong grant is money and funding | R36: Raised by the feature (ASM-101). Severity 1: Blocker, or money, funding or compliance break. Urgency High by ASM-92. | S36: Tender 18.1.2: "2) Grant Calculator integration // 3) SFC gateway integration // 8) Grant integration"

Sheet Regression Assumptions
A1: ASM ID | B1: Type | C1: Requirement | D1: Original gap | E1: Assumption | F1: Nearest evidence | G1: Reason | H1: If the input differs | I1: State | J1: Affected TCs | K1: Question to confirm | L1: Resolution
A2: ASM-96 | B2: Assumption | C2: Regression plan | D2: The Tender and the slides give no regression rule | E2: The regression suite of a test case follows its Severity: Severity 1 is Smoke, Severity 2 is Core, Severity 3 and 4 is Extended. A Reject case is Not ready. Only test cases of clauses on a step of the Self-Enrol + Funding flow (Direct), clauses that share data or a rule with them (Possible) and the new test cases are in the regression pack. Test cases of the other clauses of the three modules are left out | F2: Lesson 3 risk based regression scope and Lesson 4 retesting and regression (course) | G2: Level 1: risk is the only selection basis the course gives | H2: If the team selects by changed component, change the Regression suite column | I2: Open | J2: Regression TestCases columns Flow step, Impact, Regression suite | K2: Is regression selected by risk or by changed component?
A3: ASM-97 | B3: Assumption | C3: Regression plan | D3: No entry or exit criteria are given | E3: Entry: the build is deployed to SIT and all Smoke cases pass. Exit: no open Severity 1 or 2 defect, all Core cases run, and at least 95 percent of Core cases pass. The 95 percent is my figure | F3: Lesson 3 exit criteria idea (course) | G3: Level 1: figures are needed for a plan | H3: If the team sets other limits, replace the figures in the Regression Plan document | I3: Open | J3: Regression TestCases column Regression suite | K3: What are the entry and exit limits?
A4: ASM-98 | B4: Assumption | C4: Flow step | D4: The Tender has no Self-Enrol clause | E4: The flow has 7 steps: 1 Login and MyInfo, 2 Blacklist check, 3 Prerequisite and restriction check, 4 Grant eligibility and fee, 5 Seat confirm or waitlist, 6 Net fee and invoice, 7 Outcome based funding. Each clause is linked to the step it supports (Clause List Notes A6). Where a new test case needs an expected result for a join between two steps, the result is taken from this order of steps | F4: Inference from Tender clauses of sections 2, 8, 6.3, 6.4, 9 | G4: Level 1: the feature is named in slide 44 but not described | H4: If the real flow differs, change the Flow step column and the new test cases | I4: Open | J4: Regression TestCases columns Flow step, Impact; all 26 new test cases | K4: What are the steps of Self-Enrol + Funding?
A5: ASM-99 | B5: Assumption | C5: Regression plan | D5: The Tender does not say which test cases a new feature affects | E5: A clause on a step of the flow is Direct. A clause of the three modules that is not on a step but shares data, a rule or a trigger with a Direct clause is Possible. The other clauses are not affected. The reason for each Possible clause is in the column Why in regression | F5: Lesson 3 risk based regression scope (course) | G5: Level 1: a side effect through shared data is possible but cannot be read from the Tender | H5: If the team knows the design, move clauses between Direct, Possible and not affected | I5: Open | J5: Regression TestCases column Impact (Possible rows) | K5: Which other clauses read the data or the result of the Self-Enrol + Funding flow?
A6: ASM-100 | B6: Assumption | C6: Regression plan | D6: A Possible test case needs a suite as well | E6: A Possible test case is never Smoke, because Smoke is kept for the flow itself. Possible with Severity 1 is Core and all other Possible test cases are Extended. A New test case follows its Severity like a Direct one | F6: ASM-96 | G6: Level 1: the risk of a side effect is lower than the risk of the flow | H6: If the team wants Possible cases in Smoke, change the formula of the column Regression suite | I6: Open | J6: Regression TestCases column Regression suite | K6: Should side effect test cases ever be in Smoke?
A7: ASM-101 | B7: Assumption | C7: Regression Defects | D7: The Tender does not say how a new feature changes the severity of existing defects | E7: Self-enrol removes the staff check. A defect whose symptom was caught or corrected by staff before money moved, and that now reaches the learner, the seat, the fee or the funding claim directly, takes the next more severe level. A defect limited to a report, a layout or an administrator only function keeps its severity. Urgency follows ASM-92 and Priority follows the matrix of ASM-91 after the change | F7: Slide 44 Individual Assignment and Lesson 4 Severity and Priority (course) | G7: Level 1: the feature changes who sees a failure first | H7: If the team judges a defect differently, change the column Severity after | I7: Open | J7: Regression Defects Table 2 | K7: Does the removal of staff review raise the severity of these defects?
A8: ASM-102 | B8: Assumption | C8: Regression TestCases | D8: ASM-91 lets defect severity differ from test case severity | E8: In Regression TestCases only, a test case linked to a changed defect takes the new severity of the defect when that is more severe, so that a Smoke defect has a Smoke test case. A new test case takes the severity of its new defect. The Priority is recalculated by ASM-95. The sheet TestCases is not changed. The Severity and Priority cells changed are in bold | F8: ASM-91, ASM-95 | G8: Level 1: a Severity 1 defect needs a test case in Smoke | H8: If the team keeps test case severity apart from defect severity, undo the bold cells | I8: Open | J8: TC-SCN-045-02 (2 to 1), TC-SCN-069-01 (2 to 1), TC-SCN-093-01 (2 to 1), TC-SCN-148-01 (2 to 1) | K8: Is the test case severity raised with the defect severity?
A9: ASM-103 | B9: Assumption | C9: Regression Defects and TestCases | D9: The new feature has no clause, so new defects and test cases have no Tender row of their own | E9: Each new defect and test case is placed where two or more steps meet. The Tender clause is the clause that states the rule, and the other clauses are in the columns Other clauses and Traceability Requirement. The Sprint is the latest Sprint of the clauses involved, because the join can be tested only then. The Checkpoint Ref is the checkpoint of the clause that states the rule. The scenario IDs SCN-R01 to SCN-R08 and the test case IDs TC-SCN-R01-01 and up exist only in Regression TestCases. Defect IDs continue from DEF-071. Status is Draft because the expected result depends on ASM-98 | F9: Tender clauses listed in the Evidence column of Regression Defects | G9: Level 1: a rule is needed so that every new row can be traced | H9: If the Tender owner adds a Self-Enrol clause, replace the Tender clause of the new rows | I9: Open | J9: Regression Defects Table 1, Regression TestCases Table 1 | K9: Is there a Tender clause for Self-Enrol + Funding?
A11: Rules applied
A12: Regression suite | C12: Severity 1 is Smoke, Severity 2 is Core, Severity 3 and 4 is Extended, Reject is Not ready (ASM-96). Possible cases follow ASM-100
A13: Scope | C13: Table 1 holds the new test cases. Table 2 holds the existing test cases to retest, Direct (on a step of the flow) and Possible (shared data or rules) (ASM-99)
A14: Defects | C14: Regression Defects Table 1 holds the new defects. Table 2 holds the existing defects whose severity changes, with the values before and after (ASM-101). Defects identical to the Defects sheet are not repeated
A15: Defect priority | C15: Impact x Urgency from Lesson 4 section 22. Impact is High for Severity 1 and 2, Urgency follows ASM-92
A16: Colours | C16: In the column Impact green marks a New test case and yellow marks a Possible test case. Severity and Status use the colours of the main sheets. A value in bold is a value changed by the feature
A17: Source data | C17: Table 2 of Regression TestCases copies rows of TestCases and Table 2 of Regression Defects refers to rows of Defects. Change the main sheets first
A18: Execution | C18: No test case was executed. Actual Result is Not Executed and every defect is potential
A20: References
A21: Tender_requirements_0232.xlsx | C21: Only requirement source. Verbatim quotes in the Evidence column of Regression Defects
A22: Slide 44 Individual Assignment | C22: Defect triage (Sev1 to 4) and regression plan for the Self-Enrol + Funding feature
A23: Lesson 3 and Lesson 4 (course) | C23: Risk based regression scope, retest versus regression, Severity and Priority
A24: Regression_Plan_Self-Enrol_Funding.docx | C24: Plan that uses these sheets (scope, suites, order, entry and exit)

Sheet Clause Overview
A1: Tender clauses by Sprint and Module (Training Management)
A2: Modules follow the assignment slides: Enrolment, Assessment, Funding. Sprints follow column Sprint # of the Tender. Counts are formulas over the sheets listed.
A4: Module | B4: Sprint 1 | C4: Sprint 2 | D4: Sprint 3 | E4: Unscheduled | F4: Total rows listed
A5: Enrolment | B5: =COUNTIFS('Sprint 1'!$A:$A,$A5) -> 48 | C5: =COUNTIFS('Sprint 2'!$A:$A,$A5) -> 63 | D5: =COUNTIFS('Sprint 3'!$A:$A,$A5) -> 28 | E5: =COUNTIFS(Unscheduled!$A:$A,$A5) -> 4 | F5: =SUM(B5:E5) -> 143
A6: Assessment | B6: =COUNTIFS('Sprint 1'!$A:$A,$A6) -> 6 | C6: =COUNTIFS('Sprint 2'!$A:$A,$A6) -> 2 | D6: =COUNTIFS('Sprint 3'!$A:$A,$A6) -> 52 | E6: =COUNTIFS(Unscheduled!$A:$A,$A6) -> 1 | F6: =SUM(B6:E6) -> 61
A7: Funding | B7: =COUNTIFS('Sprint 1'!$A:$A,$A7) -> 14 | C7: =COUNTIFS('Sprint 2'!$A:$A,$A7) -> 67 | D7: =COUNTIFS('Sprint 3'!$A:$A,$A7) -> 32 | E7: =COUNTIFS(Unscheduled!$A:$A,$A7) -> 18 | F7: =SUM(B7:E7) -> 131
A8: Total | B8: =SUM(B5:B7) -> 68 | C8: =SUM(C5:C7) -> 132 | D8: =SUM(D5:D7) -> 112 | E8: =SUM(E5:E7) -> 23 | F8: =SUM(F5:F7) -> 335
A9: A Tender row with several sprints (for example 1,2,3) counts once in each sprint it names, so the grand total can exceed the number of distinct Tender rows.
A11: Module | B11: Core rows | C11: Supporting rows | D11: Meaning
A12: Enrolment | B12: =COUNTIFS('Sprint 1'!$A:$A,$A12,'Sprint 1'!$B:$B,"Core")+COUNTIFS('Sprint 2'!$A:$A,$A12,'Sprint 2'!$B:$B,"Core")+COUNTIFS('Sprint 3'!$A:$A,$A12,'Sprint 3'!$B:$B,"Core")+COUNTIFS(Unscheduled!$A:$A,$A12,Unscheduled!$B:$B,"Core") -> 117 | C12: =COUNTIFS('Sprint 1'!$A:$A,$A12,'Sprint 1'!$B:$B,"Supporting")+COUNTIFS('Sprint 2'!$A:$A,$A12,'Sprint 2'!$B:$B,"Supporting")+COUNTIFS('Sprint 3'!$A:$A,$A12,'Sprint 3'!$B:$B,"Supporting")+COUNTIFS(Unscheduled!$A:$A,$A12,Unscheduled!$B:$B,"Supporting") -> 26 | D12: Core: registration and enrolment clauses (8.2, 8.3, 8.5, 8.6, 8.1.9 to 8.1.12). Supporting: login, form setup, course switching, integrations
A13: Assessment | B13: =COUNTIFS('Sprint 1'!$A:$A,$A13,'Sprint 1'!$B:$B,"Core")+COUNTIFS('Sprint 2'!$A:$A,$A13,'Sprint 2'!$B:$B,"Core")+COUNTIFS('Sprint 3'!$A:$A,$A13,'Sprint 3'!$B:$B,"Core")+COUNTIFS(Unscheduled!$A:$A,$A13,Unscheduled!$B:$B,"Core") -> 44 | C13: =COUNTIFS('Sprint 1'!$A:$A,$A13,'Sprint 1'!$B:$B,"Supporting")+COUNTIFS('Sprint 2'!$A:$A,$A13,'Sprint 2'!$B:$B,"Supporting")+COUNTIFS('Sprint 3'!$A:$A,$A13,'Sprint 3'!$B:$B,"Supporting")+COUNTIFS(Unscheduled!$A:$A,$A13,Unscheduled!$B:$B,"Supporting") -> 17 | D13: Core: mark and grade setup (6.5) and section 10 (attendance, assessment, progression). Supporting: certificate rules, assessment scheduling, integrations
A14: Funding | B14: =COUNTIFS('Sprint 1'!$A:$A,$A14,'Sprint 1'!$B:$B,"Core")+COUNTIFS('Sprint 2'!$A:$A,$A14,'Sprint 2'!$B:$B,"Core")+COUNTIFS('Sprint 3'!$A:$A,$A14,'Sprint 3'!$B:$B,"Core")+COUNTIFS(Unscheduled!$A:$A,$A14,Unscheduled!$B:$B,"Core") -> 89 | C14: =COUNTIFS('Sprint 1'!$A:$A,$A14,'Sprint 1'!$B:$B,"Supporting")+COUNTIFS('Sprint 2'!$A:$A,$A14,'Sprint 2'!$B:$B,"Supporting")+COUNTIFS('Sprint 3'!$A:$A,$A14,'Sprint 3'!$B:$B,"Supporting")+COUNTIFS(Unscheduled!$A:$A,$A14,Unscheduled!$B:$B,"Supporting") -> 42 | D14: Core: fee and funding setup (6.3, 6.4), grant checks at registration, alumni credit, PSEA, funding reports. Supporting: invoice, payment and refund clauses that carry funding
A16: Sheet guide
A17: Sprint 1, Sprint 2, Sprint 3 | B17: One sheet per sprint. Each sheet has three module blocks in the order Enrolment, Assessment, Funding.
A18: Unscheduled | B18: Rows with a blank Sprint # or a cell Excel converted to a date. Listed for transparency, not placed in a sprint.
A19: Clause List Notes | B19: Notes A1 to A9 on how clauses were mapped to modules and sprints, and Tender sections left out. The test case assumptions are on the Assumptions sheet.
A20: Column Self-Enrol + Funding flow step | B20: Draft link from a clause to a step of the Self-Enrol + Funding flow: 1 Login and MyInfo, 2 Blacklist check, 3 Prerequisite and restriction check, 4 Grant eligibility and fee, 5 Seat confirm or waitlist, 6 Net fee and invoice, 7 Outcome based funding. Draft until A6 is confirmed.

Sheet Sprint 1
A1: Sprint 1: Tender clauses by module
A2: Source: Tender_requirements_0232.xlsx, column Sprint #. A row with several sprints (for example 1,2,3) is listed in each sprint it names. Notes A1 to A9 are on the Clause List Notes sheet.
A4: Module | B4: Relevance | C4: Clause | D4: Requirement (Tender text) | E4: Context (lead in of the clause) | F4: Sprint # in Tender | G4: Self-Enrol + Funding flow step (draft, A6) | H4: Tender row | I4: Note
A5: ="ENROLMENT MODULE: "&COUNTIF($A$6:$A$53,"Enrolment")&" Tender rows" -> ENROLMENT MODULE: 48 Tender rows
A6: Enrolment | B6: Supporting | C6: 2.2 | D6: The System shall provide integration with SingPass for authentication of Singapore Residents for login. | F6: 1 | G6: 1 Login and MyInfo | H6: 24
A7: Enrolment | B7: Supporting | C7: 2.4 | D7: The System shall cater for credential login ID, password and 2FA through One Time Password (OTP) for Learners, Corporate Customers and external users (external trainers, both local & overseas) who cannot be authenticated using SingPass and CorpPass for login. | F7: 1 | H7: 26
A8: Enrolment | B8: Supporting | C8: 5.3.1 | D8: Learners shall have access to browse the course catalogue, their course progress including attendance, assessments, payments and make requests via a portal. SingPass MyInfo integration should be done to allow users to retrieve personal particulars information easily. | F8: 1 | H8: 180
A9: Enrolment | B9: Supporting | C9: 6.1.5 | D9: The System shall allow the differentiation between Credit Bearing and Non-Credit Bearing routes to a course and allow learners to pursue register accordingly. | F9: 1 | H9: 202
A10: Enrolment | B10: Supporting | C10: 7.1.1 | D10: 3) Course Run intake size configuration | E10: The System shall allow Course Administrator to manage and schedule Course Runs. The functions required include but not limited to: | F10: 1 | H10: 302
A11: Enrolment | B11: Supporting | C11: 7.1.1 | D11: 4) Course registration period configuration | E11: The System shall allow Course Administrator to manage and schedule Course Runs. The functions required include but not limited to: | F11: 1 | H11: 303
A12: Enrolment | B12: Supporting | C12: 8.1.1 | D12: The System shall allow the set-up of different workflows for approval with status tracking of programmes/courses to be offered, with course application management by course level and by course run. | F12: 1 | H12: 317
A13: Enrolment | B13: Supporting | C13: 8.1.2 | D13: The System shall allow multiple individual learner and corporate registration forms for the various types of courses by respective Schools. | F13: 1 | H13: 318
A14: Enrolment | B14: Supporting | C14: 8.1.3 | D14: The System shall allow import functions for batch registration by Sponsor (Employers) or by Staff. | F14: 1 | H14: 319
A15: Enrolment | B15: Supporting | C15: 8.1.3 | D15: The System shall have the capability to automatically perform batch processing of registration. | E15: The System shall allow import functions for batch registration by Sponsor (Employers) or by Staff. | F15: 1 | H15: 320
A16: Enrolment | B16: Supporting | C16: 8.1.4 | D16: The System shall perform basic registration form validation which includes mandatory field data entry, data types, format, minimum and maximum length, within predefined ranges, consistency, look up (validate data against predefined values), etc. | F16: 1 | H16: 321
A17: Enrolment | B17: Supporting | C17: 8.1.6 | D17: The System shall allow course runs to be cloned for several subsequent new course runs. | F17: 1 | H17: 323
A18: Enrolment | B18: Supporting | C18: 8.1.7 | D18: The System shall have the capability to allow uploading documents to support course application. | F18: 1 | H18: 324
A19: Enrolment | B19: Core | C19: 8.1.9 | D19: The System shall have the capability to allow multiple and parallel runs of the same course or assessment to be conducted with different parameter values such as period, training resource, fees, and grants. | F19: 1 | H19: 328
A20: Enrolment | B20: Core | C20: 8.1.10 | D20: The System shall have the capability to configure and set up a minimum and maximum number of Learners for each course or assessment. | F20: 1 | G20: 5 Seat confirm or waitlist | H20: 329
A21: Enrolment | B21: Core | C21: 8.1.11 | D21: The System shall have the capability to configure waitlists if meet the maximum number of learners for each course or assessment. And able to prioritize the applicants on a first come first serve basis. | F21: 1 | G21: 5 Seat confirm or waitlist | H21: 330
A22: Enrolment | B22: Core | C22: 8.1.12 | D22: The System shall have the capability to channel the applications on the waitlist to another course for confirmation. | F22: 1 | G22: 5 Seat confirm or waitlist | H22: 331
A23: Enrolment | B23: Core | C23: 8.2.1 | D23: The System shall ensure and lead all course applicants to create a new user account first when they register for the course. | F23: 1 | H23: 339
A24: Enrolment | B24: Core | C24: 8.2.2 | D24: The System shall allow Indemnity and Personal Data Protection Act (PDPA) declaration and consent to use personal data for course/ programme administration to be captured during registration for individual applicant, company-sponsored applicant, and company representative that submit the registration | F24: 1 | H24: 340
A25: Enrolment | B25: Core | C25: 8.2.2 | D25: The System shall allow acknowledgement of Terms and Conditions by applicants. | E25: The System shall allow Indemnity and Personal Data Protection Act (PDPA) declaration and consent to use personal data for course/ programme administration to be | F25: 1 | H25: 341
A26: Enrolment | B26: Core | C26: 8.2.3 | D26: The System shall allow Learners to opt out of receiving marketing material campaign. | F26: 1 | H26: 342
A27: Enrolment | B27: Core | C27: 8.2.4 | D27: The System shall allow registrants to log in with their existing user account if they already have one and populate their information. | F27: 1 | G27: 1 Login and MyInfo | H27: 343
A28: Enrolment | B28: Core | C28: 8.2.5 | D28: The System shall populate applicant’s personal information (verified by SingPass MyInfo) from user account to registration form. | F28: 1 | G28: 1 Login and MyInfo | H28: 344
A29: Enrolment | B29: Core | C29: 8.2.6 | D29: The System shall allow both mandatory and optional fields in the registration form and have a mechanism for applicants to save the application, if not completed in stipulated time or Learners need to revisit later. | F29: 1 | H29: 345
A30: Enrolment | B30: Core | C30: 8.2.7 | D30: The System shall have a mechanism to track incomplete registration forms, send automatic reminders to applicants to complete; alert and allow Course Administrators to run reports for monitoring. | F30: 1 | H30: 346
A31: Enrolment | B31: Core | C31: 8.2.8 | D31: The System shall allow registration at both course and programme level. | F31: 1 | H31: 347
A32: Enrolment | B32: Core | C32: 8.2.10 | D32: The System shall allow uploading of supporting documents for registration and automated checking for the list of required documents to be submitted. | F32: 1 | H32: 349
A33: Enrolment | B33: Core | C33: 8.2.15 | D33: The System shall capture all information in structured fields for downstream processing of activities and avoid re-entering of information. | F33: 1 | H33: 354
A34: Enrolment | B34: Core | C34: 8.2.19 (unnumbered paragraph) | D34: 1. Salutation | E34: The System shall ensure all information is captured for processing the course application which includes the following but not limited to: | F34: 1 | H34: 360 | I34: Unnumbered paragraph that follows 8.2.19 in the Tender; it is the list of data captured at registration
A35: Enrolment | B35: Core | C35: 8.2.19 (unnumbered paragraph) | D35: 2. Full name as per NRIC/FIN/Passport | E35: The System shall ensure all information is captured for processing the course application which includes the following but not limited to: | F35: 1 | H35: 361 | I35: Unnumbered paragraph that follows 8.2.19 in the Tender; it is the list of data captured at registration
A36: Enrolment | B36: Core | C36: 8.2.19 (unnumbered paragraph) | D36: 3. NRIC/FIN/Passport No | E36: The System shall ensure all information is captured for processing the course application which includes the following but not limited to: | F36: 1 | H36: 362 | I36: Unnumbered paragraph that follows 8.2.19 in the Tender; it is the list of data captured at registration
A37: Enrolment | B37: Core | C37: 8.2.19 (unnumbered paragraph) | D37: 4. Date of birth | E37: The System shall ensure all information is captured for processing the course application which includes the following but not limited to: | F37: 1 | H37: 363 | I37: Unnumbered paragraph that follows 8.2.19 in the Tender; it is the list of data captured at registration
A38: Enrolment | B38: Core | C38: 8.2.19 (unnumbered paragraph) | D38: 5. Nationality | E38: The System shall ensure all information is captured for processing the course application which includes the following but not limited to: | F38: 1 | H38: 364 | I38: Unnumbered paragraph that follows 8.2.19 in the Tender; it is the list of data captured at registration
A39: Enrolment | B39: Core | C39: 8.2.19 (unnumbered paragraph) | D39: 6. Address | E39: The System shall ensure all information is captured for processing the course application which includes the following but not limited to: | F39: 1 | H39: 365 | I39: Unnumbered paragraph that follows 8.2.19 in the Tender; it is the list of data captured at registration
A40: Enrolment | B40: Core | C40: 8.2.19 (unnumbered paragraph) | D40: 7. Telephone No | E40: The System shall ensure all information is captured for processing the course application which includes the following but not limited to: | F40: 1 | H40: 366 | I40: Unnumbered paragraph that follows 8.2.19 in the Tender; it is the list of data captured at registration
A41: Enrolment | B41: Core | C41: 8.2.19 (unnumbered paragraph) | D41: 8. Email address | E41: The System shall ensure all information is captured for processing the course application which includes the following but not limited to: | F41: 1 | H41: 367 | I41: Unnumbered paragraph that follows 8.2.19 in the Tender; it is the list of data captured at registration
A42: Enrolment | B42: Core | C42: 8.2.19 (unnumbered paragraph) | D42: 9. Education Information | E42: The System shall ensure all information is captured for processing the course application which includes the following but not limited to: | F42: 1 | H42: 368 | I42: Unnumbered paragraph that follows 8.2.19 in the Tender; it is the list of data captured at registration
A43: Enrolment | B43: Core | C43: 8.2.19 (unnumbered paragraph) | D43: 10. Alumni status | E43: The System shall ensure all information is captured for processing the course application which includes the following but not limited to: | F43: 1 | H43: 369 | I43: Unnumbered paragraph that follows 8.2.19 in the Tender; it is the list of data captured at registration
A44: Enrolment | B44: Core | C44: 8.2.19 (unnumbered paragraph) | D44: 11. Professional Body Membership | E44: The System shall ensure all information is captured for processing the course application which includes the following but not limited to: | F44: 1 | H44: 370 | I44: Unnumbered paragraph that follows 8.2.19 in the Tender; it is the list of data captured at registration
A45: Enrolment | B45: Core | C45: 8.2.19 (unnumbered paragraph) | D45: 12. Company Name | E45: The System shall ensure all information is captured for processing the course application which includes the following but not limited to: | F45: 1 | H45: 371 | I45: Unnumbered paragraph that follows 8.2.19 in the Tender; it is the list of data captured at registration
... A50: Enrolment | B50: Core | C50: 8.2.19 (unnumbered paragraph) | D50: 17. Billing address | E50: The System shall ensure all information is captured for processing the course application which includes the following but not limited to: | F50: 1 | H50: 376 | I50: Unnumbered paragraph that follows 8.2.19 in the Tender; it is the list of data captured at registration
A51: Enrolment | B51: Supporting | C51: 18.1.2 | D51: 4) Enrolment integration | E51: The System shall provide seamless integration with SSG systems / TG Gateway at the various integration points but not limited to the following processes: | F51: 1,2,3 | H51: 952
A52: Enrolment | B52: Supporting | C52: 18.2.1 | D52: The System shall support integration with the external entity MyInfo. | F52: 1 | G52: 1 Login and MyInfo | H52: 960
A53: Enrolment | B53: Supporting | C53: 18.2.2 | D53: The System shall support integration with the external entity SingPass. | F53: 1 | G53: 1 Login and MyInfo | H53: 961
A54: ="ASSESSMENT MODULE: "&COUNTIF($A$55:$A$60,"Assessment")&" Tender rows" -> ASSESSMENT MODULE: 6 Tender rows
A55: Assessment | B55: Supporting | C55: 7.1.1 | D55: 7) Assessment scheduling | E55: The System shall allow Course Administrator to manage and schedule Course Runs. The functions required include but not limited to: | F55: 1 | H55: 306
A56: Assessment | B56: Supporting | C56: 7.1.5 | D56: The System shall have the capability to tag resources and facilities to courses and assessments. | F56: 1 | H56: 311
A57: Assessment | B57: Supporting | C57: 7.1.6 | D57: The System shall have the capability to allow administrators to create course / assessment schedule in template form with upload function. | F57: 1 | H57: 312
A58: Assessment | B58: Core | C58: 10.3.2 | D58: The System shall include the capability to track and recommend the progression of courses a Learner must complete in order to attain the relevant qualification including the courses passed, enrolled in, outstanding, and different course equivalency and remaining candidature. | F58: 1 | H58: 577
A59: Assessment | B59: Supporting | C59: 18.1.2 | D59: 5) eAttendance integration | E59: The System shall provide seamless integration with SSG systems / TG Gateway at the various integration points but not limited to the following processes: | F59: 1,2,3 | H59: 953
A60: Assessment | B60: Supporting | C60: 18.1.2 | D60: 6) Assessment integration | E60: The System shall provide seamless integration with SSG systems / TG Gateway at the various integration points but not limited to the following processes: | F60: 1,2,3 | H60: 954
A61: ="FUNDING MODULE: "&COUNTIF($A$62:$A$75,"Funding")&" Tender rows" -> FUNDING MODULE: 14 Tender rows
A62: Funding | B62: Core | C62: 6.3.1 | D62: The System shall allow course fee profile creation for self-sponsored and company sponsorships cases. | F62: 1 | H62: 222
A63: Funding | B63: Core | C63: 6.3.2 | D63: The System shall allow the creation of rules for calculation of course fees and GST. | F63: 1 | H63: 223
A64: Funding | B64: Core | C64: 6.3.6 | D64: 7) MOE teachers | E64: The System shall have the capability to generate fees payable with automatic calculation based on criteria including but not limited to: | F64: 1 | H64: 240
A65: Funding | B65: Core | C65: 6.4.1 | D65: The System shall allow the setup of different fee profiles with different fee types for self-sponsored and corporate sponsored for SkillsFuture subsidised and nonsubsidised courses, with details including but not limited to each different eligibility rule around subsidies, grants, credits, and discounts for different fee profiles. | F65: 1 | G65: 4 Grant eligibility and fee | H65: 243
A66: Funding | B66: Core | C66: 6.4.2 | D66: 3) Ad-hoc discount | E66: The System shall allow the Course Administrators to configure various types of discounts with complex and multi-tier hierarchical business rules and eligibility | F66: 1 | H66: 247
A67: Funding | B67: Core | C67: 6.4.2 | D67: 4) Group discount | E67: The System shall allow the Course Administrators to configure various types of discounts with complex and multi-tier hierarchical business rules and eligibility | F67: 1 | H67: 248
A68: Funding | B68: Core | C68: 6.4.6 | D68: The System shall allow the option to apply a discretionary discount by percentage or a flat rate with automated calculation of fees after applying the discount. The System shall facilitate the refunds of fees with necessary approvals. | F68: 1,2 | H68: 256
A69: Funding | B69: Core | C69: 6.4.11 | D69: For multiple sponsorships per course, the System shall support multiple billing of sponsors with pre-configured billing allocation automatically. | E69: The System shall allow the setting up of multiple funding agencies, schemes, and/or multiple sponsorships per course/programme. | F69: 1 | H69: 270
A70: Funding | B70: Supporting | C70: 8.2.9 | D70: The System shall allow individual learners to register as self-sponsored or company sponsored and have the capability to provide costing accordingly. For company sponsored, the System shall allow learner to provide the company details such as company name, address, and contact person, etc. | F70: 1 | G70: 4 Grant eligibility and fee | H70: 348
A71: Funding | B71: Core | C71: 8.2.18 | D71: The System shall facilitate applicants to check on the available Skills Future Credit (SFC) including SFC (mid-career) top-up. | F71: 1 | G71: 4 Grant eligibility and fee | H71: 357
A72: Funding | B72: Supporting | C72: 18.1.1 | D72: The System shall support integration with the SkillsFuture Singapore (SSG) System and Training Partners Gateway (TPGateway). | F72: 1,2,3 | H72: 947
A73: Funding | B73: Core | C73: 18.1.2 | D73: 2) Grant Calculator integration | E73: The System shall provide seamless integration with SSG systems / TG Gateway at the various integration points but not limited to the following processes: | F73: 1,2,3 | H73: 950
A74: Funding | B74: Core | C74: 18.1.2 | D74: 3) SFC gateway integration | E74: The System shall provide seamless integration with SSG systems / TG Gateway at the various integration points but not limited to the following processes: | F74: 1,2,3 | H74: 951
A75: Funding | B75: Core | C75: 18.1.2 | D75: 8) Grant integration | E75: The System shall provide seamless integration with SSG systems / TG Gateway at the various integration points but not limited to the following processes: | F75: 1,2,3 | H75: 956

Sheet Sprint 2
A1: Sprint 2: Tender clauses by module
A2: Source: Tender_requirements_0232.xlsx, column Sprint #. A row with several sprints (for example 1,2,3) is listed in each sprint it names. Notes A1 to A9 are on the Clause List Notes sheet.
A4: Module | B4: Relevance | C4: Clause | D4: Requirement (Tender text) | E4: Context (lead in of the clause) | F4: Sprint # in Tender | G4: Self-Enrol + Funding flow step (draft, A6) | H4: Tender row | I4: Note
A5: ="ENROLMENT MODULE: "&COUNTIF($A$6:$A$68,"Enrolment")&" Tender rows" -> ENROLMENT MODULE: 63 Tender rows
A6: Enrolment | B6: Supporting | C6: 8.1.5 | D6: The System shall allow learners to review offer decisions, appeals, request change of programme/courses, request for leave of absence, request for withdrawal, request for deferment, request for waiver, etc. via a self-service portal. Relevant workflow processing shall be triggered based on the type of learner's request. | F6: 2 | H6: 322
A7: Enrolment | B7: Core | C7: 8.2.11 | D7: The System shall allow bulk registrations by uploading learner information in Excel file and have a mechanism to upload all supporting documents. | F7: 2 | H7: 350
A8: Enrolment | B8: Core | C8: 8.2.12 | D8: The System shall allow group registrations for 3 people or more, early bird registration, for applicants to enjoy respective discounts. | F8: 2 | H8: 351
A9: Enrolment | B9: Core | C9: 8.2.14 | D9: The System shall check if applicants are in the SSG and Schools’ blacklisting and compute the overview of course fee for registration. | F9: 2 | G9: 2 Blacklist check | H9: 353
A10: Enrolment | B10: Core | C10: 8.2.19 (unnumbered paragraph) | D10: 18. Company HR contact (for company sponsorship) | E10: The System shall ensure all information is captured for processing the course application which includes the following but not limited to: | F10: 2 | H10: 377 | I10: Unnumbered paragraph that follows 8.2.19 in the Tender; it is the list of data captured at registration
A11: Enrolment | B11: Core | C11: 8.2.19 (unnumbered paragraph) | D11: The System shall allow standard email templates where Course Administrators can activate a communication to applicants or communication email sent automatically. | E11: The System shall ensure all information is captured for processing the course application which includes the following but not limited to: | F11: 2 | H11: 378 | I11: Unnumbered paragraph that follows 8.2.19 in the Tender; it is the list of data captured at registration
A12: Enrolment | B12: Core | C12: 8.2.20 | D12: The System shall validate the prerequisites and enrolment criteria of courses and programmes during application registration. If Learners do not meet the validation criteria, the System shall alert Administrators and provide them with descriptive reasons for the failed application, for follow-up. | F12: 2 | G12: 3 Prerequisite and restriction check | H12: 379
A13: Enrolment | B13: Core | C13: 8.3.1 | D13: (A) Company HR Contact: - 1. Company Name | E13: The System shall ensure important information is captured for processing the application which includes the following but not limited to: | F13: 2 | H13: 382
A14: Enrolment | B14: Core | C14: 8.3.1 | D14: 2. Department | E14: The System shall ensure important information is captured for processing the application which includes the following but not limited to: | F14: 2 | H14: 383
A15: Enrolment | B15: Core | C15: 8.3.1 | D15: 3. Company website | E15: The System shall ensure important information is captured for processing the application which includes the following but not limited to: | F15: 2 | H15: 384
A16: Enrolment | B16: Core | C16: 8.3.1 | D16: 4. Company address | E16: The System shall ensure important information is captured for processing the application which includes the following but not limited to: | F16: 2 | H16: 385
A17: Enrolment | B17: Core | C17: 8.3.1 | D17: 5. Billing address | E17: The System shall ensure important information is captured for processing the application which includes the following but not limited to: | F17: 2 | H17: 386
A18: Enrolment | B18: Core | C18: 8.3.1 | D18: 6. HR Contact Name | E18: The System shall ensure important information is captured for processing the application which includes the following but not limited to: | F18: 2 | H18: 387
A19: Enrolment | B19: Core | C19: 8.3.1 | D19: 7. HR Job Title | E19: The System shall ensure important information is captured for processing the application which includes the following but not limited to: | F19: 2 | H19: 388
A20: Enrolment | B20: Core | C20: 8.3.1 | D20: 8. HR Contact Tel No | E20: The System shall ensure important information is captured for processing the application which includes the following but not limited to: | F20: 2 | H20: 389
A21: Enrolment | B21: Core | C21: 8.3.1 | D21: 9. HR Contact Email address | E21: The System shall ensure important information is captured for processing the application which includes the following but not limited to: | F21: 2 | H21: 390
A22: Enrolment | B22: Core | C22: 8.3.1 | D22: 1. Salutation | E22: The System shall ensure important information is captured for processing the application which includes the following but not limited to: | F22: 2 | H22: 392
A23: Enrolment | B23: Core | C23: 8.3.1 | D23: 2. Full name as per NRIC/FIN/Passport | E23: The System shall ensure important information is captured for processing the application which includes the following but not limited to: | F23: 2 | H23: 393
A24: Enrolment | B24: Core | C24: 8.3.1 | D24: 3. NRIC/FIN/Passport No | E24: The System shall ensure important information is captured for processing the application which includes the following but not limited to: | F24: 2 | H24: 394
... A35: Enrolment | B35: Core | C35: 8.3.1 | D35: The System shall allow standard email templates where Course Administrators can activate a communication to applicants or communication email sent automatically. | E35: The System shall ensure important information is captured for processing the application which includes the following but not limited to: | F35: 2 | H35: 405
A36: Enrolment | B36: Core | C36: 8.3.2 | D36: The System shall ensure and lead corporate applicants to create a new user account first when they register for the course. | F36: 2 | H36: 406
A37: Enrolment | B37: Core | C37: 8.3.2 | D37: The System shall allow corporate registrants to log in with their existing user account if they already have one. | E37: The System shall ensure and lead corporate applicants to create a new user account first when they register for the course. | F37: 2 | H37: 407
A38: Enrolment | B38: Core | C38: 8.3.3 | D38: For company sponsored registrations, the System shall do an automatic check on the UEN number entered by applicant. | F38: 2 | H38: 408
A39: Enrolment | B39: Core | C39: 8.3.4 | D39: The System shall populate corporate applicant’s company information from user account to registration form and consent to the PDPA and privacy statement on the course registration form. | F39: 2 | H39: 409
A40: Enrolment | B40: Core | C40: 8.3.5 | D40: The System shall allow both mandatory and optional fields in the registration form and have a mechanism for corporate applicants to save the application, if not completed in stipulated time or Learners need to revisit later. | F40: 2 | H40: 410
A41: Enrolment | B41: Core | C41: 8.3.6 | D41: The System shall have a mechanism to track incomplete registration forms and alert Course Administrators. The System shall allow them to run reports for monitoring. | F41: 2 | H41: 411
A42: Enrolment | B42: Core | C42: 8.3.7 | D42: The System shall allow registration at both course and programme level. | F42: 2 | H42: 412
A43: Enrolment | B43: Core | C43: 8.3.8 | D43: The System shall allow uploading of supporting documents for registration and automated checking for the list of required documents to be submitted. | F43: 2 | H43: 413
A44: Enrolment | B44: Core | C44: 8.3.9 | D44: The System shall allow bulk registrations by uploading learner information in Excel file and have a mechanism to upload all supporting documents. | F44: 2 | H44: 414
A45: Enrolment | B45: Core | C45: 8.3.10 | D45: For company sponsored registrations, the System shall do an automatic check on the UEN number entered by corporate applicant. | F45: 2 | H45: 415
A46: Enrolment | B46: Core | C46: 8.3.11 | D46: The System shall capture all information in structured fields for downstream processing of activities and avoid re-entering data. | F46: 2 | H46: 416
A47: Enrolment | B47: Core | C47: 8.3.13 | D47: The System shall allow supporting documents for registrations to be uploaded and automated checking for list of required documents to be submitted. | F47: 2 | H47: 418
A48: Enrolment | B48: Supporting | C48: 8.4.1 | D48: The System shall allow settings for applicants to submit pre-assessment requirements for different shortlisting criteria assessment process (Same to be applicable for FlexiMasters and SkillsFuture Career Transition Programmes that require shortlisting). | F48: 2 | H48: 420
A49: Enrolment | B49: Supporting | C49: 8.4.2 | D49: The System shall allow automated sending of list/survey for pre-assessment requirements to the applicants upon their application | F49: 2 | H49: 421
A50: Enrolment | B50: Supporting | C50: 8.4.3 | D50: The System shall support scheduling of assessment and interview between shortlisted applicants and Training provider staff/faculty for in-person/online interviews. | F50: 2 | H50: 422
A51: Enrolment | B51: Supporting | C51: 8.4.3 | D51: The System shall have the capability to send automatic communication to applicants for scheduling interviews and confirmation on application. | E51: The System shall support scheduling of assessment and interview between shortlisted applicants and Training provider staff/faculty for in-person/online intervie | F51: 2 | H51: 423
A52: Enrolment | B52: Core | C52: 8.5.1 | D52: The System shall have the capability based on capacity-based auto confirmation and on first-come-first-serve basis. | F52: 2 | G52: 5 Seat confirm or waitlist | H52: 425
A53: Enrolment | B53: Core | C53: 8.5.2 | D53: The System shall have an automated process to auto register and enroll those who are in the parent course into its individual multiple courses for courses that have bitesized courses. | F53: 2 | H53: 426
A54: Enrolment | B54: Core | C54: 8.5.3 | D54: The System shall allow the capability to automatically put Learners on a waitlist if the class is full and notify candidates when seats are available and channel them to another course. | F54: 2 | G54: 5 Seat confirm or waitlist | H54: 427
A55: Enrolment | B55: Core | C55: 8.5.4 | D55: The System shall support course offer management where letter of offer is customizable for various courses by respective Schools. | F55: 2 | H55: 428
A56: Enrolment | B56: Core | C56: 8.5.5 | D56: The System shall include the capability to configure and set up enrolment restriction based on criteria including but not limited to: | F56: 2 | G56: 3 Prerequisite and restriction check | H56: 429
A57: Enrolment | B57: Core | C57: 8.5.5 | D57: 1) Age; | E57: The System shall include the capability to configure and set up enrolment restriction based on criteria including but not limited to: | F57: 2 | G57: 3 Prerequisite and restriction check | H57: 430
A58: Enrolment | B58: Core | C58: 8.5.5 | D58: 2) Course/Assessment Prerequisites; | E58: The System shall include the capability to configure and set up enrolment restriction based on criteria including but not limited to: | F58: 2 | G58: 3 Prerequisite and restriction check | H58: 431
A59: Enrolment | B59: Core | C59: 8.5.5 | D59: 3) Penalty; | E59: The System shall include the capability to configure and set up enrolment restriction based on criteria including but not limited to: | F59: 2 | G59: 3 Prerequisite and restriction check | H59: 432
A60: Enrolment | B60: Core | C60: 8.5.5 | D60: 4) Capacity of course/assessment. | E60: The System shall include the capability to configure and set up enrolment restriction based on criteria including but not limited to: | F60: 2 | G60: 3 Prerequisite and restriction check | H60: 433
A61: Enrolment | B61: Core | C61: 8.5.6 | D61: The System shall allow Course Administrator to perform ad-hoc enrolment for selfsponsored or corporate sponsored Learners for exception cases. | F61: 2 | H61: 434
A62: Enrolment | B62: Core | C62: 8.5.7 | D62: The System shall have the capability to set a limit of waitlist slots and automatically close registration for the course when waitlist is full. | F62: 2 | G62: 5 Seat confirm or waitlist | H62: 435
A63: Enrolment | B63: Core | C63: 8.5.8 | D63: The System shall have the capability for Learners to withdraw, send replacement or transfer to another training schedule with remark field to capture the reason, within specified period of time. | F63: 2 | H63: 436
A64: Enrolment | B64: Core | C64: 8.5.8 | D64: The System shall have the capability to automatically include Learners’ particulars who have been transferred to another training schedule or course. | E64: The System shall have the capability for Learners to withdraw, send replacement or transfer to another training schedule with remark field to capture the reason | F64: 2 | H64: 437
A65: Enrolment | B65: Core | C65: 8.5.9 | D65: The System shall have the capability to assign to different classes or assessment for Learners who choose to withdraw or re-schedule course or assessment, subject to approval. | F65: 2 | H65: 438
A66: Enrolment | B66: Core | C66: 8.5.10 | D66: The System shall have the capability for Learners to defer courses and assessments subject to approval by the authorizing department and track them accordingly. | F66: 2 | H66: 439
A67: Enrolment | B67: Core | C67: 8.5.16 | D67: The System shall have the capability to automatically interface Enrolments to Training Partners Gateway (TPGateway). | F67: 2 | H67: 459
A68: Enrolment | B68: Supporting | C68: 18.1.2 | D68: 4) Enrolment integration | E68: The System shall provide seamless integration with SSG systems / TG Gateway at the various integration points but not limited to the following processes: | F68: 1,2,3 | H68: 952
A69: ="ASSESSMENT MODULE: "&COUNTIF($A$70:$A$71,"Assessment")&" Tender rows" -> ASSESSMENT MODULE: 2 Tender rows
A70: Assessment | B70: Supporting | C70: 18.1.2 | D70: 5) eAttendance integration | E70: The System shall provide seamless integration with SSG systems / TG Gateway at the various integration points but not limited to the following processes: | F70: 1,2,3 | H70: 953
A71: Assessment | B71: Supporting | C71: 18.1.2 | D71: 6) Assessment integration | E71: The System shall provide seamless integration with SSG systems / TG Gateway at the various integration points but not limited to the following processes: | F71: 1,2,3 | H71: 954
A72: ="FUNDING MODULE: "&COUNTIF($A$73:$A$139,"Funding")&" Tender rows" -> FUNDING MODULE: 67 Tender rows
A73: Funding | B73: Core | C73: 6.3.3 | D73: 1) Withdrawals | E73: The System shall allow fee changes and approval in cases including but not limited to: | F73: 2 | H73: 225
A74: Funding | B74: Core | C74: 6.3.3 | D74: 2) Leave of Absence (LOA) | E74: The System shall allow fee changes and approval in cases including but not limited to: | F74: 2 | H74: 226
A75: Funding | B75: Core | C75: 6.3.3 | D75: 3) Deferrals | E75: The System shall allow fee changes and approval in cases including but not limited to: | F75: 2 | H75: 227
A76: Funding | B76: Core | C76: 6.3.3 | D76: 4) Termination | E76: The System shall allow fee changes and approval in cases including but not limited to: | F76: 2 | H76: 228
A77: Funding | B77: Core | C77: 6.3.4 | D77: The System shall allow different payment processes for: 1) Applicant Payments, 2) Sponsor Payments. | F77: 2 | H77: 229
A78: Funding | B78: Core | C78: 6.3.6 | D78: 6) Company SME status | E78: The System shall have the capability to generate fees payable with automatic calculation based on criteria including but not limited to: | F78: 2 | H78: 239
A79: Funding | B79: Core | C79: 6.3.7 | D79: The System shall have the capability to setup various course fee structures and associated administration fee, volume discount, material fee, reassessment fee, registration fee, course exemption fee, etc including but not limited to: 1) Installment payments; 2) Late payments. The system shall have the checker and approver of the setups to abide to audit requirements for check and balance. | F79: 2 | H79: 241
A80: Funding | B80: Core | C80: 6.4.2 | D80: 1) Special discount, e.g. staff, alumni, Singapore citizens, etc | E80: The System shall allow the Course Administrators to configure various types of discounts with complex and multi-tier hierarchical business rules and eligibility | F80: 2 | H80: 245
A81: Funding | B81: Core | C81: 6.4.2 | D81: 2) Promotional discount, e.g. early-bird discount, eVouchers, etc | E81: The System shall allow the Course Administrators to configure various types of discounts with complex and multi-tier hierarchical business rules and eligibility | F81: 2 | H81: 246
A82: Funding | B82: Core | C82: 6.4.2 | D82: System shall keep track of grant utilization and discounts by Schools, school, and course types. | E82: The System shall allow the Course Administrators to configure various types of discounts with complex and multi-tier hierarchical business rules and eligibility | F82: 2 | H82: 249
A83: Funding | B83: Core | C83: 6.4.3 | D83: The System shall allow automation for application of grant, subsidies, SFC, SFC (mid-career) top up, ETSS, credits, discounts, PSEA, Alumni Course Credit (ACC), and Additional Funding Support (AFS applicable for SkillsFuture Career Transition Programme) for fee calculation. | F83: 2 | G83: 4 Grant eligibility and fee | H83: 250
A84: Funding | B84: Core | C84: 6.4.4 | D84: The System shall support automated outcome based SkillsFuture Singapore (SSG) funding based on the following requirements: | F84: 2 | G84: 7 Outcome based funding | H84: 252
A85: Funding | B85: Core | C85: 6.4.4 | D85: 1) Minimum 75% attendance | E85: The System shall support automated outcome based SkillsFuture Singapore (SSG) funding based on the following requirements: | F85: 2 | G85: 7 Outcome based funding | H85: 253
A86: Funding | B86: Core | C86: 6.4.4 | D86: 2) Passing the assessment | E86: The System shall support automated outcome based SkillsFuture Singapore (SSG) funding based on the following requirements: | F86: 2 | G86: 7 Outcome based funding | H86: 254
A87: Funding | B87: Core | C87: 6.4.5 | D87: The System shall support the integration with Training Partners Gateway’s (TPGateway) Financial Management System for automated drawing down of block grants for completed courses. | F87: 2 | H87: 255
A88: Funding | B88: Core | C88: 6.4.6 | D88: The System shall allow the option to apply a discretionary discount by percentage or a flat rate with automated calculation of fees after applying the discount. The System shall facilitate the refunds of fees with necessary approvals. | F88: 1,2 | H88: 256
A89: Funding | B89: Core | C89: 6.4.8 | D89: The System shall allow inputs of the Vendor@Gov Business Unit reference and Government Electronic Business (GeBIZ) purchase order number for the Small and Medium-sized Enterprises (SME) to record their status as SME status to be entitled for Enhanced Training Support for SMEs (ETSS) funding from SkillsFuture Singapore (SSG). | F89: 2 | H89: 259
